Workbook

Sheet SharePoint Export
A1: Nr | B1: Customer | C1: Project document library | D1: Legal entity | E1: Industry | F1: Project status | G1: Started at | H1: Closed at | I1: PM | J1: PP | K1: PA | L1: Services | M1: Financing type | N1: Quotation Number | O1: CapEx | P1: IPS fees | Q1: Project start year | R1: Project close year | S1: Reference Sheet link | T1: ID | U1: Teams Site | V1: Item Type | W1: Path | X1: Project Status Check | Y1: PM Check | Z1: Pilot Check | AA1: Exclude | AB1: Project Status Align | AC1: PM Align | AD1: Pilot Align
A2: O3581 | B2: GOPA | C2: EM4897_BESS Project | D2: IAPS Tunisia | E2: Chemicals | F2: Work in progress | G2: 46098.042 | I2: Wissem Bensaid | J2: Wissem Bensaid | L2: Project Management;#1;#Engineering;#7;#HVAC Engineering;#14;#Utilities Engineering;#19 | M2: Lump sum | N2: Q9253 | O2: 0 | P2: 172000 | Q2: 2026 | T2: 2963 | U2: O3581 GOPA EM4897_BESS Project | V2: Item | W2: sites/Activity/Lists/GroupIPSProjects | X2: =VLOOKUP(Table_query__64[[#This Row],[Nr]],'MyTracker Export'!A:P,'MyTracker Export'!$P$1,FALSE) -> Work in progress | Y2: =VLOOKUP(Table_query__64[[#This Row],[Nr]],'MyTracker Export'!A:Z,'MyTracker Export'!$Z$1,FALSE) -> Istabrak Frikha | Z2: =VLOOKUP(Table_query__64[[#This Row],[Nr]],'MyTracker Export'!A:AA,'MyTracker Export'!$AA$1,FALSE) -> Wissem Bensaid | AB2: =IF(Table_query__64[[#This Row],[Project status]]=Table_query__64[[#This Row],[Project Status Check]],"OK","NOK") -> OK | AC2: =IF(Table_query__64[[#This Row],[PM]]=Table_query__64[[#This Row],[PM Check]],"OK","NOK") -> NOK | AD2: =IF(Table_query__64[[#This Row],[PP]]=Table_query__64[[#This Row],[Pilot Check]],"OK","NOK") -> OK
A3: O3580 | B3: Cargill Chocolate Belgium NV (Mouscron) | C3: P&ID Update Nuts connection | D3: IPS Belgium | E3: Food & Beverages | F3: Work in progress | G3: 46098.042 | I3: Audric Jeanne | J3: Karel De Swert | L3: Project Management;#1;#Engineering;#7 | M3: Lump sum | N3: Q9213 | O3: 10000 | P3: 828.09 | Q3: 2026 | T3: 2962 | U3: O3580 Cargill P&ID Update Nuts connection | V3: Item | W3: sites/Activity/Lists/GroupIPSProjects | X3: =VLOOKUP(Table_query__64[[#This Row],[Nr]],'MyTracker Export'!A:P,'MyTracker Export'!$P$1,FALSE) -> Work in progress | Y3: =VLOOKUP(Table_query__64[[#This Row],[Nr]],'MyTracker Export'!A:Z,'MyTracker Export'!$Z$1,FALSE) -> Audric Jeanne | Z3: =VLOOKUP(Table_query__64[[#This Row],[Nr]],'MyTracker Export'!A:AA,'MyTracker Export'!$AA$1,FALSE) -> Karel De Swert | AB3: =IF(Table_query__64[[#This Row],[Project status]]=Table_query__64[[#This Row],[Project Status Check]],"OK","NOK") -> OK | AC3: =IF(Table_query__64[[#This Row],[PM]]=Table_query__64[[#This Row],[PM Check]],"OK","NOK") -> OK | AD3: =IF(Table_query__64[[#This Row],[PP]]=Table_query__64[[#This Row],[Pilot Check]],"OK","NOK") -> OK
A4: O3579 | B4: BLIP | C4: BLIP OFFICES | D4: Arquid | E4: Buildings | F4: Work in progress | G4: 46097.042 | I4: Laura Cestau | J4: Laura Cestau | L4: Project Management;#1;#Architecture;#5 | M4: Lump sum | N4: Q9076 | O4: 20 | P4: 33957 | Q4: 2026 | T4: 2961 | U4: O3579 BLIP BLIP OFFICES | V4: Item | W4: sites/Activity/Lists/GroupIPSProjects | X4: =VLOOKUP(Table_query__64[[#This Row],[Nr]],'MyTracker Export'!A:P,'MyTracker Export'!$P$1,FALSE) -> Work in progress | Y4: =VLOOKUP(Table_query__64[[#This Row],[Nr]],'MyTracker Export'!A:Z,'MyTracker Export'!$Z$1,FALSE) -> Laura Cestau | Z4: =VLOOKUP(Table_query__64[[#This Row],[Nr]],'MyTracker Export'!A:AA,'MyTracker Export'!$AA$1,FALSE) -> Laura Cestau | AB4: =IF(Table_query__64[[#This Row],[Project status]]=Table_query__64[[#This Row],[Project Status Check]],"OK","NOK") -> OK | AC4: =IF(Table_query__64[[#This Row],[PM]]=Table_query__64[[#This Row],[PM Check]],"OK","NOK") -> OK | AD4: =IF(Table_query__64[[#This Row],[PP]]=Table_query__64[[#This Row],[Pilot Check]],"OK","NOK") -> OK
A5: O3578 | B5: TPS | C5: EM4549_Guebiba water | D5: IAPS Tunisia | E5: Chemicals | F5: Work in progress | G5: 46093.042 | I5: Wissem Bensaid | J5: Wissem Bensaid | L5: Project Management;#1;#Engineering;#7;#Mechanical Engineering;#15;#Piping Engineering;#16;#Process Engineering;#17 | M5: Lump sum | N5: Q9247 | O5: 0 | P5: 88827.9 | Q5: 2026 | T5: 2960 | U5: O3578 TPS EM4549_Guebiba water | V5: Item | W5: sites/Activity/Lists/GroupIPSProjects | X5: =VLOOKUP(Table_query__64[[#This Row],[Nr]],'MyTracker Export'!A:P,'MyTracker Export'!$P$1,FALSE) -> Work in progress | Y5: =VLOOKUP(Table_query__64[[#This Row],[Nr]],'MyTracker Export'!A:Z,'MyTracker Export'!$Z$1,FALSE) -> Anouar Trigui | Z5: =VLOOKUP(Table_query__64[[#This Row],[Nr]],'MyTracker Export'!A:AA,'MyTracker Export'!$AA$1,FALSE) -> Wissem Bensaid | AB5: =IF(Table_query__64[[#This Row],[Project status]]=Table_query__64[[#This Row],[Project Status Check]],"OK","NOK") -> OK | AC5: =IF(Table_query__64[[#This Row],[PM]]=Table_query__64[[#This Row],[PM Check]],"OK","NOK") -> NOK | AD5: =IF(Table_query__64[[#This Row],[PP]]=Table_query__64[[#This Row],[Pilot Check]],"OK","NOK") -> OK
A6: O3577 | B6: Ab InBev EU HQ (BEL Leuven) | C6: Magor Land Conversion | D6: Group-IPS | E6: Food & Beverages | F6: Work in progress | G6: 46093.042 | I6: Natalia Martínez Nieto | J6: Natalia Martínez Nieto | L6: Architecture;#5 | M6: Lump sum | N6: Q9240 | O6: 0 | P6: 4492.65 | Q6: 2026 | T6: 2959 | U6: O3577 Ab InBev Magor Land Conversion | V6: Item | W6: sites/Activity/Lists/GroupIPSProjects | X6: =VLOOKUP(Table_query__64[[#This Row],[Nr]],'MyTracker Export'!A:P,'MyTracker Export'!$P$1,FALSE) -> Work in progress | Y6: =VLOOKUP(Table_query__64[[#This Row],[Nr]],'MyTracker Export'!A:Z,'MyTracker Export'!$Z$1,FALSE) -> Natalia Martínez Nieto | Z6: =VLOOKUP(Table_query__64[[#This Row],[Nr]],'MyTracker Export'!A:AA,'MyTracker Export'!$AA$1,FALSE) -> Natalia Martínez Nieto | AB6: =IF(Table_query__64[[#This Row],[Project status]]=Table_query__64[[#This Row],[Project Status Check]],"OK","NOK") -> OK | AC6: =IF(Table_query__64[[#This Row],[PM]]=Table_query__64[[#This Row],[PM Check]],"OK","NOK") -> OK | AD6: =IF(Table_query__64[[#This Row],[PP]]=Table_query__64[[#This Row],[Pilot Check]],"OK","NOK") -> OK
A7: O3576 | B7: Affinity Factory Italy | C7: Affinity Petcare CGM_STB | D7: IPS Spain | E7: Food & Beverages | F7: Work in progress | G7: 46090.042 | I7: Maria Bonaccio | J7: Maria Bonaccio | L7: Project Management;#1 | M7: Reimbursable | N7: Q9151 | O7: 500000 | P7: 155932.13 | Q7: 2026 | T7: 2958 | U7: O3576 Affinity Factory Italy Affinity Petcare CGM_STB | V7: Item | W7: sites/Activity/Lists/GroupIPSProjects | X7: =VLOOKUP(Table_query__64[[#This Row],[Nr]],'MyTracker Export'!A:P,'MyTracker Export'!$P$1,FALSE) -> Work in progress | Y7: =VLOOKUP(Table_query__64[[#This Row],[Nr]],'MyTracker Export'!A:Z,'MyTracker Export'!$Z$1,FALSE) -> Maria Bonaccio | Z7: =VLOOKUP(Table_query__64[[#This Row],[Nr]],'MyTracker Export'!A:AA,'MyTracker Export'!$AA$1,FALSE) -> Maria Bonaccio | AB7: =IF(Table_query__64[[#This Row],[Project status]]=Table_query__64[[#This Row],[Project Status Check]],"OK","NOK") -> OK | AC7: =IF(Table_query__64[[#This Row],[PM]]=Table_query__64[[#This Row],[PM Check]],"OK","NOK") -> OK | AD7: =IF(Table_query__64[[#This Row],[PP]]=Table_query__64[[#This Row],[Pilot Check]],"OK","NOK") -> OK
A8: O3575 | B8: Albioma | C8: Logistics / Customs | D8: IPS France | E8: Chemicals | F8: Work in progress | G8: 46090.042 | I8: Maria Romero | J8: Josué Silverio | K8: Salma Gueblaoui | L8: Consulting;#2;#Masterplan;#66 | M8: Reimbursable | N8: Q9118 | O8: 350 | P8: 15876 | Q8: 2026 | T8: 2956 | U8: O3575 Albioma Logistics Customs | V8: Item | W8: sites/Activity/Lists/GroupIPSProjects | X8: =VLOOKUP(Table_query__64[[#This Row],[Nr]],'MyTracker Export'!A:P,'MyTracker Export'!$P$1,FALSE) -> Work in progress | Y8: =VLOOKUP(Table_query__64[[#This Row],[Nr]],'MyTracker Export'!A:Z,'MyTracker Export'!$Z$1,FALSE) -> Maria Romero | Z8: =VLOOKUP(Table_query__64[[#This Row],[Nr]],'MyTracker Export'!A:AA,'MyTracker Export'!$AA$1,FALSE) -> Josué Silverio | AB8: =IF(Table_query__64[[#This Row],[Project status]]=Table_query__64[[#This Row],[Project Status Check]],"OK","NOK") -> OK | AC8: =IF(Table_query__64[[#This Row],[PM]]=Table_query__64[[#This Row],[PM Check]],"OK","NOK") -> OK | AD8: =IF(Table_query__64[[#This Row],[PP]]=Table_query__64[[#This Row],[Pilot Check]],"OK","NOK") -> OK
A9: O3574 | B9: InBev Belgium BV | C9: Leuven WH roof renovation | D9: IPS Belgium | E9: Food & Beverages | F9: Work in progress | G9: 46087.042 | I9: Valérie Codesido | J9: Lucas Soto Alonso | L9: Architecture;#5;#Engineering;#7;#Utilities Engineering;#19 | M9: Lump sum | N9: Q9236 | O9: 1.7 | P9: 25725.73 | Q9: 2026 | T9: 2955 | U9: O3574 InBev Belgium BV Leuven WH roof renovation | V9: Item | W9: sites/Activity/Lists/GroupIPSProjects | X9: =VLOOKUP(Table_query__64[[#This Row],[Nr]],'MyTracker Export'!A:P,'MyTracker Export'!$P$1,FALSE) -> Work in progress | Y9: =VLOOKUP(Table_query__64[[#This Row],[Nr]],'MyTracker Export'!A:Z,'MyTracker Export'!$Z$1,FALSE) -> Valérie Codesido | Z9: =VLOOKUP(Table_query__64[[#This Row],[Nr]],'MyTracker Export'!A:AA,'MyTracker Export'!$AA$1,FALSE) -> Lucas Soto | AB9: =IF(Table_query__64[[#This Row],[Project status]]=Table_query__64[[#This Row],[Project Status Check]],"OK","NOK") -> OK | AC9: =IF(Table_query__64[[#This Row],[PM]]=Table_query__64[[#This Row],[PM Check]],"OK","NOK") -> OK | AD9: =IF(Table_query__64[[#This Row],[PP]]=Table_query__64[[#This Row],[Pilot Check]],"OK","NOK") -> NOK
A10: O3573 | B10: GlaxoSmithKline Biologicals Rixensart | C10: GSK RX86 - BoD | D10: IPS Belgium | E10: Life Sciences | F10: Work in progress | G10: 46087 | I10: Mathias Martin | J10: Yves Debaisieux | K10: Céline Lechado | L10: Project Management;#1;#Engineering;#7;#Process Engineering;#17;#Utilities Engineering;#19;#Construction Management;#42;#Engineering Coordination;#54;#Project Assistance;#73;#Safety & Site Supervision;#78 | M10: Lump sum | N10: Q9070 | O10: 1 | P10: 123937 | Q10: 2026 | T10: 2954 | U10: O3573 GlaxoSmithKline GSK RX86 - BoD | V10: Item | W10: sites/Activity/Lists/GroupIPSProjects | X10: =VLOOKUP(Table_query__64[[#This Row],[Nr]],'MyTracker Export'!A:P,'MyTracker Export'!$P$1,FALSE) -> Work in progress | Y10: =VLOOKUP(Table_query__64[[#This Row],[Nr]],'MyTracker Export'!A:Z,'MyTracker Export'!$Z$1,FALSE) -> Mathias Martin | Z10: =VLOOKUP(Table_query__64[[#This Row],[Nr]],'MyTracker Export'!A:AA,'MyTracker Export'!$AA$1,FALSE) -> Yves Debaisieux | AB10: =IF(Table_query__64[[#This Row],[Project status]]=Table_query__64[[#This Row],[Project Status Check]],"OK","NOK") -> OK | AC10: =IF(Table_query__64[[#This Row],[PM]]=Table_query__64[[#This Row],[PM Check]],"OK","NOK") -> OK | AD10: =IF(Table_query__64[[#This Row],[PP]]=Table_query__64[[#This Row],[Pilot Check]],"OK","NOK") -> OK
A11: O3572 | B11: Tennant Solutions | C11: Facility Single Line Diagram | D11: IPS USA | E11: Primary & Metals | F11: Work in progress | G11: 46085.042 | I11: Pranay Pawar | J11: Pranay Pawar | L11: Engineering;#7 | M11: Lump sum | N11: Q9082 | O11: 0.01 | P11: 15454 | Q11: 2026 | T11: 2953 | U11: O3572 Tennant Solutions Facility Single Line Diagram | V11: Item | W11: sites/Activity/Lists/GroupIPSProjects | X11: =VLOOKUP(Table_query__64[[#This Row],[Nr]],'MyTracker Export'!A:P,'MyTracker Export'!$P$1,FALSE) -> Work in progress | Y11: =VLOOKUP(Table_query__64[[#This Row],[Nr]],'MyTracker Export'!A:Z,'MyTracker Export'!$Z$1,FALSE) -> Pranay Pawar | Z11: =VLOOKUP(Table_query__64[[#This Row],[Nr]],'MyTracker Export'!A:AA,'MyTracker Export'!$AA$1,FALSE) -> Pranay Pawar | AB11: =IF(Table_query__64[[#This Row],[Project status]]=Table_query__64[[#This Row],[Project Status Check]],"OK","NOK") -> OK | AC11: =IF(Table_query__64[[#This Row],[PM]]=Table_query__64[[#This Row],[PM Check]],"OK","NOK") -> OK | AD11: =IF(Table_query__64[[#This Row],[PP]]=Table_query__64[[#This Row],[Pilot Check]],"OK","NOK") -> OK
A12: O3571 | B12: Eberspaecher Bulgaria | C12: EBS_Plot EPCM services | D12: IPS Bulgaria | E12: Buildings | F12: Work in progress | G12: 46085.042 | I12: Nevena Banova | J12: Nevena Banova | L12: Project Management;#1;#Engineering;#7;#Construction Management;#42 | M12: Lump sum | N12: Q8653 | O12: 0 | P12: 4780 | Q12: 2026 | T12: 2952 | U12: O3571 Eberspaecher Bulgaria EBS_Plot EPCM services | V12: Item | W12: sites/Activity/Lists/GroupIPSProjects | X12: =VLOOKUP(Table_query__64[[#This Row],[Nr]],'MyTracker Export'!A:P,'MyTracker Export'!$P$1,FALSE) -> Work in progress | Y12: =VLOOKUP(Table_query__64[[#This Row],[Nr]],'MyTracker Export'!A:Z,'MyTracker Export'!$Z$1,FALSE) -> Nevena Banova | Z12: =VLOOKUP(Table_query__64[[#This Row],[Nr]],'MyTracker Export'!A:AA,'MyTracker Export'!$AA$1,FALSE) -> Nevena Banova | AB12: =IF(Table_query__64[[#This Row],[Project status]]=Table_query__64[[#This Row],[Project Status Check]],"OK","NOK") -> OK | AC12: =IF(Table_query__64[[#This Row],[PM]]=Table_query__64[[#This Row],[PM Check]],"OK","NOK") -> OK | AD12: =IF(Table_query__64[[#This Row],[PP]]=Table_query__64[[#This Row],[Pilot Check]],"OK","NOK") -> OK
A13: O3570 | B13: Ab InBev EU HQ (BEL Leuven) | C13: Highbay Extension Leuven | D13: IPS Belgium | E13: Food & Beverages | F13: Work in progress | G13: 46085.042 | I13: Karel De Swert | J13: Karel De Swert | L13: Project Management;#1;#Consulting;#2;#Architecture;#5;#Engineering;#7;#Masterplan;#66 | M13: Lump sum | N13: Q9176 | O13: 0 | P13: 25046.95 | Q13: 2026 | T13: 2951 | U13: O3570 Ab InBev Highbay Extension Leuven | V13: Item | W13: sites/Activity/Lists/GroupIPSProjects | X13: =VLOOKUP(Table_query__64[[#This Row],[Nr]],'MyTracker Export'!A:P,'MyTracker Export'!$P$1,FALSE) -> Work in progress | Y13: =VLOOKUP(Table_query__64[[#This Row],[Nr]],'MyTracker Export'!A:Z,'MyTracker Export'!$Z$1,FALSE) -> Karel De Swert | Z13: =VLOOKUP(Table_query__64[[#This Row],[Nr]],'MyTracker Export'!A:AA,'MyTracker Export'!$AA$1,FALSE) -> Karel De Swert | AB13: =IF(Table_query__64[[#This Row],[Project status]]=Table_query__64[[#This Row],[Project Status Check]],"OK","NOK") -> OK | AC13: =IF(Table_query__64[[#This Row],[PM]]=Table_query__64[[#This Row],[PM Check]],"OK","NOK") -> OK | AD13: =IF(Table_query__64[[#This Row],[PP]]=Table_query__64[[#This Row],[Pilot Check]],"OK","NOK") -> OK
A14: O3569 | B14: Fertinagro | C14: EM4817_Safi TSP Plant | D14: IAPS Tunisia | E14: Chemicals | F14: Work in progress | G14: 46085.042 | I14: Wissem Bensaid | J14: Wissem Bensaid | L14: Project Management;#1 | M14: Lump sum | N14: Q9223 | O14: 0 | P14: 264000 | Q14: 2026 | T14: 2950 | U14: O3569 Fertinagro EM4817_Safi TSP Plant | V14: Item | W14: sites/Activity/Lists/GroupIPSProjects | X14: =VLOOKUP(Table_query__64[[#This Row],[Nr]],'MyTracker Export'!A:P,'MyTracker Export'!$P$1,FALSE) -> Work in progress | Y14: =VLOOKUP(Table_query__64[[#This Row],[Nr]],'MyTracker Export'!A:Z,'MyTracker Export'!$Z$1,FALSE) -> Souhail WALI | Z14: =VLOOKUP(Table_query__64[[#This Row],[Nr]],'MyTracker Export'!A:AA,'MyTracker Export'!$AA$1,FALSE) -> Wissem Bensaid | AB14: =IF(Table_query__64[[#This Row],[Project status]]=Table_query__64[[#This Row],[Project Status Check]],"OK","NOK") -> OK | AC14: =IF(Table_query__64[[#This Row],[PM]]=Table_query__64[[#This Row],[PM Check]],"OK","NOK") -> NOK | AD14: =IF(Table_query__64[[#This Row],[PP]]=Table_query__64[[#This Row],[Pilot Check]],"OK","NOK") -> OK
A15: O3568 | B15: Servicoop Management SL | C15: Cooperativa de Vivienda | D15: Arquid | E15: Buildings | F15: Work in progress | G15: 46084.042 | I15: Jaime ÁLVAREZ PÉREZ | J15: Felipe Langa Hernáez | L15: Project Management;#1;#Architecture;#5;#Engineering;#7;#Utilities Engineering;#19 | M15: Lump sum | N15: Q9130 | O15: 5 | P15: 151188.6 | Q15: 2026 | T15: 2949 | U15: O3568 Servicoop Management SL Cooperativa de Vivienda | V15: Item | W15: sites/Activity/Lists/GroupIPSProjects | X15: =VLOOKUP(Table_query__64[[#This Row],[Nr]],'MyTracker Export'!A:P,'MyTracker Export'!$P$1,FALSE) -> Work in progress | Y15: =VLOOKUP(Table_query__64[[#This Row],[Nr]],'MyTracker Export'!A:Z,'MyTracker Export'!$Z$1,FALSE) -> Jaime Álvarez Pérez | Z15: =VLOOKUP(Table_query__64[[#This Row],[Nr]],'MyTracker Export'!A:AA,'MyTracker Export'!$AA$1,FALSE) -> Felipe Langa Hernáez | AB15: =IF(Table_query__64[[#This Row],[Project status]]=Table_query__64[[#This Row],[Project Status Check]],"OK","NOK") -> OK | AC15: =IF(Table_query__64[[#This Row],[PM]]=Table_query__64[[#This Row],[PM Check]],"OK","NOK") -> OK | AD15: =IF(Table_query__64[[#This Row],[PP]]=Table_query__64[[#This Row],[Pilot Check]],"OK","NOK") -> OK
A16: O3567 | B16: Fertinagro | C16: EM4723_Storage & Pipeline | D16: IAPS Tunisia | E16: Chemicals | F16: Work in progress | G16: 46084.042 | I16: Wissem Bensaid | J16: Wissem Bensaid | L16: Project Management;#1;#Engineering;#7;#Piping Engineering;#16;#Process Engineering;#17 | M16: Lump sum | N16: Q9220 | O16: 0 | P16: 66420 | Q16: 2026 | T16: 2948 | U16: O3567 Fertinagro EM4723_Storage & Pipeline | V16: Item | W16: sites/Activity/Lists/GroupIPSProjects | X16: =VLOOKUP(Table_query__64[[#This Row],[Nr]],'MyTracker Export'!A:P,'MyTracker Export'!$P$1,FALSE) -> Work in progress | Y16: =VLOOKUP(Table_query__64[[#This Row],[Nr]],'MyTracker Export'!A:Z,'MyTracker Export'!$Z$1,FALSE) -> Ali TRIGUI | Z16: =VLOOKUP(Table_query__64[[#This Row],[Nr]],'MyTracker Export'!A:AA,'MyTracker Export'!$AA$1,FALSE) -> Wissem Bensaid | AB16: =IF(Table_query__64[[#This Row],[Project status]]=Table_query__64[[#This Row],[Project Status Check]],"OK","NOK") -> OK | AC16: =IF(Table_query__64[[#This Row],[PM]]=Table_query__64[[#This Row],[PM Check]],"OK","NOK") -> NOK | AD16: =IF(Table_query__64[[#This Row],[PP]]=Table_query__64[[#This Row],[Pilot Check]],"OK","NOK") -> OK
A17: O3566 | B17: WiTTE Automotive | C17: Witte Bg _PlantExtension | D17: IPS Bulgaria | E17: Other industry | F17: Work in progress | G17: 46083.042 | I17: Nevena Banova | J17: Nevena Banova | L17: Project Management;#1 | M17: Reimbursable | N17: Q8870 | O17: 0 | P17: 7845.8 | Q17: 2026 | T17: 2947 | U17: O3566 WiTTE Automotive Witte Bg _PlantExtension | V17: Item | W17: sites/Activity/Lists/GroupIPSProjects | X17: =VLOOKUP(Table_query__64[[#This Row],[Nr]],'MyTracker Export'!A:P,'MyTracker Export'!$P$1,FALSE) -> Work in progress | Y17: =VLOOKUP(Table_query__64[[#This Row],[Nr]],'MyTracker Export'!A:Z,'MyTracker Export'!$Z$1,FALSE) -> Nevena Banova | Z17: =VLOOKUP(Table_query__64[[#This Row],[Nr]],'MyTracker Export'!A:AA,'MyTracker Export'!$AA$1,FALSE) -> Nevena Banova | AB17: =IF(Table_query__64[[#This Row],[Project status]]=Table_query__64[[#This Row],[Project Status Check]],"OK","NOK") -> OK | AC17: =IF(Table_query__64[[#This Row],[PM]]=Table_query__64[[#This Row],[PM Check]],"OK","NOK") -> OK | AD17: =IF(Table_query__64[[#This Row],[PP]]=Table_query__64[[#This Row],[Pilot Check]],"OK","NOK") -> OK
A18: O3565 | B18: WiTTE Automotive | C18: Witte Bg _PlantExtension | D18: IPS Bulgaria | E18: Other industry | F18: Work in progress | G18: 46083.042 | I18: Nevena Banova | J18: Nevena Banova | L18: Project Management;#1;#Project Assistance;#73 | M18: Reimbursable | N18: Q8740 | O18: 0 | P18: 13238.4 | Q18: 2026 | T18: 2946 | U18: O3565 WiTTE Automotive Witte Bg _PlantExtension | V18: Item | W18: sites/Activity/Lists/GroupIPSProjects | X18: =VLOOKUP(Table_query__64[[#This Row],[Nr]],'MyTracker Export'!A:P,'MyTracker Export'!$P$1,FALSE) -> Work in progress | Y18: =VLOOKUP(Table_query__64[[#This Row],[Nr]],'MyTracker Export'!A:Z,'MyTracker Export'!$Z$1,FALSE) -> Nevena Banova | Z18: =VLOOKUP(Table_query__64[[#This Row],[Nr]],'MyTracker Export'!A:AA,'MyTracker Export'!$AA$1,FALSE) -> Nevena Banova | AB18: =IF(Table_query__64[[#This Row],[Project status]]=Table_query__64[[#This Row],[Project Status Check]],"OK","NOK") -> OK | AC18: =IF(Table_query__64[[#This Row],[PM]]=Table_query__64[[#This Row],[PM Check]],"OK","NOK") -> OK | AD18: =IF(Table_query__64[[#This Row],[PP]]=Table_query__64[[#This Row],[Pilot Check]],"OK","NOK") -> OK
A19: O3564 | B19: Mondelez GmbH Lörrach | C19: HSE Standards | D19: Group-IPS | E19: Food & Beverages | F19: Work in progress | G19: 46080.042 | I19: Jan Beske | J19: Yannick Vega | L19: Project Management;#1 | M19: Reimbursable | N19: Q9147 | O19: 1 | P19: 116002 | Q19: 2026 | T19: 2945 | U19: O3564 Mondelez GmbH Lörrach HSE Standards | V19: Item | W19: sites/Activity/Lists/GroupIPSProjects | X19: =VLOOKUP(Table_query__64[[#This Row],[Nr]],'MyTracker Export'!A:P,'MyTracker Export'!$P$1,FALSE) -> Work in progress | Y19: =VLOOKUP(Table_query__64[[#This Row],[Nr]],'MyTracker Export'!A:Z,'MyTracker Export'!$Z$1,FALSE) -> Jan Beske | Z19: =VLOOKUP(Table_query__64[[#This Row],[Nr]],'MyTracker Export'!A:AA,'MyTracker Export'!$AA$1,FALSE) -> Yannick Vega Fernandez | AB19: =IF(Table_query__64[[#This Row],[Project status]]=Table_query__64[[#This Row],[Project Status Check]],"OK","NOK") -> OK | AC19: =IF(Table_query__64[[#This Row],[PM]]=Table_query__64[[#This Row],[PM Check]],"OK","NOK") -> OK | AD19: =IF(Table_query__64[[#This Row],[PP]]=Table_query__64[[#This Row],[Pilot Check]],"OK","NOK") -> NOK
A20: O3563 | B20: Evonik Antwerpen N.V. | C20: FK_D763 Str eng concr. floor | D20: IPS Belgium | E20: Chemicals | F20: Work in progress | G20: 46080.042 | I20: Charlélie Michel | J20: Peter Holvoet | K20: Sophie Saussu | L20: Project Management;#1;#Engineering;#7 | M20: Reimbursable | N20: Q9119 | O20: 0.3 | P20: 15742.35 | Q20: 2026 | T20: 2944 | U20: O3563 Evonik Antwerpen N.V. FK_D763 Str eng concr. floor | V20: Item | W20: sites/Activity/Lists/GroupIPSProjects | X20: =VLOOKUP(Table_query__64[[#This Row],[Nr]],'MyTracker Export'!A:P,'MyTracker Export'!$P$1,FALSE) -> Work in progress | Y20: =VLOOKUP(Table_query__64[[#This Row],[Nr]],'MyTracker Export'!A:Z,'MyTracker Export'!$Z$1,FALSE) -> Charlélie Michel | Z20: =VLOOKUP(Table_query__64[[#This Row],[Nr]],'MyTracker Export'!A:AA,'MyTracker Export'!$AA$1,FALSE) -> Peter Holvoet | AB20: =IF(Table_query__64[[#This Row],[Project status]]=Table_query__64[[#This Row],[Project Status Check]],"OK","NOK") -> OK | AC20: =IF(Table_query__64[[#This Row],[PM]]=Table_query__64[[#This Row],[PM Check]],"OK","NOK") -> OK | AD20: =IF(Table_query__64[[#This Row],[PP]]=Table_query__64[[#This Row],[Pilot Check]],"OK","NOK") -> OK
A21: O3562 | B21: Connecting visions | C21: Industrial Laundry BILBAO | D21: IPS Spain | E21: Other industry | F21: Work in progress | G21: 46078.042 | I21: Maria Romero | J21: Miguel Menéndez | L21: Consulting;#2 | M21: Lump sum | N21: Q9180 | O21: 1 | P21: 8694 | Q21: 2026 | T21: 2943 | U21: O3562 Connecting visions Industrial Laundry BILBAO | V21: Item | W21: sites/Activity/Lists/GroupIPSProjects | X21: =VLOOKUP(Table_query__64[[#This Row],[Nr]],'MyTracker Export'!A:P,'MyTracker Export'!$P$1,FALSE) -> Work in progress | Y21: =VLOOKUP(Table_query__64[[#This Row],[Nr]],'MyTracker Export'!A:Z,'MyTracker Export'!$Z$1,FALSE) -> Maria Romero | Z21: =VLOOKUP(Table_query__64[[#This Row],[Nr]],'MyTracker Export'!A:AA,'MyTracker Export'!$AA$1,FALSE) -> Miguel Menéndez | AB21: =IF(Table_query__64[[#This Row],[Project status]]=Table_query__64[[#This Row],[Project Status Check]],"OK","NOK") -> OK | AC21: =IF(Table_query__64[[#This Row],[PM]]=Table_query__64[[#This Row],[PM Check]],"OK","NOK") -> OK | AD21: =IF(Table_query__64[[#This Row],[PP]]=Table_query__64[[#This Row],[Pilot Check]],"OK","NOK") -> OK
A22: O3561 | B22: Affinity Factory _ Spain | C22: VSU Sistema 7 | D22: IPS Spain | E22: Food & Beverages | F22: Finished | G22: 46078.042 | H22: 46078.042 | I22: Maria Bonaccio | J22: Maria Bonaccio | L22: Project Management;#1 | M22: Reimbursable | N22: Q9059 | O22: 0 | P22: 0 | Q22: 2026 | R22: 2026 | T22: 2942 | U22: O3561 Affinity Factory _ Spain VSU Sistema 7 | V22: Item | W22: sites/Activity/Lists/GroupIPSProjects | X22: =VLOOKUP(Table_query__64[[#This Row],[Nr]],'MyTracker Export'!A:P,'MyTracker Export'!$P$1,FALSE) -> Finished | Y22: =VLOOKUP(Table_query__64[[#This Row],[Nr]],'MyTracker Export'!A:Z,'MyTracker Export'!$Z$1,FALSE) -> Maria Bonaccio | Z22: =VLOOKUP(Table_query__64[[#This Row],[Nr]],'MyTracker Export'!A:AA,'MyTracker Export'!$AA$1,FALSE) -> Maria Bonaccio | AB22: =IF(Table_query__64[[#This Row],[Project status]]=Table_query__64[[#This Row],[Project Status Check]],"OK","NOK") -> OK | AC22: =IF(Table_query__64[[#This Row],[PM]]=Table_query__64[[#This Row],[PM Check]],"OK","NOK") -> OK | AD22: =IF(Table_query__64[[#This Row],[PP]]=Table_query__64[[#This Row],[Pilot Check]],"OK","NOK") -> OK
A23: O3560 | B23: ARCADE | C23: ARCADE 2026 | D23: Arquid | E23: Other industry | F23: Work in progress | G23: 46077.042 | I23: Rubén Gutiérrez Llamas | J23: Felipe Langa Hernáez | L23: Architecture;#5 | M23: Lump sum | N23: Q9211 | O23: 0 | P23: 0 | Q23: 2026 | T23: 2941 | U23: O3560 ARCADE ARCADE 2026 | V23: Item | W23: sites/Activity/Lists/GroupIPSProjects | X23: =VLOOKUP(Table_query__64[[#This Row],[Nr]],'MyTracker Export'!A:P,'MyTracker Export'!$P$1,FALSE) -> Work in progress | Y23: =VLOOKUP(Table_query__64[[#This Row],[Nr]],'MyTracker Export'!A:Z,'MyTracker Export'!$Z$1,FALSE) -> Rubén Gutiérrez Llamas | Z23: =VLOOKUP(Table_query__64[[#This Row],[Nr]],'MyTracker Export'!A:AA,'MyTracker Export'!$AA$1,FALSE) -> Felipe Langa Hernáez | AB23: =IF(Table_query__64[[#This Row],[Project status]]=Table_query__64[[#This Row],[Project Status Check]],"OK","NOK") -> OK | AC23: =IF(Table_query__64[[#This Row],[PM]]=Table_query__64[[#This Row],[PM Check]],"OK","NOK") -> OK | AD23: =IF(Table_query__64[[#This Row],[PP]]=Table_query__64[[#This Row],[Pilot Check]],"OK","NOK") -> OK
A24: O3559 | B24: MARETAP | C24: EM4930_Etd remplac séparateur | D24: IAPS Tunisia | E24: Chemicals | F24: Work in progress | G24: 46073.042 | I24: Wissem Bensaid | J24: Wissem Bensaid | L24: Project Management;#1;#Engineering;#7;#Mechanical Engineering;#15;#Piping Engineering;#16;#Process Engineering;#17 | M24: Lump sum | N24: Q9205 | O24: 0 | P24: 25000 | Q24: 2026 | T24: 2940 | U24: O3559 MARETAP EM4930_Etd remplac séparateur | V24: Item | W24: sites/Activity/Lists/GroupIPSProjects | X24: =VLOOKUP(Table_query__64[[#This Row],[Nr]],'MyTracker Export'!A:P,'MyTracker Export'!$P$1,FALSE) -> Work in progress | Y24: =VLOOKUP(Table_query__64[[#This Row],[Nr]],'MyTracker Export'!A:Z,'MyTracker Export'!$Z$1,FALSE) -> Taha Elghith | Z24: =VLOOKUP(Table_query__64[[#This Row],[Nr]],'MyTracker Export'!A:AA,'MyTracker Export'!$AA$1,FALSE) -> Wissem Bensaid | AB24: =IF(Table_query__64[[#This Row],[Project status]]=Table_query__64[[#This Row],[Project Status Check]],"OK","NOK") -> OK | AC24: =IF(Table_query__64[[#This Row],[PM]]=Table_query__64[[#This Row],[PM Check]],"OK","NOK") -> NOK | AD24: =IF(Table_query__64[[#This Row],[PP]]=Table_query__64[[#This Row],[Pilot Check]],"OK","NOK") -> OK
A25: O3558 | B25: Ineos Feluy SA | C25: MS project planning TAR | D25: IPS Belgium | E25: Chemicals | F25: Work in progress | G25: 46072.042 | I25: Niels Van Osselaer | J25: Peter Holvoet | K25: Julie Pollet | L25: Project Management;#1;#Project Assistance;#73 | M25: Reimbursable | N25: Q9165 | O25: 0.5 | P25: 15088.37 | Q25: 2026 | T25: 2939 | U25: O3558 Ineos Feluy SA MS project planning TAR | V25: Item | W25: sites/Activity/Lists/GroupIPSProjects | X25: =VLOOKUP(Table_query__64[[#This Row],[Nr]],'MyTracker Export'!A:P,'MyTracker Export'!$P$1,FALSE) -> Work in progress | Y25: =VLOOKUP(Table_query__64[[#This Row],[Nr]],'MyTracker Export'!A:Z,'MyTracker Export'!$Z$1,FALSE) -> Niels Van Osselaer | Z25: =VLOOKUP(Table_query__64[[#This Row],[Nr]],'MyTracker Export'!A:AA,'MyTracker Export'!$AA$1,FALSE) -> Peter Holvoet | AB25: =IF(Table_query__64[[#This Row],[Project status]]=Table_query__64[[#This Row],[Project Status Check]],"OK","NOK") -> OK | AC25: =IF(Table_query__64[[#This Row],[PM]]=Table_query__64[[#This Row],[PM Check]],"OK","NOK") -> OK | AD25: =IF(Table_query__64[[#This Row],[PP]]=Table_query__64[[#This Row],[Pilot Check]],"OK","NOK") -> OK
A26: O3557 | B26: 2Valorise Amel S.A. | C26: Safety & CS Support_shutdown | D26: IPS Belgium | E26: Primary & Metals | F26: Work in progress | G26: 46072.042 | I26: Guy Melis | J26: Jurgen Van Den Driessche | L26: Project Management;#1;#Safety & Site Supervision;#78 | M26: Reimbursable | N26: Q9114 | O26: 1 | P26: 45855 | Q26: 2026 | T26: 2938 | U26: O3557 2Valorise Amel S.A. Safety & CS Support_shutdown | V26: Item | W26: sites/Activity/Lists/GroupIPSProjects | X26: =VLOOKUP(Table_query__64[[#This Row],[Nr]],'MyTracker Export'!A:P,'MyTracker Export'!$P$1,FALSE) -> Work in progress | Y26: =VLOOKUP(Table_query__64[[#This Row],[Nr]],'MyTracker Export'!A:Z,'MyTracker Export'!$Z$1,FALSE) -> Guy Melis | Z26: =VLOOKUP(Table_query__64[[#This Row],[Nr]],'MyTracker Export'!A:AA,'MyTracker Export'!$AA$1,FALSE) -> Jurgen Van Den Driessche | AB26: =IF(Table_query__64[[#This Row],[Project status]]=Table_query__64[[#This Row],[Project Status Check]],"OK","NOK") -> OK | AC26: =IF(Table_query__64[[#This Row],[PM]]=Table_query__64[[#This Row],[PM Check]],"OK","NOK") -> OK | AD26: =IF(Table_query__64[[#This Row],[PP]]=Table_query__64[[#This Row],[Pilot Check]],"OK","NOK") -> OK
A27: O3556 | B27: ArcelorMittal Esch-Belval | C27: Dedusting AM Belval TMB | D27: IPS Belgium | E27: Primary & Metals | F27: Work in progress | G27: 46072.042 | I27: Denis Remacle | J27: Denis Remacle | K27: Amandyne Rosart | L27: Project Management;#1;#Engineering;#7;#Process Engineering;#17 | M27: Reimbursable | N27: Q9067 | O27: 0.01 | P27: 11582.11 | Q27: 2026 | T27: 2937 | U27: O3556 ArcelorMittal Esch-Belval Dedusting AM Belval TMB | V27: Item | W27: sites/Activity/Lists/GroupIPSProjects | X27: =VLOOKUP(Table_query__64[[#This Row],[Nr]],'MyTracker Export'!A:P,'MyTracker Export'!$P$1,FALSE) -> Work in progress | Y27: =VLOOKUP(Table_query__64[[#This Row],[Nr]],'MyTracker Export'!A:Z,'MyTracker Export'!$Z$1,FALSE) -> Denis Remacle | Z27: =VLOOKUP(Table_query__64[[#This Row],[Nr]],'MyTracker Export'!A:AA,'MyTracker Export'!$AA$1,FALSE) -> Denis Remacle | AB27: =IF(Table_query__64[[#This Row],[Project status]]=Table_query__64[[#This Row],[Project Status Check]],"OK","NOK") -> OK | AC27: =IF(Table_query__64[[#This Row],[PM]]=Table_query__64[[#This Row],[PM Check]],"OK","NOK") -> OK | AD27: =IF(Table_query__64[[#This Row],[PP]]=Table_query__64[[#This Row],[Pilot Check]],"OK","NOK") -> OK
A28: O3555 | B28: SANITECHNIEK | C28: EM4946_Prépration Plan Fluide | D28: IAPS Tunisia | E28: Buildings | F28: Work in progress | G28: 46072.042 | I28: Wissem Bensaid | J28: Wissem Bensaid | L28: Project Management;#1;#Engineering;#7;#Engineering Coordination;#54 | M28: Reimbursable | N28: Q9202 | O28: 0 | P28: 8000 | Q28: 2026 | T28: 2936 | U28: O3555 SANITECHNIEK EM4946_Prépration Plan Fluide | V28: Item | W28: sites/Activity/Lists/GroupIPSProjects | X28: =VLOOKUP(Table_query__64[[#This Row],[Nr]],'MyTracker Export'!A:P,'MyTracker Export'!$P$1,FALSE) -> Work in progress | Y28: =VLOOKUP(Table_query__64[[#This Row],[Nr]],'MyTracker Export'!A:Z,'MyTracker Export'!$Z$1,FALSE) -> Lamiss Derbel | Z28: =VLOOKUP(Table_query__64[[#This Row],[Nr]],'MyTracker Export'!A:AA,'MyTracker Export'!$AA$1,FALSE) -> Wissem Bensaid | AB28: =IF(Table_query__64[[#This Row],[Project status]]=Table_query__64[[#This Row],[Project Status Check]],"OK","NOK") -> OK | AC28: =IF(Table_query__64[[#This Row],[PM]]=Table_query__64[[#This Row],[PM Check]],"OK","NOK") -> NOK | AD28: =IF(Table_query__64[[#This Row],[PP]]=Table_query__64[[#This Row],[Pilot Check]],"OK","NOK") -> OK
A29: O3554 | B29: GlaxoSmithKline Biologicals Wavre | C29: C&Q Cuves Mobiles WN10 | D29: IPS Belgium | E29: Life Sciences | F29: Work in progress | G29: 46071.042 | I29: Yves Debaisieux | J29: Loïc Bouvier | K29: Céline Lechado | L29: Project Management;#1 | M29: Lump sum | N29: Q9054 | O29: 2 | P29: 121800 | Q29: 2026 | T29: 2935 | U29: O3554 GlaxoSmithKline C&Q Cuves Mobiles WN10 | V29: Item | W29: sites/Activity/Lists/GroupIPSProjects | X29: =VLOOKUP(Table_query__64[[#This Row],[Nr]],'MyTracker Export'!A:P,'MyTracker Export'!$P$1,FALSE) -> Work in progress | Y29: =VLOOKUP(Table_query__64[[#This Row],[Nr]],'MyTracker Export'!A:Z,'MyTracker Export'!$Z$1,FALSE) -> Yves Debaisieux | Z29: =VLOOKUP(Table_query__64[[#This Row],[Nr]],'MyTracker Export'!A:AA,'MyTracker Export'!$AA$1,FALSE) -> Loïc Bouvier | AB29: =IF(Table_query__64[[#This Row],[Project status]]=Table_query__64[[#This Row],[Project Status Check]],"OK","NOK") -> OK | AC29: =IF(Table_query__64[[#This Row],[PM]]=Table_query__64[[#This Row],[PM Check]],"OK","NOK") -> OK | AD29: =IF(Table_query__64[[#This Row],[PP]]=Table_query__64[[#This Row],[Pilot Check]],"OK","NOK") -> OK
A30: O3553 | B30: SANITECHNIEK | C30: EM4922_Projeteur HVAC | D30: IAPS Tunisia | E30: Buildings | F30: Work in progress | G30: 46069.042 | I30: Wissem Bensaid | J30: Wissem Bensaid | L30: Project Management;#1 | M30: Reimbursable | N30: Q9192 | O30: 0 | P30: 6400 | Q30: 2026 | T30: 2934 | U30: O3553 SANITECHNIEK EM4922_Projeteur HVAC | V30: Item | W30: sites/Activity/Lists/GroupIPSProjects | X30: =VLOOKUP(Table_query__64[[#This Row],[Nr]],'MyTracker Export'!A:P,'MyTracker Export'!$P$1,FALSE) -> Work in progress | Y30: =VLOOKUP(Table_query__64[[#This Row],[Nr]],'MyTracker Export'!A:Z,'MyTracker Export'!$Z$1,FALSE) -> Hanen GABSI | Z30: =VLOOKUP(Table_query__64[[#This Row],[Nr]],'MyTracker Export'!A:AA,'MyTracker Export'!$AA$1,FALSE) -> Wissem Bensaid | AB30: =IF(Table_query__64[[#This Row],[Project status]]=Table_query__64[[#This Row],[Project Status Check]],"OK","NOK") -> OK | AC30: =IF(Table_query__64[[#This Row],[PM]]=Table_query__64[[#This Row],[PM Check]],"OK","NOK") -> NOK | AD30: =IF(Table_query__64[[#This Row],[PP]]=Table_query__64[[#This Row],[Pilot Check]],"OK","NOK") -> OK
A31: O3552 | B31: Mondelez GmbH Lörrach | C31: Project Engineer external | D31: Group-IPS | E31: Food & Beverages | F31: Work in progress | G31: 46069.042 | I31: Fiete Heinrich | J31: Yannick Vega | K31: Yasmine Ben Rhaiem | L31: Project Management;#1 | M31: Reimbursable | N31: Q9191 | O31: 0 | P31: 44000 | Q31: 2026 | T31: 2933 | U31: O3552 Mondelez GmbH Lörrach Project Engineer external | V31: Item | W31: sites/Activity/Lists/GroupIPSProjects | X31: =VLOOKUP(Table_query__64[[#This Row],[Nr]],'MyTracker Export'!A:P,'MyTracker Export'!$P$1,FALSE) -> Work in progress | Y31: =VLOOKUP(Table_query__64[[#This Row],[Nr]],'MyTracker Export'!A:Z,'MyTracker Export'!$Z$1,FALSE) -> Fiete Heinrich | Z31: =VLOOKUP(Table_query__64[[#This Row],[Nr]],'MyTracker Export'!A:AA,'MyTracker Export'!$AA$1,FALSE) -> Yannick Vega Fernandez | AB31: =IF(Table_query__64[[#This Row],[Project status]]=Table_query__64[[#This Row],[Project Status Check]],"OK","NOK") -> OK | AC31: =IF(Table_query__64[[#This Row],[PM]]=Table_query__64[[#This Row],[PM Check]],"OK","NOK") -> OK | AD31: =IF(Table_query__64[[#This Row],[PP]]=Table_query__64[[#This Row],[Pilot Check]],"OK","NOK") -> NOK
A32: O3551 | B32: VEMAK | C32: EM4866_LNG Terminal Project | D32: IAPS Tunisia | E32: Chemicals | F32: Work in progress | G32: 46069.042 | I32: Wissem Bensaid | J32: Wissem Bensaid | L32: Project Management;#1;#Engineering;#7;#Mechanical Engineering;#15;#Piping Engineering;#16;#Process Engineering;#17 | M32: Lump sum | N32: Q9167 | O32: 0 | P32: 251915.4 | Q32: 2026 | T32: 2932 | U32: O3551 VEMAK EM4866_LNG Terminal Project | V32: Item | W32: sites/Activity/Lists/GroupIPSProjects | X32: =VLOOKUP(Table_query__64[[#This Row],[Nr]],'MyTracker Export'!A:P,'MyTracker Export'!$P$1,FALSE) -> Work in progress | Y32: =VLOOKUP(Table_query__64[[#This Row],[Nr]],'MyTracker Export'!A:Z,'MyTracker Export'!$Z$1,FALSE) -> Omar Tounsi | Z32: =VLOOKUP(Table_query__64[[#This Row],[Nr]],'MyTracker Export'!A:AA,'MyTracker Export'!$AA$1,FALSE) -> Wissem Bensaid | AB32: =IF(Table_query__64[[#This Row],[Project status]]=Table_query__64[[#This Row],[Project Status Check]],"OK","NOK") -> OK | AC32: =IF(Table_query__64[[#This Row],[PM]]=Table_query__64[[#This Row],[PM Check]],"OK","NOK") -> NOK | AD32: =IF(Table_query__64[[#This Row],[PP]]=Table_query__64[[#This Row],[Pilot Check]],"OK","NOK") -> OK
A33: O3550 | B33: The British School | C33: Realization Phase 1 BSB | D33: Group-IPS | E33: Buildings | F33: Work in progress | G33: 46069.042 | I33: Corto Tristan Travada | J33: Juan Juarez | K33: Delphine Myllecan | L33: Project Management;#1;#Consulting;#2;#Architecture;#5;#Engineering;#7;#Construction Management;#42;#Project Assistance;#73;#Safety & Site Supervision;#78;#Safety Coordination;#80 | M33: Lump sum | N33: Q9173 | O33: 35 | P33: 1653632 | Q33: 2026 | T33: 2931 | U33: O3550 The British School Realization Phase 1 BSB | V33: Item | W33: sites/Activity/Lists/GroupIPSProjects | X33: =VLOOKUP(Table_query__64[[#This Row],[Nr]],'MyTracker Export'!A:P,'MyTracker Export'!$P$1,FALSE) -> Work in progress | Y33: =VLOOKUP(Table_query__64[[#This Row],[Nr]],'MyTracker Export'!A:Z,'MyTracker Export'!$Z$1,FALSE) -> Corto Tristan Travada | Z33: =VLOOKUP(Table_query__64[[#This Row],[Nr]],'MyTracker Export'!A:AA,'MyTracker Export'!$AA$1,FALSE) -> Juan Juarez Quintana | AB33: =IF(Table_query__64[[#This Row],[Project status]]=Table_query__64[[#This Row],[Project Status Check]],"OK","NOK") -> OK | AC33: =IF(Table_query__64[[#This Row],[PM]]=Table_query__64[[#This Row],[PM Check]],"OK","NOK") -> OK | AD33: =IF(Table_query__64[[#This Row],[PP]]=Table_query__64[[#This Row],[Pilot Check]],"OK","NOK") -> NOK
A34: O3549 | B34: Groupe OCP | C34: EM4872_Elec&Mechanical PM | D34: IAPS Tunisia | E34: Chemicals | F34: Work in progress | G34: 46069.042 | I34: Wissem Bensaid | J34: Wissem Bensaid | L34: Project Management;#1 | M34: Lump sum | N34: Q9189 | O34: 0 | P34: 70400 | Q34: 2026 | T34: 2930 | U34: O3549 Groupe OCP EM4872_Elec&Mechanical PM | V34: Item | W34: sites/Activity/Lists/GroupIPSProjects | X34: =VLOOKUP(Table_query__64[[#This Row],[Nr]],'MyTracker Export'!A:P,'MyTracker Export'!$P$1,FALSE) -> Work in progress | Y34: =VLOOKUP(Table_query__64[[#This Row],[Nr]],'MyTracker Export'!A:Z,'MyTracker Export'!$Z$1,FALSE) -> Zied Maghrebi | Z34: =VLOOKUP(Table_query__64[[#This Row],[Nr]],'MyTracker Export'!A:AA,'MyTracker Export'!$AA$1,FALSE) -> Wissem Bensaid | AB34: =IF(Table_query__64[[#This Row],[Project status]]=Table_query__64[[#This Row],[Project Status Check]],"OK","NOK") -> OK | AC34: =IF(Table_query__64[[#This Row],[PM]]=Table_query__64[[#This Row],[PM Check]],"OK","NOK") -> NOK | AD34: =IF(Table_query__64[[#This Row],[PP]]=Table_query__64[[#This Row],[Pilot Check]],"OK","NOK") -> OK
A35: O3548 | B35: SCG Gabes | C35: EM4899_Etude servomoteur | D35: IAPS Tunisia | E35: Primary & Metals | F35: Work in progress | G35: 46069.042 | I35: Wissem Bensaid | J35: Wissem Bensaid | L35: Project Management;#1;#Engineering;#7;#Mechanical Engineering;#15 | M35: Lump sum | N35: Q9188 | O35: 0 | P35: 4363.64 | Q35: 2026 | T35: 2929 | U35: O3548 SCG Gabes EM4899_Etude servomoteur | V35: Item | W35: sites/Activity/Lists/GroupIPSProjects | X35: =VLOOKUP(Table_query__64[[#This Row],[Nr]],'MyTracker Export'!A:P,'MyTracker Export'!$P$1,FALSE) -> Work in progress | Y35: =VLOOKUP(Table_query__64[[#This Row],[Nr]],'MyTracker Export'!A:Z,'MyTracker Export'!$Z$1,FALSE) -> Zied Maghrebi | Z35: =VLOOKUP(Table_query__64[[#This Row],[Nr]],'MyTracker Export'!A:AA,'MyTracker Export'!$AA$1,FALSE) -> Wissem Bensaid | AB35: =IF(Table_query__64[[#This Row],[Project status]]=Table_query__64[[#This Row],[Project Status Check]],"OK","NOK") -> OK | AC35: =IF(Table_query__64[[#This Row],[PM]]=Table_query__64[[#This Row],[PM Check]],"OK","NOK") -> NOK | AD35: =IF(Table_query__64[[#This Row],[PP]]=Table_query__64[[#This Row],[Pilot Check]],"OK","NOK") -> OK
A36: O3547 | B36: SCG Gabes | C36: EM4749_Plan As-Built | D36: IAPS Tunisia | E36: Primary & Metals | F36: Work in progress | G36: 46069.042 | I36: Wissem Bensaid | J36: Wissem Bensaid | L36: Project Management;#1;#Engineering;#7;#Piping Engineering;#16 | M36: Lump sum | N36: Q9186 | O36: 0 | P36: 7871.52 | Q36: 2026 | T36: 2928 | U36: O3547 SCG Gabes EM4749_Plan As-Built | V36: Item | W36: sites/Activity/Lists/GroupIPSProjects | X36: =VLOOKUP(Table_query__64[[#This Row],[Nr]],'MyTracker Export'!A:P,'MyTracker Export'!$P$1,FALSE) -> Work in progress | Y36: =VLOOKUP(Table_query__64[[#This Row],[Nr]],'MyTracker Export'!A:Z,'MyTracker Export'!$Z$1,FALSE) -> Zied Maghrebi | Z36: =VLOOKUP(Table_query__64[[#This Row],[Nr]],'MyTracker Export'!A:AA,'MyTracker Export'!$AA$1,FALSE) -> Wissem Bensaid | AB36: =IF(Table_query__64[[#This Row],[Project status]]=Table_query__64[[#This Row],[Project Status Check]],"OK","NOK") -> OK | AC36: =IF(Table_query__64[[#This Row],[PM]]=Table_query__64[[#This Row],[PM Check]],"OK","NOK") -> NOK | AD36: =IF(Table_query__64[[#This Row],[PP]]=Table_query__64[[#This Row],[Pilot Check]],"OK","NOK") -> OK
A37: O3546 | B37: TPS | C37: EM4867_Root causes analysis | D37: IAPS Tunisia | E37: Chemicals | F37: Work in progress | G37: 46069.042 | I37: Wissem Bensaid | J37: Wissem Bensaid | L37: Project Management;#1 | M37: Lump sum | N37: Q9187 | O37: 0 | P37: 2100 | Q37: 2026 | T37: 2927 | U37: O3546 TPS EM4867_Root causes analysis | V37: Item | W37: sites/Activity/Lists/GroupIPSProjects | X37: =VLOOKUP(Table_query__64[[#This Row],[Nr]],'MyTracker Export'!A:P,'MyTracker Export'!$P$1,FALSE) -> Work in progress | Y37: =VLOOKUP(Table_query__64[[#This Row],[Nr]],'MyTracker Export'!A:Z,'MyTracker Export'!$Z$1,FALSE) -> Zied Maghrebi | Z37: =VLOOKUP(Table_query__64[[#This Row],[Nr]],'MyTracker Export'!A:AA,'MyTracker Export'!$AA$1,FALSE) -> Wissem Bensaid | AB37: =IF(Table_query__64[[#This Row],[Project status]]=Table_query__64[[#This Row],[Project Status Check]],"OK","NOK") -> OK | AC37: =IF(Table_query__64[[#This Row],[PM]]=Table_query__64[[#This Row],[PM Check]],"OK","NOK") -> NOK | AD37: =IF(Table_query__64[[#This Row],[PP]]=Table_query__64[[#This Row],[Pilot Check]],"OK","NOK") -> OK
A38: O3545 | B38: FIVES | C38: EM4910_3D & 2D de gaines | D38: IAPS Tunisia | E38: Primary & Metals | F38: Work in progress | G38: 46066.042 | I38: Wissem Bensaid | J38: Wissem Bensaid | L38: Project Management;#1;#Engineering;#7;#Mechanical Engineering;#15 | M38: Lump sum | N38: Q9185 | O38: 0 | P38: 7200 | Q38: 2026 | T38: 2926 | U38: O3545 FIVES EM4910_3D & 2D de gaines | V38: Item | W38: sites/Activity/Lists/GroupIPSProjects | X38: =VLOOKUP(Table_query__64[[#This Row],[Nr]],'MyTracker Export'!A:P,'MyTracker Export'!$P$1,FALSE) -> Work in progress | Y38: =VLOOKUP(Table_query__64[[#This Row],[Nr]],'MyTracker Export'!A:Z,'MyTracker Export'!$Z$1,FALSE) -> Souhir HAMMAMI | Z38: =VLOOKUP(Table_query__64[[#This Row],[Nr]],'MyTracker Export'!A:AA,'MyTracker Export'!$AA$1,FALSE) -> Wissem Bensaid | AB38: =IF(Table_query__64[[#This Row],[Project status]]=Table_query__64[[#This Row],[Project Status Check]],"OK","NOK") -> OK | AC38: =IF(Table_query__64[[#This Row],[PM]]=Table_query__64[[#This Row],[PM Check]],"OK","NOK") -> NOK | AD38: =IF(Table_query__64[[#This Row],[PP]]=Table_query__64[[#This Row],[Pilot Check]],"OK","NOK") -> OK
A39: O3544 | B39: Groupe OCP | C39: EM4472_ Descriptif Tech | D39: IAPS Tunisia | E39: Chemicals | F39: Work in progress | G39: 46066.042 | I39: Wissem Bensaid | J39: Wissem Bensaid | L39: Project Management;#1;#Engineering;#7;#Mechanical Engineering;#15 | M39: Lump sum | N39: Q9184 | O39: 0 | P39: 85876 | Q39: 2026 | T39: 2925 | U39: O3544 Groupe OCP EM4472_ Descriptif Tech | V39: Item | W39: sites/Activity/Lists/GroupIPSProjects | X39: =VLOOKUP(Table_query__64[[#This Row],[Nr]],'MyTracker Export'!A:P,'MyTracker Export'!$P$1,FALSE) -> Work in progress | Y39: =VLOOKUP(Table_query__64[[#This Row],[Nr]],'MyTracker Export'!A:Z,'MyTracker Export'!$Z$1,FALSE) -> Mansour Hamza | Z39: =VLOOKUP(Table_query__64[[#This Row],[Nr]],'MyTracker Export'!A:AA,'MyTracker Export'!$AA$1,FALSE) -> Wissem Bensaid | AB39: =IF(Table_query__64[[#This Row],[Project status]]=Table_query__64[[#This Row],[Project Status Check]],"OK","NOK") -> OK | AC39: =IF(Table_query__64[[#This Row],[PM]]=Table_query__64[[#This Row],[PM Check]],"OK","NOK") -> NOK | AD39: =IF(Table_query__64[[#This Row],[PP]]=Table_query__64[[#This Row],[Pilot Check]],"OK","NOK") -> OK
A40: O3543 | B40: FIVES | C40: EM4743_2 x CGL & CAGL in USA | D40: IAPS Tunisia | E40: Primary & Metals | F40: Work in progress | G40: 46066.042 | I40: Wissem Bensaid | J40: Wissem Bensaid | L40: Project Management;#1;#Engineering;#7;#Mechanical Engineering;#15 | M40: Lump sum | N40: Q9183 | O40: 0 | P40: 24842.98 | Q40: 2026 | T40: 2924 | U40: O3543 FIVES EM4743_2 x CGL & CAGL in USA | V40: Item | W40: sites/Activity/Lists/GroupIPSProjects | X40: =VLOOKUP(Table_query__64[[#This Row],[Nr]],'MyTracker Export'!A:P,'MyTracker Export'!$P$1,FALSE) -> Work in progress | Y40: =VLOOKUP(Table_query__64[[#This Row],[Nr]],'MyTracker Export'!A:Z,'MyTracker Export'!$Z$1,FALSE) -> Souhir HAMMAMI | Z40: =VLOOKUP(Table_query__64[[#This Row],[Nr]],'MyTracker Export'!A:AA,'MyTracker Export'!$AA$1,FALSE) -> Wissem Bensaid | AB40: =IF(Table_query__64[[#This Row],[Project status]]=Table_query__64[[#This Row],[Project Status Check]],"OK","NOK") -> OK | AC40: =IF(Table_query__64[[#This Row],[PM]]=Table_query__64[[#This Row],[PM Check]],"OK","NOK") -> NOK | AD40: =IF(Table_query__64[[#This Row],[PP]]=Table_query__64[[#This Row],[Pilot Check]],"OK","NOK") -> OK
A41: O3542 | B41: FIVES | C41: EM4849_Catalogue Plant 3D | D41: IAPS Tunisia | E41: Primary & Metals | F41: Work in progress | G41: 46066.042 | I41: Wissem Bensaid | J41: Wissem Bensaid | L41: Project Management;#1;#Engineering;#7;#Piping Engineering;#16 | M41: Lump sum | N41: Q9181 | O41: 0 | P41: 8320 | Q41: 2026 | T41: 2923 | U41: O3542 FIVES EM4849_Catalogue Plant 3D | V41: Item | W41: sites/Activity/Lists/GroupIPSProjects | X41: =VLOOKUP(Table_query__64[[#This Row],[Nr]],'MyTracker Export'!A:P,'MyTracker Export'!$P$1,FALSE) -> Work in progress | Y41: =VLOOKUP(Table_query__64[[#This Row],[Nr]],'MyTracker Export'!A:Z,'MyTracker Export'!$Z$1,FALSE) -> Haithem Elleuch | Z41: =VLOOKUP(Table_query__64[[#This Row],[Nr]],'MyTracker Export'!A:AA,'MyTracker Export'!$AA$1,FALSE) -> Wissem Bensaid | AB41: =IF(Table_query__64[[#This Row],[Project status]]=Table_query__64[[#This Row],[Project Status Check]],"OK","NOK") -> OK | AC41: =IF(Table_query__64[[#This Row],[PM]]=Table_query__64[[#This Row],[PM Check]],"OK","NOK") -> NOK | AD41: =IF(Table_query__64[[#This Row],[PP]]=Table_query__64[[#This Row],[Pilot Check]],"OK","NOK") -> OK
A42: O3541 | B42: Almayan | C42: EM4802_Al Jouf Greenfield | D42: IAPS Tunisia | E42: Buildings | F42: Work in progress | G42: 46066.042 | I42: Wissem Bensaid | J42: Wissem Bensaid | L42: Project Management;#1;#Engineering;#7;#Utilities Engineering;#19 | M42: Lump sum | N42: Q9178 | O42: 0 | P42: 27567.9 | Q42: 2026 | T42: 2922 | U42: O3541 Almayan EM4802_Al Jouf Greenfield | V42: Item | W42: sites/Activity/Lists/GroupIPSProjects | X42: =VLOOKUP(Table_query__64[[#This Row],[Nr]],'MyTracker Export'!A:P,'MyTracker Export'!$P$1,FALSE) -> Work in progress | Y42: =VLOOKUP(Table_query__64[[#This Row],[Nr]],'MyTracker Export'!A:Z,'MyTracker Export'!$Z$1,FALSE) -> Souhail WALI | Z42: =VLOOKUP(Table_query__64[[#This Row],[Nr]],'MyTracker Export'!A:AA,'MyTracker Export'!$AA$1,FALSE) -> Wissem Bensaid | AB42: =IF(Table_query__64[[#This Row],[Project status]]=Table_query__64[[#This Row],[Project Status Check]],"OK","NOK") -> OK | AC42: =IF(Table_query__64[[#This Row],[PM]]=Table_query__64[[#This Row],[PM Check]],"OK","NOK") -> NOK | AD42: =IF(Table_query__64[[#This Row],[PP]]=Table_query__64[[#This Row],[Pilot Check]],"OK","NOK") -> OK
A43: O3540 | B43: Cargill GmbH (Berlin-Reinickendorf) | C43: Project Hazelnut PE Support | D43: IPS Germany | E43: Food & Beverages | F43: Work in progress | G43: 46065.042 | I43: Fiete Heinrich | J43: Fiete Heinrich | L43: Project Management;#1;#Engineering;#7;#Engineering Coordination;#54 | M43: Reimbursable | N43: Q9145 | O43: 4 | P43: 54400 | Q43: 2026 | T43: 2921 | U43: O3540 Cargill Project Hazelnut PE Support | V43: Item | W43: sites/Activity/Lists/GroupIPSProjects | X43: =VLOOKUP(Table_query__64[[#This Row],[Nr]],'MyTracker Export'!A:P,'MyTracker Export'!$P$1,FALSE) -> Work in progress | Y43: =VLOOKUP(Table_query__64[[#This Row],[Nr]],'MyTracker Export'!A:Z,'MyTracker Export'!$Z$1,FALSE) -> Fiete Heinrich | Z43: =VLOOKUP(Table_query__64[[#This Row],[Nr]],'MyTracker Export'!A:AA,'MyTracker Export'!$AA$1,FALSE) -> Fiete Heinrich | AB43: =IF(Table_query__64[[#This Row],[Project status]]=Table_query__64[[#This Row],[Project Status Check]],"OK","NOK") -> OK | AC43: =IF(Table_query__64[[#This Row],[PM]]=Table_query__64[[#This Row],[PM Check]],"OK","NOK") -> OK | AD43: =IF(Table_query__64[[#This Row],[PP]]=Table_query__64[[#This Row],[Pilot Check]],"OK","NOK") -> OK
A44: O3539 | B44: FIVES | C44: EM4806_Shougang CGL9 | D44: IAPS Tunisia | E44: Primary & Metals | F44: Work in progress | G44: 46065.042 | I44: Wissem Bensaid | J44: Wissem Bensaid | L44: Project Management;#1;#Engineering;#7;#Piping Engineering;#16 | M44: Lump sum | N44: Q9177 | O44: 0 | P44: 159637.5 | Q44: 2026 | T44: 2920 | U44: O3539 FIVES EM4806_Shougang CGL9 | V44: Item | W44: sites/Activity/Lists/GroupIPSProjects | X44: =VLOOKUP(Table_query__64[[#This Row],[Nr]],'MyTracker Export'!A:P,'MyTracker Export'!$P$1,FALSE) -> Work in progress | Y44: =VLOOKUP(Table_query__64[[#This Row],[Nr]],'MyTracker Export'!A:Z,'MyTracker Export'!$Z$1,FALSE) -> Mohamed Hedi Hammemi | Z44: =VLOOKUP(Table_query__64[[#This Row],[Nr]],'MyTracker Export'!A:AA,'MyTracker Export'!$AA$1,FALSE) -> Wissem Bensaid | AB44: =IF(Table_query__64[[#This Row],[Project status]]=Table_query__64[[#This Row],[Project Status Check]],"OK","NOK") -> OK | AC44: =IF(Table_query__64[[#This Row],[PM]]=Table_query__64[[#This Row],[PM Check]],"OK","NOK") -> NOK | AD44: =IF(Table_query__64[[#This Row],[PP]]=Table_query__64[[#This Row],[Pilot Check]],"OK","NOK") -> OK
A45: O3538 | B45: Ab InBev EU HQ (BEL Leuven) | C45: Roof Renovation Leuven WH | D45: Arquid | E45: Buildings | F45: Work in progress | G45: 46065.042 | H45: 46065.042 | I45: Lucas Soto Alonso | J45: Lucas Soto Alonso | L45: Architecture;#5;#Engineering;#7;#Utilities Engineering;#19 | M45: Lump sum | N45: Q9097 | O45: 0 | P45: 0 | Q45: 2026 | R45: 2026 | T45: 2919 | U45: O3538 Ab InBev Roof Renovation Leuven WH | V45: Item | W45: sites/Activity/Lists/GroupIPSProjects | X45: =VLOOKUP(Table_query__64[[#This Row],[Nr]],'MyTracker Export'!A:P,'MyTracker Export'!$P$1,FALSE) -> Finished | Y45: =VLOOKUP(Table_query__64[[#This Row],[Nr]],'MyTracker Export'!A:Z,'MyTracker Export'!$Z$1,FALSE) -> Lucas Soto | Z45: =VLOOKUP(Table_query__64[[#This Row],[Nr]],'MyTracker Export'!A:AA,'MyTracker Export'!$AA$1,FALSE) -> Lucas Soto | AB45: =IF(Table_query__64[[#This Row],[Project status]]=Table_query__64[[#This Row],[Project Status Check]],"OK","NOK") -> NOK | AC45: =IF(Table_query__64[[#This Row],[PM]]=Table_query__64[[#This Row],[PM Check]],"OK","NOK") -> NOK | AD45: =IF(Table_query__64[[#This Row],[PP]]=Table_query__64[[#This Row],[Pilot Check]],"OK","NOK") -> NOK
A46: O3537 | B46: Reforma viviendas | C46: AS152 | D46: Arquid | E46: Buildings | F46: Work in progress | G46: 46064.042 | I46: Begona Soto | J46: Begona Soto | L46: Architecture;#5;#Engineering;#7 | M46: Lump sum | N46: Q9093 | O46: 297 | P46: 5130 | Q46: 2026 | T46: 2918 | U46: O3537 Reforma viviendas AS152 | V46: Item | W46: sites/Activity/Lists/GroupIPSProjects | X46: =VLOOKUP(Table_query__64[[#This Row],[Nr]],'MyTracker Export'!A:P,'MyTracker Export'!$P$1,FALSE) -> Work in progress | Y46: =VLOOKUP(Table_query__64[[#This Row],[Nr]],'MyTracker Export'!A:Z,'MyTracker Export'!$Z$1,FALSE) -> Begona Soto | Z46: =VLOOKUP(Table_query__64[[#This Row],[Nr]],'MyTracker Export'!A:AA,'MyTracker Export'!$AA$1,FALSE) -> Begona Soto | AB46: =IF(Table_query__64[[#This Row],[Project status]]=Table_query__64[[#This Row],[Project Status Check]],"OK","NOK") -> OK | AC46: =IF(Table_query__64[[#This Row],[PM]]=Table_query__64[[#This Row],[PM Check]],"OK","NOK") -> OK | AD46: =IF(Table_query__64[[#This Row],[PP]]=Table_query__64[[#This Row],[Pilot Check]],"OK","NOK") -> OK
A47: O3536 | B47: Indicator Srl | C47: Arch-PM refurb. support | D47: Arquid | E47: Buildings | F47: Work in progress | G47: 46064.042 | I47: Lucas Soto Alonso | J47: Lucas Soto Alonso | K47: Maximiliano Martin Parra | L47: Architecture;#5 | M47: Reimbursable | N47: Q9175 | O47: 1000000 | P47: 19600 | Q47: 2026 | T47: 2917 | U47: O3536 Indicator Srl Arch-PM refurb. support | V47: Item | W47: sites/Activity/Lists/GroupIPSProjects | X47: =VLOOKUP(Table_query__64[[#This Row],[Nr]],'MyTracker Export'!A:P,'MyTracker Export'!$P$1,FALSE) -> Work in progress | Y47: =VLOOKUP(Table_query__64[[#This Row],[Nr]],'MyTracker Export'!A:Z,'MyTracker Export'!$Z$1,FALSE) -> Lucas Soto | Z47: =VLOOKUP(Table_query__64[[#This Row],[Nr]],'MyTracker Export'!A:AA,'MyTracker Export'!$AA$1,FALSE) -> Lucas Soto | AB47: =IF(Table_query__64[[#This Row],[Project status]]=Table_query__64[[#This Row],[Project Status Check]],"OK","NOK") -> OK | AC47: =IF(Table_query__64[[#This Row],[PM]]=Table_query__64[[#This Row],[PM Check]],"OK","NOK") -> NOK | AD47: =IF(Table_query__64[[#This Row],[PP]]=Table_query__64[[#This Row],[Pilot Check]],"OK","NOK") -> NOK
A48: O3535 | B48: EPHEMERALL | C48: FC Nürnberg Fan Experience | D48: Arquid | E48: Buildings | F48: Work in progress | G48: 46064.042 | I48: Natalia Martínez Nieto | J48: Natalia Martínez Nieto | L48: Architecture;#5 | M48: Lump sum | N48: Q9174 | O48: 0 | P48: 3677 | Q48: 2026 | T48: 2916 | U48: O3535 EPHEMERALL FC Nürnberg Fan Experience | V48: Item | W48: sites/Activity/Lists/GroupIPSProjects | X48: =VLOOKUP(Table_query__64[[#This Row],[Nr]],'MyTracker Export'!A:P,'MyTracker Export'!$P$1,FALSE) -> Work in progress | Y48: =VLOOKUP(Table_query__64[[#This Row],[Nr]],'MyTracker Export'!A:Z,'MyTracker Export'!$Z$1,FALSE) -> Natalia Martínez Nieto | Z48: =VLOOKUP(Table_query__64[[#This Row],[Nr]],'MyTracker Export'!A:AA,'MyTracker Export'!$AA$1,FALSE) -> Natalia Martínez Nieto | AB48: =IF(Table_query__64[[#This Row],[Project status]]=Table_query__64[[#This Row],[Project Status Check]],"OK","NOK") -> OK | AC48: =IF(Table_query__64[[#This Row],[PM]]=Table_query__64[[#This Row],[PM Check]],"OK","NOK") -> OK | AD48: =IF(Table_query__64[[#This Row],[PP]]=Table_query__64[[#This Row],[Pilot Check]],"OK","NOK") -> OK
A49: O3534 | B49: Cargill Riesa | C49: Public Tendering support | D49: IPS Germany | E49: Food & Beverages | F49: Work in progress | G49: 46063.042 | I49: Sang Tan Dang | J49: Fiete Heinrich | L49: Engineering;#7 | M49: Reimbursable | N49: Q9168 | O49: 0 | P49: 2925 | Q49: 2026 | T49: 2915 | U49: O3534 Cargill Riesa Public Tendering support | V49: Item | W49: sites/Activity/Lists/GroupIPSProjects | X49: =VLOOKUP(Table_query__64[[#This Row],[Nr]],'MyTracker Export'!A:P,'MyTracker Export'!$P$1,FALSE) -> Work in progress | Y49: =VLOOKUP(Table_query__64[[#This Row],[Nr]],'MyTracker Export'!A:Z,'MyTracker Export'!$Z$1,FALSE) -> Sang Tan Dang | Z49: =VLOOKUP(Table_query__64[[#This Row],[Nr]],'MyTracker Export'!A:AA,'MyTracker Export'!$AA$1,FALSE) -> Fiete Heinrich | AB49: =IF(Table_query__64[[#This Row],[Project status]]=Table_query__64[[#This Row],[Project Status Check]],"OK","NOK") -> OK | AC49: =IF(Table_query__64[[#This Row],[PM]]=Table_query__64[[#This Row],[PM Check]],"OK","NOK") -> OK | AD49: =IF(Table_query__64[[#This Row],[PP]]=Table_query__64[[#This Row],[Pilot Check]],"OK","NOK") -> OK
A50: O3533 | B50: FIVES | C50: EM4884_ Tag Electrique | D50: IAPS Tunisia | E50: Primary & Metals | F50: Work in progress | G50: 46063.042 | I50: Wissem Bensaid | J50: Wissem Bensaid | L50: Project Management;#1;#Engineering;#7 | M50: Lump sum | N50: Q9166 | O50: 0 | P50: 10800 | Q50: 2026 | T50: 2914 | U50: O3533 FIVES EM4884_ Tag Electrique | V50: Item | W50: sites/Activity/Lists/GroupIPSProjects | X50: =VLOOKUP(Table_query__64[[#This Row],[Nr]],'MyTracker Export'!A:P,'MyTracker Export'!$P$1,FALSE) -> Work in progress | Y50: =VLOOKUP(Table_query__64[[#This Row],[Nr]],'MyTracker Export'!A:Z,'MyTracker Export'!$Z$1,FALSE) -> Rawya TLIG | Z50: =VLOOKUP(Table_query__64[[#This Row],[Nr]],'MyTracker Export'!A:AA,'MyTracker Export'!$AA$1,FALSE) -> Wissem Bensaid | AB50: =IF(Table_query__64[[#This Row],[Project status]]=Table_query__64[[#This Row],[Project Status Check]],"OK","NOK") -> OK | AC50: =IF(Table_query__64[[#This Row],[PM]]=Table_query__64[[#This Row],[PM Check]],"OK","NOK") -> NOK | AD50: =IF(Table_query__64[[#This Row],[PP]]=Table_query__64[[#This Row],[Pilot Check]],"OK","NOK") -> OK
A51: O3532 | B51: ENDECO | C51: EM4811_Flow Line Design | D51: IAPS Tunisia | E51: Chemicals | F51: Work in progress | G51: 46063.042 | I51: Wissem Bensaid | J51: Wissem Bensaid | L51: Project Management;#1;#Engineering;#7;#Piping Engineering;#16 | M51: Lump sum | N51: Q9164 | O51: 0 | P51: 7000 | Q51: 2026 | T51: 2913 | U51: O3532 ENDECO EM4811_Flow Line Design | V51: Item | W51: sites/Activity/Lists/GroupIPSProjects | X51: =VLOOKUP(Table_query__64[[#This Row],[Nr]],'MyTracker Export'!A:P,'MyTracker Export'!$P$1,FALSE) -> Work in progress | Y51: =VLOOKUP(Table_query__64[[#This Row],[Nr]],'MyTracker Export'!A:Z,'MyTracker Export'!$Z$1,FALSE) -> Houssem Bac Ali | Z51: =VLOOKUP(Table_query__64[[#This Row],[Nr]],'MyTracker Export'!A:AA,'MyTracker Export'!$AA$1,FALSE) -> Wissem Bensaid | AB51: =IF(Table_query__64[[#This Row],[Project status]]=Table_query__64[[#This Row],[Project Status Check]],"OK","NOK") -> OK | AC51: =IF(Table_query__64[[#This Row],[PM]]=Table_query__64[[#This Row],[PM Check]],"OK","NOK") -> NOK | AD51: =IF(Table_query__64[[#This Row],[PP]]=Table_query__64[[#This Row],[Pilot Check]],"OK","NOK") -> OK
A52: O3531 | B52: ENDECO | C52: EM4715_Dispersion study | D52: IAPS Tunisia | E52: Chemicals | F52: Work in progress | G52: 46063.042 | I52: Wissem Bensaid | J52: Wissem Bensaid | L52: Engineering;#7;#Process Engineering;#17 | M52: Lump sum | N52: Q9163 | O52: 0 | P52: 3000 | Q52: 2026 | T52: 2912 | U52: O3531 ENDECO EM4715_Dispersion study | V52: Item | W52: sites/Activity/Lists/GroupIPSProjects | X52: =VLOOKUP(Table_query__64[[#This Row],[Nr]],'MyTracker Export'!A:P,'MyTracker Export'!$P$1,FALSE) -> Work in progress | Y52: =VLOOKUP(Table_query__64[[#This Row],[Nr]],'MyTracker Export'!A:Z,'MyTracker Export'!$Z$1,FALSE) -> Wassim Ktari | Z52: =VLOOKUP(Table_query__64[[#This Row],[Nr]],'MyTracker Export'!A:AA,'MyTracker Export'!$AA$1,FALSE) -> Wissem Bensaid | AB52: =IF(Table_query__64[[#This Row],[Project status]]=Table_query__64[[#This Row],[Project Status Check]],"OK","NOK") -> OK | AC52: =IF(Table_query__64[[#This Row],[PM]]=Table_query__64[[#This Row],[PM Check]],"OK","NOK") -> NOK | AD52: =IF(Table_query__64[[#This Row],[PP]]=Table_query__64[[#This Row],[Pilot Check]],"OK","NOK") -> OK
A53: O3530 | B53: Cordia Homes | C53: Cerrado del Aguila plot M1-B | D53: IPS Spain | E53: Buildings | F53: Work in progress | G53: 46062.042 | I53: Miguel Menéndez | J53: Miguel Menéndez | L53: Project Management;#1;#Engineering;#7 | M53: Lump sum | N53: Q9161 | O53: 0 | P53: 0 | Q53: 2026 | T53: 2911 | U53: O3530 Cordia Homes Cerrado del Aguila plot M1-B | V53: Item | W53: sites/Activity/Lists/GroupIPSProjects | X53: =VLOOKUP(Table_query__64[[#This Row],[Nr]],'MyTracker Export'!A:P,'MyTracker Export'!$P$1,FALSE) -> Work in progress | Y53: =VLOOKUP(Table_query__64[[#This Row],[Nr]],'MyTracker Export'!A:Z,'MyTracker Export'!$Z$1,FALSE) -> Miguel Menéndez | Z53: =VLOOKUP(Table_query__64[[#This Row],[Nr]],'MyTracker Export'!A:AA,'MyTracker Export'!$AA$1,FALSE) -> Miguel Menéndez | AB53: =IF(Table_query__64[[#This Row],[Project status]]=Table_query__64[[#This Row],[Project Status Check]],"OK","NOK") -> OK | AC53: =IF(Table_query__64[[#This Row],[PM]]=Table_query__64[[#This Row],[PM Check]],"OK","NOK") -> OK | AD53: =IF(Table_query__64[[#This Row],[PP]]=Table_query__64[[#This Row],[Pilot Check]],"OK","NOK") -> OK
A54: O3529 | B54: MARETAP | C54: EM4705_Design Report heater | D54: IAPS Tunisia | E54: Chemicals | F54: Work in progress | G54: 46062.042 | I54: Wissem Bensaid | J54: Wissem Bensaid | L54: Engineering;#7;#Mechanical Engineering;#15 | M54: Lump sum | N54: Q9159 | O54: 0 | P54: 1600 | Q54: 2026 | T54: 2910 | U54: O3529 MARETAP EM4705_Design Report heater | V54: Item | W54: sites/Activity/Lists/GroupIPSProjects | X54: =VLOOKUP(Table_query__64[[#This Row],[Nr]],'MyTracker Export'!A:P,'MyTracker Export'!$P$1,FALSE) -> Work in progress | Y54: =VLOOKUP(Table_query__64[[#This Row],[Nr]],'MyTracker Export'!A:Z,'MyTracker Export'!$Z$1,FALSE) -> Walid TAKTAK | Z54: =VLOOKUP(Table_query__64[[#This Row],[Nr]],'MyTracker Export'!A:AA,'MyTracker Export'!$AA$1,FALSE) -> Wissem Bensaid | AB54: =IF(Table_query__64[[#This Row],[Project status]]=Table_query__64[[#This Row],[Project Status Check]],"OK","NOK") -> OK | AC54: =IF(Table_query__64[[#This Row],[PM]]=Table_query__64[[#This Row],[PM Check]],"OK","NOK") -> NOK | AD54: =IF(Table_query__64[[#This Row],[PP]]=Table_query__64[[#This Row],[Pilot Check]],"OK","NOK") -> OK
A55: O3528 | B55: PC Switzerland | C55: EM4803_Architectural plan | D55: IAPS Tunisia | E55: Buildings | F55: Work in progress | G55: 46062.042 | I55: Wissem Bensaid | J55: Wissem Bensaid | L55: Engineering;#7 | M55: Lump sum | N55: Q9160 | O55: 0 | P55: 1800 | Q55: 2026 | T55: 2909 | U55: O3528 PC Switzerland EM4803_Architectural plan | V55: Item | W55: sites/Activity/Lists/GroupIPSProjects | X55: =VLOOKUP(Table_query__64[[#This Row],[Nr]],'MyTracker Export'!A:P,'MyTracker Export'!$P$1,FALSE) -> Work in progress | Y55: =VLOOKUP(Table_query__64[[#This Row],[Nr]],'MyTracker Export'!A:Z,'MyTracker Export'!$Z$1,FALSE) -> Mohamed Ali Bouaziz | Z55: =VLOOKUP(Table_query__64[[#This Row],[Nr]],'MyTracker Export'!A:AA,'MyTracker Export'!$AA$1,FALSE) -> Wissem Bensaid | AB55: =IF(Table_query__64[[#This Row],[Project status]]=Table_query__64[[#This Row],[Project Status Check]],"OK","NOK") -> OK | AC55: =IF(Table_query__64[[#This Row],[PM]]=Table_query__64[[#This Row],[PM Check]],"OK","NOK") -> NOK | AD55: =IF(Table_query__64[[#This Row],[PP]]=Table_query__64[[#This Row],[Pilot Check]],"OK","NOK") -> OK
A56: O3527 | B56: Cordia Homes | C56: Cerrado del Aguila plot M1-A | D56: IPS Spain | E56: Buildings | F56: Work in progress | G56: 46062.042 | I56: Belén Lopez Barrera | J56: Miguel Menéndez | L56: Project Management;#1;#Engineering;#7 | M56: Lump sum | N56: Q8945 | O56: 27 | P56: 8316 | Q56: 2026 | T56: 2908 | U56: O3527 Cordia Homes Cerrado del Aguila plot M1-A | V56: Item | W56: sites/Activity/Lists/GroupIPSProjects | X56: =VLOOKUP(Table_query__64[[#This Row],[Nr]],'MyTracker Export'!A:P,'MyTracker Export'!$P$1,FALSE) -> Work in progress | Y56: =VLOOKUP(Table_query__64[[#This Row],[Nr]],'MyTracker Export'!A:Z,'MyTracker Export'!$Z$1,FALSE) -> Belén Lopez Barrera | Z56: =VLOOKUP(Table_query__64[[#This Row],[Nr]],'MyTracker Export'!A:AA,'MyTracker Export'!$AA$1,FALSE) -> Miguel Menéndez | AB56: =IF(Table_query__64[[#This Row],[Project status]]=Table_query__64[[#This Row],[Project Status Check]],"OK","NOK") -> OK | AC56: =IF(Table_query__64[[#This Row],[PM]]=Table_query__64[[#This Row],[PM Check]],"OK","NOK") -> OK | AD56: =IF(Table_query__64[[#This Row],[PP]]=Table_query__64[[#This Row],[Pilot Check]],"OK","NOK") -> OK
A57: O3526 | B57: S.W.I.F.T. SC | C57: 2026 Project Support | D57: IPS Belgium | E57: Buildings | F57: Work in progress | G57: 46059.042 | I57: Sunny Yip | J57: Sunny Yip | K57: Delphine Myllecan | L57: Project Management;#1;#Engineering;#7;#HVAC Engineering;#14;#Construction Management;#42;#Project Assistance;#73 | M57: Reimbursable | N57: Q9010 | O57: 10 | P57: 467409.56 | Q57: 2026 | T57: 2907 | U57: O3526 S.W.I.F.T. SC 2026 Project Support | V57: Item | W57: sites/Activity/Lists/GroupIPSProjects | X57: =VLOOKUP(Table_query__64[[#This Row],[Nr]],'MyTracker Export'!A:P,'MyTracker Export'!$P$1,FALSE) -> Work in progress | Y57: =VLOOKUP(Table_query__64[[#This Row],[Nr]],'MyTracker Export'!A:Z,'MyTracker Export'!$Z$1,FALSE) -> Sunny Yip | Z57: =VLOOKUP(Table_query__64[[#This Row],[Nr]],'MyTracker Export'!A:AA,'MyTracker Export'!$AA$1,FALSE) -> Sunny Yip | AB57: =IF(Table_query__64[[#This Row],[Project status]]=Table_query__64[[#This Row],[Project Status Check]],"OK","NOK") -> OK | AC57: =IF(Table_query__64[[#This Row],[PM]]=Table_query__64[[#This Row],[PM Check]],"OK","NOK") -> OK | AD57: =IF(Table_query__64[[#This Row],[PP]]=Table_query__64[[#This Row],[Pilot Check]],"OK","NOK") -> OK
A58: O3525 | B58: Cargill Chocolate Belgium NV (Mouscron) | C58: ATEX file update | D58: IPS Belgium | E58: Food & Beverages | F58: Work in progress | G58: 46056.042 | I58: Audric Jeanne | J58: Karel De Swert | K58: Delphine Myllecan | L58: Project Management;#1;#Safety Engineering;#81 | M58: Lump sum | N58: Q9110 | O58: 0.01 | P58: 23167.99 | Q58: 2026 | T58: 2906 | U58: O3525 Cargill ATEX file update | V58: Item | W58: sites/Activity/Lists/GroupIPSProjects | X58: =VLOOKUP(Table_query__64[[#This Row],[Nr]],'MyTracker Export'!A:P,'MyTracker Export'!$P$1,FALSE) -> Work in progress | Y58: =VLOOKUP(Table_query__64[[#This Row],[Nr]],'MyTracker Export'!A:Z,'MyTracker Export'!$Z$1,FALSE) -> Audric Jeanne | Z58: =VLOOKUP(Table_query__64[[#This Row],[Nr]],'MyTracker Export'!A:AA,'MyTracker Export'!$AA$1,FALSE) -> Karel De Swert | AB58: =IF(Table_query__64[[#This Row],[Project status]]=Table_query__64[[#This Row],[Project Status Check]],"OK","NOK") -> OK | AC58: =IF(Table_query__64[[#This Row],[PM]]=Table_query__64[[#This Row],[PM Check]],"OK","NOK") -> OK | AD58: =IF(Table_query__64[[#This Row],[PP]]=Table_query__64[[#This Row],[Pilot Check]],"OK","NOK") -> OK
A59: O3524 | B59: Gianni Housing | C59: Informe Villanueva 41 | D59: Arquid | E59: Buildings | F59: Work in progress | G59: 46052.042 | I59: Begona Soto | J59: Begona Soto | L59: Architecture;#5 | M59: Lump sum | N59: Q9140 | O59: 1 | P59: 1100 | Q59: 2026 | T59: 2905 | U59: O3524 Gianni Housing Informe Villanueva 41 | V59: Item | W59: sites/Activity/Lists/GroupIPSProjects | X59: =VLOOKUP(Table_query__64[[#This Row],[Nr]],'MyTracker Export'!A:P,'MyTracker Export'!$P$1,FALSE) -> Work in progress | Y59: =VLOOKUP(Table_query__64[[#This Row],[Nr]],'MyTracker Export'!A:Z,'MyTracker Export'!$Z$1,FALSE) -> Begona Soto | Z59: =VLOOKUP(Table_query__64[[#This Row],[Nr]],'MyTracker Export'!A:AA,'MyTracker Export'!$AA$1,FALSE) -> Begona Soto | AB59: =IF(Table_query__64[[#This Row],[Project status]]=Table_query__64[[#This Row],[Project Status Check]],"OK","NOK") -> OK | AC59: =IF(Table_query__64[[#This Row],[PM]]=Table_query__64[[#This Row],[PM Check]],"OK","NOK") -> OK | AD59: =IF(Table_query__64[[#This Row],[PP]]=Table_query__64[[#This Row],[Pilot Check]],"OK","NOK") -> OK
A60: O3523 | B60: ECOMIN | C60: EM4762_Algeria Beneficiation | D60: IAPS Tunisia | E60: Chemicals | F60: Work in progress | G60: 46052.042 | I60: Wissem Bensaid | J60: Wissem Bensaid | L60: Project Management;#1;#Engineering;#7;#Mechanical Engineering;#15;#Piping Engineering;#16;#Process Engineering;#17 | M60: Lump sum | N60: Q9144 | O60: 0 | P60: 154800 | Q60: 2026 | T60: 2904 | U60: O3523 ECOMIN EM4762_Algeria Beneficiation | V60: Item | W60: sites/Activity/Lists/GroupIPSProjects | X60: =VLOOKUP(Table_query__64[[#This Row],[Nr]],'MyTracker Export'!A:P,'MyTracker Export'!$P$1,FALSE) -> Work in progress | Y60: =VLOOKUP(Table_query__64[[#This Row],[Nr]],'MyTracker Export'!A:Z,'MyTracker Export'!$Z$1,FALSE) -> Amir Ben Ayed | Z60: =VLOOKUP(Table_query__64[[#This Row],[Nr]],'MyTracker Export'!A:AA,'MyTracker Export'!$AA$1,FALSE) -> Wissem Bensaid | AB60: =IF(Table_query__64[[#This Row],[Project status]]=Table_query__64[[#This Row],[Project Status Check]],"OK","NOK") -> OK | AC60: =IF(Table_query__64[[#This Row],[PM]]=Table_query__64[[#This Row],[PM Check]],"OK","NOK") -> NOK | AD60: =IF(Table_query__64[[#This Row],[PP]]=Table_query__64[[#This Row],[Pilot Check]],"OK","NOK") -> OK
A61: O3522 | B61: LDC Wittenberg | C61: Micella Preheater | D61: IPS Germany | E61: Food & Beverages | F61: Work in progress | G61: 46052.042 | I61: Lucas Olheiser | J61: Fiete Heinrich | L61: Project Management;#1;#Engineering;#7;#Engineering Coordination;#54 | M61: Reimbursable | N61: Q9038 | O61: 1 | P61: 59495 | Q61: 2026 | T61: 2903 | U61: O3522 LDC Wittenberg Micella Preheater | V61: Item | W61: sites/Activity/Lists/GroupIPSProjects | X61: =VLOOKUP(Table_query__64[[#This Row],[Nr]],'MyTracker Export'!A:P,'MyTracker Export'!$P$1,FALSE) -> Work in progress | Y61: =VLOOKUP(Table_query__64[[#This Row],[Nr]],'MyTracker Export'!A:Z,'MyTracker Export'!$Z$1,FALSE) -> Lucas Olheiser | Z61: =VLOOKUP(Table_query__64[[#This Row],[Nr]],'MyTracker Export'!A:AA,'MyTracker Export'!$AA$1,FALSE) -> Fiete Heinrich | AB61: =IF(Table_query__64[[#This Row],[Project status]]=Table_query__64[[#This Row],[Project Status Check]],"OK","NOK") -> OK | AC61: =IF(Table_query__64[[#This Row],[PM]]=Table_query__64[[#This Row],[PM Check]],"OK","NOK") -> OK | AD61: =IF(Table_query__64[[#This Row],[PP]]=Table_query__64[[#This Row],[Pilot Check]],"OK","NOK") -> OK
A62: O3521 | B62: LDC Wittenberg | C62: Oil Tank Replacement | D62: IPS Germany | E62: Food & Beverages | F62: Work in progress | G62: 46064.042 | I62: Sang Tan Dang | J62: Fiete Heinrich | L62: Project Management;#1 | M62: Reimbursable | N62: Q9089 | O62: 0.7 | P62: 40475 | Q62: 2026 | T62: 2902 | U62: O3521 LDC Wittenberg Oil Tank Replacement | V62: Item | W62: sites/Activity/Lists/GroupIPSProjects | X62: =VLOOKUP(Table_query__64[[#This Row],[Nr]],'MyTracker Export'!A:P,'MyTracker Export'!$P$1,FALSE) -> Work in progress | Y62: =VLOOKUP(Table_query__64[[#This Row],[Nr]],'MyTracker Export'!A:Z,'MyTracker Export'!$Z$1,FALSE) -> Sang Tan Dang | Z62: =VLOOKUP(Table_query__64[[#This Row],[Nr]],'MyTracker Export'!A:AA,'MyTracker Export'!$AA$1,FALSE) -> Fiete Heinrich | AB62: =IF(Table_query__64[[#This Row],[Project status]]=Table_query__64[[#This Row],[Project Status Check]],"OK","NOK") -> OK | AC62: =IF(Table_query__64[[#This Row],[PM]]=Table_query__64[[#This Row],[PM Check]],"OK","NOK") -> OK | AD62: =IF(Table_query__64[[#This Row],[PP]]=Table_query__64[[#This Row],[Pilot Check]],"OK","NOK") -> OK
A63: O3520 | B63: MARETAP | C63: EM4873_Etude GC Shutdown | D63: IAPS Tunisia | E63: Chemicals | F63: Work in progress | G63: 46051.042 | I63: Wissem Bensaid | J63: Wissem Bensaid | L63: Project Management;#1;#Engineering;#7 | M63: Lump sum | N63: Q9143 | O63: 0 | P63: 8600 | Q63: 2026 | T63: 2901 | U63: O3520 MARETAP EM4873_Etude GC Shutdown | V63: Item | W63: sites/Activity/Lists/GroupIPSProjects | X63: =VLOOKUP(Table_query__64[[#This Row],[Nr]],'MyTracker Export'!A:P,'MyTracker Export'!$P$1,FALSE) -> Work in progress | Y63: =VLOOKUP(Table_query__64[[#This Row],[Nr]],'MyTracker Export'!A:Z,'MyTracker Export'!$Z$1,FALSE) -> Achraf Walha | Z63: =VLOOKUP(Table_query__64[[#This Row],[Nr]],'MyTracker Export'!A:AA,'MyTracker Export'!$AA$1,FALSE) -> Wissem Bensaid | AB63: =IF(Table_query__64[[#This Row],[Project status]]=Table_query__64[[#This Row],[Project Status Check]],"OK","NOK") -> OK | AC63: =IF(Table_query__64[[#This Row],[PM]]=Table_query__64[[#This Row],[PM Check]],"OK","NOK") -> NOK | AD63: =IF(Table_query__64[[#This Row],[PP]]=Table_query__64[[#This Row],[Pilot Check]],"OK","NOK") -> OK
A64: O3519 | B64: 133 School | C64: 133_Extension_IPS Proposal | D64: IPS Bulgaria | E64: Other industry | F64: Work in progress | G64: 46051.042 | I64: Nevena Banova | J64: Nevena Banova | L64: Project Management;#1;#Architecture;#5;#Engineering;#7;#HVAC Engineering;#14;#Process Engineering;#17;#Construction Management;#42;#Safety Engineering;#81 | M64: Lump sum | N64: Q9131 | O64: 0 | P64: 25075 | Q64: 2026 | T64: 2900 | U64: O3519 133 School 133_Extension_IPS Proposal | V64: Item | W64: sites/Activity/Lists/GroupIPSProjects | X64: =VLOOKUP(Table_query__64[[#This Row],[Nr]],'MyTracker Export'!A:P,'MyTracker Export'!$P$1,FALSE) -> Work in progress | Y64: =VLOOKUP(Table_query__64[[#This Row],[Nr]],'MyTracker Export'!A:Z,'MyTracker Export'!$Z$1,FALSE) -> Maxim Mokdad | Z64: =VLOOKUP(Table_query__64[[#This Row],[Nr]],'MyTracker Export'!A:AA,'MyTracker Export'!$AA$1,FALSE) -> Boris Krastev | AB64: =IF(Table_query__64[[#This Row],[Project status]]=Table_query__64[[#This Row],[Project Status Check]],"OK","NOK") -> OK | AC64: =IF(Table_query__64[[#This Row],[PM]]=Table_query__64[[#This Row],[PM Check]],"OK","NOK") -> NOK | AD64: =IF(Table_query__64[[#This Row],[PP]]=Table_query__64[[#This Row],[Pilot Check]],"OK","NOK") -> NOK
A65: O3518 | B65: Air Liquide | C65: Air Liquide_PM services | D65: IPS Bulgaria | E65: Chemicals | F65: Work in progress | G65: 46051.042 | I65: Nevena Banova | J65: Nevena Banova | L65: Project Management;#1 | M65: Reimbursable | N65: Q8962 | O65: 0 | P65: 115200 | Q65: 2026 | T65: 2899 | U65: O3518 Air Liquide Air Liquide_PM services | V65: Item | W65: sites/Activity/Lists/GroupIPSProjects | X65: =VLOOKUP(Table_query__64[[#This Row],[Nr]],'MyTracker Export'!A:P,'MyTracker Export'!$P$1,FALSE) -> Work in progress | Y65: =VLOOKUP(Table_query__64[[#This Row],[Nr]],'MyTracker Export'!A:Z,'MyTracker Export'!$Z$1,FALSE) -> Dobri Gatev | Z65: =VLOOKUP(Table_query__64[[#This Row],[Nr]],'MyTracker Export'!A:AA,'MyTracker Export'!$AA$1,FALSE) -> Tsanko Mihov | AB65: =IF(Table_query__64[[#This Row],[Project status]]=Table_query__64[[#This Row],[Project Status Check]],"OK","NOK") -> OK | AC65: =IF(Table_query__64[[#This Row],[PM]]=Table_query__64[[#This Row],[PM Check]],"OK","NOK") -> NOK | AD65: =IF(Table_query__64[[#This Row],[PP]]=Table_query__64[[#This Row],[Pilot Check]],"OK","NOK") -> NOK
A66: O3517 | B66: Puratos_Sils (Spain) | C66: CONSULTA URBANÍSTICA_PARKING | D66: IPS Spain | E66: Food & Beverages | F66: Work in progress | G66: 46048.042 | I66: Gonzalo Martin | J66: Paqui Romero | L66: Project Management;#1;#Architecture;#5 | M66: Lump sum | N66: Q9105 | O66: 1 | P66: 6100 | Q66: 2026 | T66: 2898 | U66: O3517 Puratos_Sils (Spain) CONSULTA URBANÍSTICA_PARKING | V66: Item | W66: sites/Activity/Lists/GroupIPSProjects | X66: =VLOOKUP(Table_query__64[[#This Row],[Nr]],'MyTracker Export'!A:P,'MyTracker Export'!$P$1,FALSE) -> Work in progress | Y66: =VLOOKUP(Table_query__64[[#This Row],[Nr]],'MyTracker Export'!A:Z,'MyTracker Export'!$Z$1,FALSE) -> Paqui Romero | Z66: =VLOOKUP(Table_query__64[[#This Row],[Nr]],'MyTracker Export'!A:AA,'MyTracker Export'!$AA$1,FALSE) -> Paqui Romero | AB66: =IF(Table_query__64[[#This Row],[Project status]]=Table_query__64[[#This Row],[Project Status Check]],"OK","NOK") -> OK | AC66: =IF(Table_query__64[[#This Row],[PM]]=Table_query__64[[#This Row],[PM Check]],"OK","NOK") -> NOK | AD66: =IF(Table_query__64[[#This Row],[PP]]=Table_query__64[[#This Row],[Pilot Check]],"OK","NOK") -> OK
A67: O3516 | B67: P3 Logistic Parks | C67: TDD Azuqueca Henares | D67: IPS Spain | E67: Buildings | F67: Work in progress | G67: 46048.042 | I67: Miguel Menéndez | J67: Juan Juarez | L67: Consulting;#2 | M67: Lump sum | N67: Q9074 | O67: 30 | P67: 32997.89 | Q67: 2026 | T67: 2897 | U67: O3516 P3 Logistic Parks TDD Azuqueca Henares | V67: Item | W67: sites/Activity/Lists/GroupIPSProjects | X67: =VLOOKUP(Table_query__64[[#This Row],[Nr]],'MyTracker Export'!A:P,'MyTracker Export'!$P$1,FALSE) -> Work in progress | Y67: =VLOOKUP(Table_query__64[[#This Row],[Nr]],'MyTracker Export'!A:Z,'MyTracker Export'!$Z$1,FALSE) -> Miguel Menéndez | Z67: =VLOOKUP(Table_query__64[[#This Row],[Nr]],'MyTracker Export'!A:AA,'MyTracker Export'!$AA$1,FALSE) -> Juan Juarez Quintana | AB67: =IF(Table_query__64[[#This Row],[Project status]]=Table_query__64[[#This Row],[Project Status Check]],"OK","NOK") -> OK | AC67: =IF(Table_query__64[[#This Row],[PM]]=Table_query__64[[#This Row],[PM Check]],"OK","NOK") -> OK | AD67: =IF(Table_query__64[[#This Row],[PP]]=Table_query__64[[#This Row],[Pilot Check]],"OK","NOK") -> NOK
A68: O3515 | B68: Blommer Chocolate | C68: R&M Project Admin Work | D68: IPS USA | E68: Food & Beverages | F68: Work in progress | G68: 46048.042 | I68: Mark Sensenig | J68: Mark Sensenig | L68: Project Management;#1 | M68: Lump sum | N68: Q9135 | O68: 0.1 | P68: 27216 | Q68: 2026 | T68: 2896 | U68: O3515 Blommer Chocolate R&M Project Admin Work | V68: Item | W68: sites/Activity/Lists/GroupIPSProjects | X68: =VLOOKUP(Table_query__64[[#This Row],[Nr]],'MyTracker Export'!A:P,'MyTracker Export'!$P$1,FALSE) -> Work in progress | Y68: =VLOOKUP(Table_query__64[[#This Row],[Nr]],'MyTracker Export'!A:Z,'MyTracker Export'!$Z$1,FALSE) -> Mark Sensenig | Z68: =VLOOKUP(Table_query__64[[#This Row],[Nr]],'MyTracker Export'!A:AA,'MyTracker Export'!$AA$1,FALSE) -> Mark Sensenig | AB68: =IF(Table_query__64[[#This Row],[Project status]]=Table_query__64[[#This Row],[Project Status Check]],"OK","NOK") -> OK | AC68: =IF(Table_query__64[[#This Row],[PM]]=Table_query__64[[#This Row],[PM Check]],"OK","NOK") -> OK | AD68: =IF(Table_query__64[[#This Row],[PP]]=Table_query__64[[#This Row],[Pilot Check]],"OK","NOK") -> OK
A69: O3514 | B69: SNIM | C69: EM4511_Excellence Projets | D69: IAPS Tunisia | E69: Primary & Metals | F69: Work in progress | G69: 46045.042 | I69: Wissem Bensaid | J69: Wissem Bensaid | L69: Project Management;#1 | M69: Lump sum | N69: Q9129 | O69: 0 | P69: 87686.25 | Q69: 2026 | T69: 2895 | U69: O3514 SNIM EM4511_Excellence Projets | V69: Item | W69: sites/Activity/Lists/GroupIPSProjects | X69: =VLOOKUP(Table_query__64[[#This Row],[Nr]],'MyTracker Export'!A:P,'MyTracker Export'!$P$1,FALSE) -> Work in progress | Y69: =VLOOKUP(Table_query__64[[#This Row],[Nr]],'MyTracker Export'!A:Z,'MyTracker Export'!$Z$1,FALSE) -> Bacem CHARMI | Z69: =VLOOKUP(Table_query__64[[#This Row],[Nr]],'MyTracker Export'!A:AA,'MyTracker Export'!$AA$1,FALSE) -> Wissem Bensaid | AB69: =IF(Table_query__64[[#This Row],[Project status]]=Table_query__64[[#This Row],[Project Status Check]],"OK","NOK") -> OK | AC69: =IF(Table_query__64[[#This Row],[PM]]=Table_query__64[[#This Row],[PM Check]],"OK","NOK") -> NOK | AD69: =IF(Table_query__64[[#This Row],[PP]]=Table_query__64[[#This Row],[Pilot Check]],"OK","NOK") -> OK
A70: O3513 | B70: Digital Realty | C70: BRU1 - Project Support 2026 | D70: IPS Belgium | E70: Buildings | F70: Work in progress | G70: 46045.042 | I70: Jurgen Van Den Driessche | J70: Bram Puttemans | K70: Delphine Myllecan | L70: Project Management;#1;#Safety & Site Supervision;#78 | M70: Reimbursable | N70: Q9092 | O70: 2000000 | P70: 46440 | Q70: 2026 | T70: 2894 | U70: O3513 Digital Realty BRU1 - Project Support 2026 | V70: Item | W70: sites/Activity/Lists/GroupIPSProjects | X70: =VLOOKUP(Table_query__64[[#This Row],[Nr]],'MyTracker Export'!A:P,'MyTracker Export'!$P$1,FALSE) -> Work in progress | Y70: =VLOOKUP(Table_query__64[[#This Row],[Nr]],'MyTracker Export'!A:Z,'MyTracker Export'!$Z$1,FALSE) -> Jurgen Van Den Driessche | Z70: =VLOOKUP(Table_query__64[[#This Row],[Nr]],'MyTracker Export'!A:AA,'MyTracker Export'!$AA$1,FALSE) -> Bram Puttemans | AB70: =IF(Table_query__64[[#This Row],[Project status]]=Table_query__64[[#This Row],[Project Status Check]],"OK","NOK") -> OK | AC70: =IF(Table_query__64[[#This Row],[PM]]=Table_query__64[[#This Row],[PM Check]],"OK","NOK") -> OK | AD70: =IF(Table_query__64[[#This Row],[PP]]=Table_query__64[[#This Row],[Pilot Check]],"OK","NOK") -> OK
A71: O3512 | B71: UNIVERSAL MUSIC | C71: PM - Paseo Delicias 61 | D71: IPS Spain | E71: Buildings | F71: Work in progress | G71: 46044.042 | I71: Cristina Rubio Rodríguez | J71: Juan Juarez | L71: Project Management;#1;#Construction Management;#42 | M71: Lump sum | N71: Q8955 | O71: 2 | P71: 103509 | Q71: 2026 | T71: 2893 | U71: O3512 UNIVERSAL MUSIC PM - Paseo Delicias 61 | V71: Item | W71: sites/Activity/Lists/GroupIPSProjects | X71: =VLOOKUP(Table_query__64[[#This Row],[Nr]],'MyTracker Export'!A:P,'MyTracker Export'!$P$1,FALSE) -> Work in progress | Y71: =VLOOKUP(Table_query__64[[#This Row],[Nr]],'MyTracker Export'!A:Z,'MyTracker Export'!$Z$1,FALSE) -> Cristina Rubio Rodríguez | Z71: =VLOOKUP(Table_query__64[[#This Row],[Nr]],'MyTracker Export'!A:AA,'MyTracker Export'!$AA$1,FALSE) -> Juan Juarez Quintana | AB71: =IF(Table_query__64[[#This Row],[Project status]]=Table_query__64[[#This Row],[Project Status Check]],"OK","NOK") -> OK | AC71: =IF(Table_query__64[[#This Row],[PM]]=Table_query__64[[#This Row],[PM Check]],"OK","NOK") -> OK | AD71: =IF(Table_query__64[[#This Row],[PP]]=Table_query__64[[#This Row],[Pilot Check]],"OK","NOK") -> NOK
A72: O3511 | B72: UNIVERSAL MUSIC | C72: ART HOUSE | D72: IPS Spain | E72: Buildings | F72: Work in progress | G72: 46044.042 | I72: Cristina Rubio Rodríguez | J72: Juan Juarez | L72: Project Management;#1;#Consulting;#2;#Construction Management;#42 | M72: Lump sum | N72: Q9073 | O72: 2 | P72: 72931.5 | Q72: 2026 | T72: 2892 | U72: O3511 UNIVERSAL MUSIC ART HOUSE | V72: Item | W72: sites/Activity/Lists/GroupIPSProjects | X72: =VLOOKUP(Table_query__64[[#This Row],[Nr]],'MyTracker Export'!A:P,'MyTracker Export'!$P$1,FALSE) -> Work in progress | Y72: =VLOOKUP(Table_query__64[[#This Row],[Nr]],'MyTracker Export'!A:Z,'MyTracker Export'!$Z$1,FALSE) -> Cristina Rubio Rodríguez | Z72: =VLOOKUP(Table_query__64[[#This Row],[Nr]],'MyTracker Export'!A:AA,'MyTracker Export'!$AA$1,FALSE) -> Juan Juarez Quintana | AB72: =IF(Table_query__64[[#This Row],[Project status]]=Table_query__64[[#This Row],[Project Status Check]],"OK","NOK") -> OK | AC72: =IF(Table_query__64[[#This Row],[PM]]=Table_query__64[[#This Row],[PM Check]],"OK","NOK") -> OK | AD72: =IF(Table_query__64[[#This Row],[PP]]=Table_query__64[[#This Row],[Pilot Check]],"OK","NOK") -> NOK
A73: O3510 | B73: AMA Group | C73: EM4819_Etude Bâtiment | D73: IAPS Tunisia | E73: Buildings | F73: Work in progress | G73: 46044.042 | I73: Wissem Bensaid | J73: Wissem Bensaid | L73: Project Management;#1;#Engineering;#7;#HVAC Engineering;#14;#Utilities Engineering;#19 | M73: Lump sum | N73: Q9127 | O73: 0 | P73: 75000 | Q73: 2026 | T73: 2891 | U73: O3510 AMA Group EM4819_Etude Bâtiment | V73: Item | W73: sites/Activity/Lists/GroupIPSProjects | X73: =VLOOKUP(Table_query__64[[#This Row],[Nr]],'MyTracker Export'!A:P,'MyTracker Export'!$P$1,FALSE) -> Work in progress | Y73: =VLOOKUP(Table_query__64[[#This Row],[Nr]],'MyTracker Export'!A:Z,'MyTracker Export'!$Z$1,FALSE) -> Habib Kharrat | Z73: =VLOOKUP(Table_query__64[[#This Row],[Nr]],'MyTracker Export'!A:AA,'MyTracker Export'!$AA$1,FALSE) -> Wissem Bensaid | AB73: =IF(Table_query__64[[#This Row],[Project status]]=Table_query__64[[#This Row],[Project Status Check]],"OK","NOK") -> OK | AC73: =IF(Table_query__64[[#This Row],[PM]]=Table_query__64[[#This Row],[PM Check]],"OK","NOK") -> NOK | AD73: =IF(Table_query__64[[#This Row],[PP]]=Table_query__64[[#This Row],[Pilot Check]],"OK","NOK") -> OK
A74: O3509 | B74: TPS | C74: EM4714_Site Visit | D74: IAPS Tunisia | E74: Chemicals | F74: Work in progress | G74: 46044.042 | I74: Wissem Bensaid | J74: Wissem Bensaid | L74: Project Management;#1 | M74: Lump sum | N74: Q9126 | O74: 0 | P74: 2864.86 | Q74: 2026 | T74: 2890 | U74: O3509 TPS EM4714_Site Visit | V74: Item | W74: sites/Activity/Lists/GroupIPSProjects | X74: =VLOOKUP(Table_query__64[[#This Row],[Nr]],'MyTracker Export'!A:P,'MyTracker Export'!$P$1,FALSE) -> Work in progress | Y74: =VLOOKUP(Table_query__64[[#This Row],[Nr]],'MyTracker Export'!A:Z,'MyTracker Export'!$Z$1,FALSE) -> Zied Maghrebi | Z74: =VLOOKUP(Table_query__64[[#This Row],[Nr]],'MyTracker Export'!A:AA,'MyTracker Export'!$AA$1,FALSE) -> Wissem Bensaid | AB74: =IF(Table_query__64[[#This Row],[Project status]]=Table_query__64[[#This Row],[Project Status Check]],"OK","NOK") -> OK | AC74: =IF(Table_query__64[[#This Row],[PM]]=Table_query__64[[#This Row],[PM Check]],"OK","NOK") -> NOK | AD74: =IF(Table_query__64[[#This Row],[PP]]=Table_query__64[[#This Row],[Pilot Check]],"OK","NOK") -> OK
A75: O3508 | B75: Alsawaed Libya | C75: EM4693_modification Tank | D75: IAPS Tunisia | E75: Chemicals | F75: Work in progress | G75: 46044.042 | I75: Wissem Bensaid | J75: Wissem Bensaid | L75: Project Management;#1;#Engineering;#7;#Mechanical Engineering;#15 | M75: Lump sum | N75: Q9125 | O75: 0 | P75: 7296 | Q75: 2026 | T75: 2889 | U75: O3508 Alsawaed Libya EM4693_modification Tank | V75: Item | W75: sites/Activity/Lists/GroupIPSProjects | X75: =VLOOKUP(Table_query__64[[#This Row],[Nr]],'MyTracker Export'!A:P,'MyTracker Export'!$P$1,FALSE) -> Work in progress | Y75: =VLOOKUP(Table_query__64[[#This Row],[Nr]],'MyTracker Export'!A:Z,'MyTracker Export'!$Z$1,FALSE) -> Montassar Gharsallah | Z75: =VLOOKUP(Table_query__64[[#This Row],[Nr]],'MyTracker Export'!A:AA,'MyTracker Export'!$AA$1,FALSE) -> Wissem Bensaid | AB75: =IF(Table_query__64[[#This Row],[Project status]]=Table_query__64[[#This Row],[Project Status Check]],"OK","NOK") -> OK | AC75: =IF(Table_query__64[[#This Row],[PM]]=Table_query__64[[#This Row],[PM Check]],"OK","NOK") -> NOK | AD75: =IF(Table_query__64[[#This Row],[PP]]=Table_query__64[[#This Row],[Pilot Check]],"OK","NOK") -> OK
A76: O3507 | B76: BARRY CALLEBAUT (IVORY COAST) | C76: EM4721_PM Service | D76: IAPS Tunisia | E76: Food & Beverages | F76: Work in progress | G76: 46044.042 | I76: Wissem Bensaid | J76: Wissem Bensaid | L76: Project Management;#1;#Construction Management;#42 | M76: Lump sum | N76: Q9124 | O76: 0 | P76: 33088 | Q76: 2026 | T76: 2888 | U76: O3507 BARRY EM4721_PM Service | V76: Item | W76: sites/Activity/Lists/GroupIPSProjects | X76: =VLOOKUP(Table_query__64[[#This Row],[Nr]],'MyTracker Export'!A:P,'MyTracker Export'!$P$1,FALSE) -> Work in progress | Y76: =VLOOKUP(Table_query__64[[#This Row],[Nr]],'MyTracker Export'!A:Z,'MyTracker Export'!$Z$1,FALSE) -> Bilel Tajouri | Z76: =VLOOKUP(Table_query__64[[#This Row],[Nr]],'MyTracker Export'!A:AA,'MyTracker Export'!$AA$1,FALSE) -> Wissem Bensaid | AB76: =IF(Table_query__64[[#This Row],[Project status]]=Table_query__64[[#This Row],[Project Status Check]],"OK","NOK") -> OK | AC76: =IF(Table_query__64[[#This Row],[PM]]=Table_query__64[[#This Row],[PM Check]],"OK","NOK") -> NOK | AD76: =IF(Table_query__64[[#This Row],[PP]]=Table_query__64[[#This Row],[Pilot Check]],"OK","NOK") -> OK
A77: O3506 | B77: PETROLEAD | C77: EM4790_Tender Support | D77: IAPS Tunisia | E77: Chemicals | F77: Work in progress | G77: 46044.042 | I77: Wissem Bensaid | J77: Wissem Bensaid | L77: Project Management;#1 | M77: Lump sum | N77: Q9123 | O77: 0 | P77: 4800 | Q77: 2026 | T77: 2887 | U77: O3506 PETROLEAD EM4790_Tender Support | V77: Item | W77: sites/Activity/Lists/GroupIPSProjects | X77: =VLOOKUP(Table_query__64[[#This Row],[Nr]],'MyTracker Export'!A:P,'MyTracker Export'!$P$1,FALSE) -> Work in progress | Y77: =VLOOKUP(Table_query__64[[#This Row],[Nr]],'MyTracker Export'!A:Z,'MyTracker Export'!$Z$1,FALSE) -> Walim JRIBI | Z77: =VLOOKUP(Table_query__64[[#This Row],[Nr]],'MyTracker Export'!A:AA,'MyTracker Export'!$AA$1,FALSE) -> Wissem Bensaid | AB77: =IF(Table_query__64[[#This Row],[Project status]]=Table_query__64[[#This Row],[Project Status Check]],"OK","NOK") -> OK | AC77: =IF(Table_query__64[[#This Row],[PM]]=Table_query__64[[#This Row],[PM Check]],"OK","NOK") -> NOK | AD77: =IF(Table_query__64[[#This Row],[PP]]=Table_query__64[[#This Row],[Pilot Check]],"OK","NOK") -> OK
A78: O3505 | B78: YAZAKI TUNISIA S.A. | C78: EM4730_Etude cuisine | D78: IAPS Tunisia | E78: Primary & Metals | F78: Work in progress | G78: 46043.042 | I78: Wissem Bensaid | J78: Wissem Bensaid | L78: Project Management;#1;#Engineering;#7;#HVAC Engineering;#14;#Utilities Engineering;#19 | M78: Lump sum | N78: Q9117 | O78: 0 | P78: 18500 | Q78: 2026 | T78: 2886 | U78: O3505 YAZAKI TUNISIA S.A. EM4730_Etude cuisine | V78: Item | W78: sites/Activity/Lists/GroupIPSProjects | X78: =VLOOKUP(Table_query__64[[#This Row],[Nr]],'MyTracker Export'!A:P,'MyTracker Export'!$P$1,FALSE) -> Work in progress | Y78: =VLOOKUP(Table_query__64[[#This Row],[Nr]],'MyTracker Export'!A:Z,'MyTracker Export'!$Z$1,FALSE) -> AZIZ HENTATI | Z78: =VLOOKUP(Table_query__64[[#This Row],[Nr]],'MyTracker Export'!A:AA,'MyTracker Export'!$AA$1,FALSE) -> Wissem Bensaid | AB78: =IF(Table_query__64[[#This Row],[Project status]]=Table_query__64[[#This Row],[Project Status Check]],"OK","NOK") -> OK | AC78: =IF(Table_query__64[[#This Row],[PM]]=Table_query__64[[#This Row],[PM Check]],"OK","NOK") -> NOK | AD78: =IF(Table_query__64[[#This Row],[PP]]=Table_query__64[[#This Row],[Pilot Check]],"OK","NOK") -> OK
A79: O3504 | B79: CBRE - Global Workplace Solutions | C79: DMZR | D79: IPS Belgium | E79: Buildings | F79: Work in progress | G79: 46043.042 | I79: Audric Jeanne | J79: Karel De Swert | K79: Céline Lechado | L79: Project Management;#1;#Engineering;#7;#HVAC Engineering;#14 | M79: Lump sum | N79: Q9102 | O79: 1 | P79: 12072 | Q79: 2026 | T79: 2884 | U79: O3504 CBRE DMZR | V79: Item | W79: sites/Activity/Lists/GroupIPSProjects | X79: =VLOOKUP(Table_query__64[[#This Row],[Nr]],'MyTracker Export'!A:P,'MyTracker Export'!$P$1,FALSE) -> Work in progress | Y79: =VLOOKUP(Table_query__64[[#This Row],[Nr]],'MyTracker Export'!A:Z,'MyTracker Export'!$Z$1,FALSE) -> Audric Jeanne | Z79: =VLOOKUP(Table_query__64[[#This Row],[Nr]],'MyTracker Export'!A:AA,'MyTracker Export'!$AA$1,FALSE) -> Karel De Swert | AB79: =IF(Table_query__64[[#This Row],[Project status]]=Table_query__64[[#This Row],[Project Status Check]],"OK","NOK") -> OK | AC79: =IF(Table_query__64[[#This Row],[PM]]=Table_query__64[[#This Row],[PM Check]],"OK","NOK") -> OK | AD79: =IF(Table_query__64[[#This Row],[PP]]=Table_query__64[[#This Row],[Pilot Check]],"OK","NOK") -> OK
A80: O3503 | B80: GB Foods, Spain | C80: MasterPlan | D80: IPS Spain | E80: Food & Beverages | F80: Work in progress | G80: 46041.042 | I80: Begona Soto | J80: Carlos Bravo Fernandez | L80: Project Management;#1;#Consulting;#2;#Architecture;#5;#Engineering;#7;#Utilities Engineering;#19;#Masterplan;#66 | M80: Lump sum | N80: Spain MasterPlan, Q9075 | O80: 0 | P80: 87258.45 | Q80: 2026 | T80: 2883 | U80: O3503 GB Foods Spain MasterPlan | V80: Item | W80: sites/Activity/Lists/GroupIPSProjects | X80: =VLOOKUP(Table_query__64[[#This Row],[Nr]],'MyTracker Export'!A:P,'MyTracker Export'!$P$1,FALSE) -> Work in progress | Y80: =VLOOKUP(Table_query__64[[#This Row],[Nr]],'MyTracker Export'!A:Z,'MyTracker Export'!$Z$1,FALSE) -> Begona Soto | Z80: =VLOOKUP(Table_query__64[[#This Row],[Nr]],'MyTracker Export'!A:AA,'MyTracker Export'!$AA$1,FALSE) -> Carlos Bravo Fernández | AB80: =IF(Table_query__64[[#This Row],[Project status]]=Table_query__64[[#This Row],[Project Status Check]],"OK","NOK") -> OK | AC80: =IF(Table_query__64[[#This Row],[PM]]=Table_query__64[[#This Row],[PM Check]],"OK","NOK") -> OK | AD80: =IF(Table_query__64[[#This Row],[PP]]=Table_query__64[[#This Row],[Pilot Check]],"OK","NOK") -> NOK
A81: O3502 | B81: SynPet | C81: GF Investm. Risk evaluation | D81: Group-IPS | E81: Chemicals | F81: Finished | G81: 46041.042 | H81: 46092.042 | I81: Alfredo Bartolome | J81: Carlos Bravo Fernandez | K81: Delphine Myllecan | L81: Consulting;#2 | M81: Lump sum | N81: Q9109 | O81: 256 | P81: 6685.62 | Q81: 2026 | R81: 2026 | T81: 2882 | U81: O3502 SynPet GF Investm. Risk evaluation | V81: Item | W81: sites/Activity/Lists/GroupIPSProjects | X81: =VLOOKUP(Table_query__64[[#This Row],[Nr]],'MyTracker Export'!A:P,'MyTracker Export'!$P$1,FALSE) -> Finished | Y81: =VLOOKUP(Table_query__64[[#This Row],[Nr]],'MyTracker Export'!A:Z,'MyTracker Export'!$Z$1,FALSE) -> Alfredo Bartolome | Z81: =VLOOKUP(Table_query__64[[#This Row],[Nr]],'MyTracker Export'!A:AA,'MyTracker Export'!$AA$1,FALSE) -> Carlos Bravo Fernández | AB81: =IF(Table_query__64[[#This Row],[Project status]]=Table_query__64[[#This Row],[Project Status Check]],"OK","NOK") -> OK | AC81: =IF(Table_query__64[[#This Row],[PM]]=Table_query__64[[#This Row],[PM Check]],"OK","NOK") -> OK | AD81: =IF(Table_query__64[[#This Row],[PP]]=Table_query__64[[#This Row],[Pilot Check]],"OK","NOK") -> NOK
A82: O3501 | B82: NLMK La Louviere | C82: Airtable Implementation | D82: IPS Belgium | E82: Primary & Metals | F82: Finished | G82: 45931.083 | H82: 46081.042 | I82: Irene Martínez Margallo | J82: Damien Hemmeryckx | K82: Amandyne Rosart | L82: Project Management;#1 | M82: Reimbursable | N82: Q9108 | O82: 1000 | P82: 145462.8 | Q82: 2025 | R82: 2026 | T82: 2881 | U82: O3501 NLMK La Louviere Airtable Implementation | V82: Item | W82: sites/Activity/Lists/GroupIPSProjects | X82: =VLOOKUP(Table_query__64[[#This Row],[Nr]],'MyTracker Export'!A:P,'MyTracker Export'!$P$1,FALSE) -> Finished | Y82: =VLOOKUP(Table_query__64[[#This Row],[Nr]],'MyTracker Export'!A:Z,'MyTracker Export'!$Z$1,FALSE) -> Irene Martínez Margallo | Z82: =VLOOKUP(Table_query__64[[#This Row],[Nr]],'MyTracker Export'!A:AA,'MyTracker Export'!$AA$1,FALSE) -> Damien Hemmeryckx | AB82: =IF(Table_query__64[[#This Row],[Project status]]=Table_query__64[[#This Row],[Project Status Check]],"OK","NOK") -> OK | AC82: =IF(Table_query__64[[#This Row],[PM]]=Table_query__64[[#This Row],[PM Check]],"OK","NOK") -> OK | AD82: =IF(Table_query__64[[#This Row],[PP]]=Table_query__64[[#This Row],[Pilot Check]],"OK","NOK") -> OK
A83: O3500 | B83: DSM-firmenich Seclin | C83: Construction Management | D83: IPS France | E83: Food & Beverages | F83: Work in progress | G83: 46038.042 | I83: Francois Casteleyn | J83: Adrien Ongenae | K83: Delphine Myllecan | L83: Project Management;#1;#Construction Management;#42 | M83: Reimbursable | N83: Q9060 | O83: 20000000 | P83: 294300 | Q83: 2026 | T83: 2880 | U83: O3500 DSM-firmenich Seclin Construction Management | V83: Item | W83: sites/Activity/Lists/GroupIPSProjects | X83: =VLOOKUP(Table_query__64[[#This Row],[Nr]],'MyTracker Export'!A:P,'MyTracker Export'!$P$1,FALSE) -> Work in progress | Y83: =VLOOKUP(Table_query__64[[#This Row],[Nr]],'MyTracker Export'!A:Z,'MyTracker Export'!$Z$1,FALSE) -> François Casteleyn | Z83: =VLOOKUP(Table_query__64[[#This Row],[Nr]],'MyTracker Export'!A:AA,'MyTracker Export'!$AA$1,FALSE) -> Adrien Ongenae | AB83: =IF(Table_query__64[[#This Row],[Project status]]=Table_query__64[[#This Row],[Project Status Check]],"OK","NOK") -> OK | AC83: =IF(Table_query__64[[#This Row],[PM]]=Table_query__64[[#This Row],[PM Check]],"OK","NOK") -> NOK | AD83: =IF(Table_query__64[[#This Row],[PP]]=Table_query__64[[#This Row],[Pilot Check]],"OK","NOK") -> OK
A84: O3499 | B84: EDHINOR SA | C84: Renders EDHINOR BOCM | D84: Arquid | E84: Buildings | F84: Work in progress | G84: 46037.042 | I84: Ricardo Roda | J84: Maximiliano Martin Parra | K84: Yasmine Ben Rhaiem | L84: Architecture;#5 | M84: Lump sum | N84: Q9101 | O84: 1 | P84: 1000.69 | Q84: 2026 | T84: 2879 | U84: O3499 EDHINOR SA Renders EDHINOR BOCM | V84: Item | W84: sites/Activity/Lists/GroupIPSProjects | X84: =VLOOKUP(Table_query__64[[#This Row],[Nr]],'MyTracker Export'!A:P,'MyTracker Export'!$P$1,FALSE) -> Work in progress | Y84: =VLOOKUP(Table_query__64[[#This Row],[Nr]],'MyTracker Export'!A:Z,'MyTracker Export'!$Z$1,FALSE) -> Ricardo Roda | Z84: =VLOOKUP(Table_query__64[[#This Row],[Nr]],'MyTracker Export'!A:AA,'MyTracker Export'!$AA$1,FALSE) -> Maximiliano Martin Parra | AB84: =IF(Table_query__64[[#This Row],[Project status]]=Table_query__64[[#This Row],[Project Status Check]],"OK","NOK") -> OK | AC84: =IF(Table_query__64[[#This Row],[PM]]=Table_query__64[[#This Row],[PM Check]],"OK","NOK") -> OK | AD84: =IF(Table_query__64[[#This Row],[PP]]=Table_query__64[[#This Row],[Pilot Check]],"OK","NOK") -> OK
A85: O3498 | B85: Sergio Diez | C85: LPO Valdetorres 11 | D85: Arquid | E85: Buildings | F85: Work in progress | G85: 46037.042 | H85: 46052.042 | I85: Ricardo Roda | J85: Juan Juarez | K85: Yasmine Ben Rhaiem | L85: Architecture;#5 | M85: Lump sum | N85: Q9100 | O85: 1 | P85: 8034.26 | Q85: 2026 | R85: 2026 | T85: 2878 | U85: O3498 Sergio Diez LPO Valdetorres 11 | V85: Item | W85: sites/Activity/Lists/GroupIPSProjects | X85: =VLOOKUP(Table_query__64[[#This Row],[Nr]],'MyTracker Export'!A:P,'MyTracker Export'!$P$1,FALSE) -> Work in progress | Y85: =VLOOKUP(Table_query__64[[#This Row],[Nr]],'MyTracker Export'!A:Z,'MyTracker Export'!$Z$1,FALSE) -> Ricardo Roda | Z85: =VLOOKUP(Table_query__64[[#This Row],[Nr]],'MyTracker Export'!A:AA,'MyTracker Export'!$AA$1,FALSE) -> Juan Juarez Quintana | AB85: =IF(Table_query__64[[#This Row],[Project status]]=Table_query__64[[#This Row],[Project Status Check]],"OK","NOK") -> OK | AC85: =IF(Table_query__64[[#This Row],[PM]]=Table_query__64[[#This Row],[PM Check]],"OK","NOK") -> OK | AD85: =IF(Table_query__64[[#This Row],[PP]]=Table_query__64[[#This Row],[Pilot Check]],"OK","NOK") -> NOK
A86: O3497 | B86: John Cockerill SA | C86: JC_AFS_Site supp_Munich DE | D86: IPS Belgium | E86: Chemicals | F86: Work in progress | G86: 46035.042 | I86: Jurgen Van Den Driessche | J86: Peter Holvoet | K86: Sophie Saussu | L86: Project Management;#1;#Construction Management;#42 | M86: Lump sum | N86: Q9063 | O86: 2 | P86: 109980 | Q86: 2026 | T86: 2877 | U86: O3497 John Cockerill SA JC_AFS_Site supp_Munich DE | V86: Item | W86: sites/Activity/Lists/GroupIPSProjects | X86: =VLOOKUP(Table_query__64[[#This Row],[Nr]],'MyTracker Export'!A:P,'MyTracker Export'!$P$1,FALSE) -> Work in progress | Y86: =VLOOKUP(Table_query__64[[#This Row],[Nr]],'MyTracker Export'!A:Z,'MyTracker Export'!$Z$1,FALSE) -> Jurgen Van Den Driessche | Z86: =VLOOKUP(Table_query__64[[#This Row],[Nr]],'MyTracker Export'!A:AA,'MyTracker Export'!$AA$1,FALSE) -> Peter Holvoet | AB86: =IF(Table_query__64[[#This Row],[Project status]]=Table_query__64[[#This Row],[Project Status Check]],"OK","NOK") -> OK | AC86: =IF(Table_query__64[[#This Row],[PM]]=Table_query__64[[#This Row],[PM Check]],"OK","NOK") -> OK | AD86: =IF(Table_query__64[[#This Row],[PP]]=Table_query__64[[#This Row],[Pilot Check]],"OK","NOK") -> OK
A87: O3496 | B87: AEFA Agronutrientes | C87: CBAM training | D87: Group-IPS | E87: Chemicals | F87: Finished | G87: 46035.042 | H87: 46079.042 | I87: Maria Romero | J87: Maria Romero | K87: Céline Lechado | M87: Lump sum | N87: Q9095 | O87: 0.1 | P87: 450 | Q87: 2026 | R87: 2026 | T87: 2875 | U87: O3496 AEFA Agronutrientes CBAM training | V87: Item | W87: sites/Activity/Lists/GroupIPSProjects | X87: =VLOOKUP(Table_query__64[[#This Row],[Nr]],'MyTracker Export'!A:P,'MyTracker Export'!$P$1,FALSE) -> Finished | Y87: =VLOOKUP(Table_query__64[[#This Row],[Nr]],'MyTracker Export'!A:Z,'MyTracker Export'!$Z$1,FALSE) -> Maria Romero | Z87: =VLOOKUP(Table_query__64[[#This Row],[Nr]],'MyTracker Export'!A:AA,'MyTracker Export'!$AA$1,FALSE) -> Maria Romero | AB87: =IF(Table_query__64[[#This Row],[Project status]]=Table_query__64[[#This Row],[Project Status Check]],"OK","NOK") -> OK | AC87: =IF(Table_query__64[[#This Row],[PM]]=Table_query__64[[#This Row],[PM Check]],"OK","NOK") -> OK | AD87: =IF(Table_query__64[[#This Row],[PP]]=Table_query__64[[#This Row],[Pilot Check]],"OK","NOK") -> OK
A88: O3495 | B88: Evonik Antwerpen N.V. | C88: HK D779 Feasability | D88: IPS Belgium | E88: Chemicals | F88: Finished | G88: 46035.042 | H88: 46082.042 | I88: Sunny Yip | J88: Peter Holvoet | K88: Sophie Saussu | L88: Project Management;#1;#Engineering;#7;#Project Assistance;#73 | M88: Reimbursable | N88: Q9058 | O88: 0.5 | P88: 16470.79 | Q88: 2026 | R88: 2026 | T88: 2876 | U88: O3495 Evonik Antwerpen N.V. HK D779 Feasability | V88: Item | W88: sites/Activity/Lists/GroupIPSProjects | X88: =VLOOKUP(Table_query__64[[#This Row],[Nr]],'MyTracker Export'!A:P,'MyTracker Export'!$P$1,FALSE) -> Finished | Y88: =VLOOKUP(Table_query__64[[#This Row],[Nr]],'MyTracker Export'!A:Z,'MyTracker Export'!$Z$1,FALSE) -> Sunny Yip | Z88: =VLOOKUP(Table_query__64[[#This Row],[Nr]],'MyTracker Export'!A:AA,'MyTracker Export'!$AA$1,FALSE) -> Peter Holvoet | AB88: =IF(Table_query__64[[#This Row],[Project status]]=Table_query__64[[#This Row],[Project Status Check]],"OK","NOK") -> OK | AC88: =IF(Table_query__64[[#This Row],[PM]]=Table_query__64[[#This Row],[PM Check]],"OK","NOK") -> OK | AD88: =IF(Table_query__64[[#This Row],[PP]]=Table_query__64[[#This Row],[Pilot Check]],"OK","NOK") -> OK
A89: O3494 | B89: ArcelorMittal Esch-Belval | C89: ATC Layout | D89: IPS Belgium | E89: Primary & Metals | F89: Work in progress | G89: 46031.042 | I89: Denis Remacle | J89: Denis Remacle | K89: Amandyne Rosart | L89: Engineering;#7 | M89: Reimbursable | N89: Q8913 | O89: 0.01 | P89: 140875.73 | Q89: 2026 | T89: 2874 | U89: O3494 ArcelorMittal Esch-Belval ATC Layout | V89: Item | W89: sites/Activity/Lists/GroupIPSProjects | X89: =VLOOKUP(Table_query__64[[#This Row],[Nr]],'MyTracker Export'!A:P,'MyTracker Export'!$P$1,FALSE) -> Work in progress | Y89: =VLOOKUP(Table_query__64[[#This Row],[Nr]],'MyTracker Export'!A:Z,'MyTracker Export'!$Z$1,FALSE) -> Denis Remacle | Z89: =VLOOKUP(Table_query__64[[#This Row],[Nr]],'MyTracker Export'!A:AA,'MyTracker Export'!$AA$1,FALSE) -> Denis Remacle | AB89: =IF(Table_query__64[[#This Row],[Project status]]=Table_query__64[[#This Row],[Project Status Check]],"OK","NOK") -> OK | AC89: =IF(Table_query__64[[#This Row],[PM]]=Table_query__64[[#This Row],[PM Check]],"OK","NOK") -> OK | AD89: =IF(Table_query__64[[#This Row],[PP]]=Table_query__64[[#This Row],[Pilot Check]],"OK","NOK") -> OK
A90: O3493 | B90: Carmeuse Lime & Stone (Headquarters) | C90: Davenport, IA CM Support | D90: IPS USA | E90: Primary & Metals | F90: Work in progress | G90: 46029.042 | I90: Pranay Pawar | J90: Mac Olean | L90: Project Management;#1;#Construction Management;#42 | M90: Reimbursable | N90: IA CM Support, Q9069 | O90: 0.01 | P90: 61250 | Q90: 2026 | T90: 2873 | U90: O3493 Carmeuse Davenport IA CM Support | V90: Item | W90: sites/Activity/Lists/GroupIPSProjects | X90: =VLOOKUP(Table_query__64[[#This Row],[Nr]],'MyTracker Export'!A:P,'MyTracker Export'!$P$1,FALSE) -> Work in progress | Y90: =VLOOKUP(Table_query__64[[#This Row],[Nr]],'MyTracker Export'!A:Z,'MyTracker Export'!$Z$1,FALSE) -> Pranay Pawar | Z90: =VLOOKUP(Table_query__64[[#This Row],[Nr]],'MyTracker Export'!A:AA,'MyTracker Export'!$AA$1,FALSE) -> Mac Olean | AB90: =IF(Table_query__64[[#This Row],[Project status]]=Table_query__64[[#This Row],[Project Status Check]],"OK","NOK") -> OK | AC90: =IF(Table_query__64[[#This Row],[PM]]=Table_query__64[[#This Row],[PM Check]],"OK","NOK") -> OK | AD90: =IF(Table_query__64[[#This Row],[PP]]=Table_query__64[[#This Row],[Pilot Check]],"OK","NOK") -> OK
A91: O3492 | B91: The Residential Club | C91: Libro de Estilo | D91: Arquid | E91: Buildings | F91: Work in progress | G91: 46029.042 | I91: Laura Cestau | J91: Laura Cestau | K91: Yasmine Ben Rhaiem | L91: Architecture;#5 | M91: Lump sum | N91: Q8826 | O91: 10 | P91: 15012 | Q91: 2026 | T91: 2872 | U91: O3492 The Residential Club Libro de Estilo | V91: Item | W91: sites/Activity/Lists/GroupIPSProjects | X91: =VLOOKUP(Table_query__64[[#This Row],[Nr]],'MyTracker Export'!A:P,'MyTracker Export'!$P$1,FALSE) -> Work in progress | Y91: =VLOOKUP(Table_query__64[[#This Row],[Nr]],'MyTracker Export'!A:Z,'MyTracker Export'!$Z$1,FALSE) -> Laura Cestau | Z91: =VLOOKUP(Table_query__64[[#This Row],[Nr]],'MyTracker Export'!A:AA,'MyTracker Export'!$AA$1,FALSE) -> Laura Cestau | AB91: =IF(Table_query__64[[#This Row],[Project status]]=Table_query__64[[#This Row],[Project Status Check]],"OK","NOK") -> OK | AC91: =IF(Table_query__64[[#This Row],[PM]]=Table_query__64[[#This Row],[PM Check]],"OK","NOK") -> OK | AD91: =IF(Table_query__64[[#This Row],[PP]]=Table_query__64[[#This Row],[Pilot Check]],"OK","NOK") -> OK
A92: O3491 | B92: Cargill GmbH Barby (Elbe) | C92: Pocketfilters Glucose Loading | D92: IPS Germany | E92: Food & Beverages | F92: Work in progress | G92: 46028.042 | I92: Mohamed Chedly Ben Ghorbel | J92: Fiete Heinrich | L92: Project Management;#1;#Architecture;#5;#Engineering;#7;#Piping Engineering;#16;#Engineering Coordination;#54 | M92: Lump sum | N92: Q8964 | O92: 0.5 | P92: 32000 | Q92: 2026 | T92: 2871 | U92: O3491 Cargill GmbH Barby (Elbe) Pocketfilters Glucose Loading | V92: Item | W92: sites/Activity/Lists/GroupIPSProjects | X92: =VLOOKUP(Table_query__64[[#This Row],[Nr]],'MyTracker Export'!A:P,'MyTracker Export'!$P$1,FALSE) -> Work in progress | Y92: =VLOOKUP(Table_query__64[[#This Row],[Nr]],'MyTracker Export'!A:Z,'MyTracker Export'!$Z$1,FALSE) -> Mohamed Chedly Ben Ghorbel | Z92: =VLOOKUP(Table_query__64[[#This Row],[Nr]],'MyTracker Export'!A:AA,'MyTracker Export'!$AA$1,FALSE) -> Fiete Heinrich | AB92: =IF(Table_query__64[[#This Row],[Project status]]=Table_query__64[[#This Row],[Project Status Check]],"OK","NOK") -> OK | AC92: =IF(Table_query__64[[#This Row],[PM]]=Table_query__64[[#This Row],[PM Check]],"OK","NOK") -> OK | AD92: =IF(Table_query__64[[#This Row],[PP]]=Table_query__64[[#This Row],[Pilot Check]],"OK","NOK") -> OK
A93: O3490 | B93: SCIF | C93: EM4716_EtudesEquipement | D93: IAPS Tunisia | E93: Chemicals | F93: Work in progress | G93: 46021.042 | I93: Wissem Bensaid | J93: Wissem Bensaid | L93: Project Management;#1;#Engineering;#7;#Mechanical Engineering;#15;#Piping Engineering;#16 | M93: Lump sum | N93: Q9084 | O93: 0 | P93: 38000 | Q93: 2025 | T93: 2870 | U93: O3490 SCIF EM4716_EtudesEquipement | V93: Item | W93: sites/Activity/Lists/GroupIPSProjects | X93: =VLOOKUP(Table_query__64[[#This Row],[Nr]],'MyTracker Export'!A:P,'MyTracker Export'!$P$1,FALSE) -> Work in progress | Y93: =VLOOKUP(Table_query__64[[#This Row],[Nr]],'MyTracker Export'!A:Z,'MyTracker Export'!$Z$1,FALSE) -> Bilel Khemakhem | Z93: =VLOOKUP(Table_query__64[[#This Row],[Nr]],'MyTracker Export'!A:AA,'MyTracker Export'!$AA$1,FALSE) -> Wissem Bensaid | AB93: =IF(Table_query__64[[#This Row],[Project status]]=Table_query__64[[#This Row],[Project Status Check]],"OK","NOK") -> OK | AC93: =IF(Table_query__64[[#This Row],[PM]]=Table_query__64[[#This Row],[PM Check]],"OK","NOK") -> NOK | AD93: =IF(Table_query__64[[#This Row],[PP]]=Table_query__64[[#This Row],[Pilot Check]],"OK","NOK") -> OK
A94: O3489 | B94: Lindt & Sprungli USA | C94: Lindt Kitchen 3D Modeling | D94: IPS USA | E94: Food & Beverages | F94: Work in progress | G94: 46020.042 | I94: Evan Bardinas | J94: Mark Sensenig | L94: Engineering;#7;#Piping Engineering;#16;#Engineering Coordination;#54 | M94: Lump sum | N94: Q9050 | O94: 2 | P94: 13824 | Q94: 2025 | T94: 2869 | U94: O3489 Lindt & Sprungli USA Lindt Kitchen 3D Modeling | V94: Item | W94: sites/Activity/Lists/GroupIPSProjects | X94: =VLOOKUP(Table_query__64[[#This Row],[Nr]],'MyTracker Export'!A:P,'MyTracker Export'!$P$1,FALSE) -> Work in progress | Y94: =VLOOKUP(Table_query__64[[#This Row],[Nr]],'MyTracker Export'!A:Z,'MyTracker Export'!$Z$1,FALSE) -> Evan Bardinas | Z94: =VLOOKUP(Table_query__64[[#This Row],[Nr]],'MyTracker Export'!A:AA,'MyTracker Export'!$AA$1,FALSE) -> Mark Sensenig | AB94: =IF(Table_query__64[[#This Row],[Project status]]=Table_query__64[[#This Row],[Project Status Check]],"OK","NOK") -> OK | AC94: =IF(Table_query__64[[#This Row],[PM]]=Table_query__64[[#This Row],[PM Check]],"OK","NOK") -> OK | AD94: =IF(Table_query__64[[#This Row],[PP]]=Table_query__64[[#This Row],[Pilot Check]],"OK","NOK") -> OK
A95: O3488 | B95: JESA | C95: EM4768_Etude Réservoir Daoui | D95: IAPS Tunisia | E95: Chemicals | F95: Work in progress | G95: 46016.042 | I95: Wissem Bensaid | J95: Wissem Bensaid | L95: Project Management;#1;#Engineering;#7;#Mechanical Engineering;#15;#Piping Engineering;#16;#Process Engineering;#17 | M95: Lump sum | N95: Q9062 | O95: 0 | P95: 90500 | Q95: 2025 | T95: 2868 | U95: O3488 JESA EM4768_Etude Réservoir Daoui | V95: Item | W95: sites/Activity/Lists/GroupIPSProjects | X95: =VLOOKUP(Table_query__64[[#This Row],[Nr]],'MyTracker Export'!A:P,'MyTracker Export'!$P$1,FALSE) -> Work in progress | Y95: =VLOOKUP(Table_query__64[[#This Row],[Nr]],'MyTracker Export'!A:Z,'MyTracker Export'!$Z$1,FALSE) -> Mansour Hamza | Z95: =VLOOKUP(Table_query__64[[#This Row],[Nr]],'MyTracker Export'!A:AA,'MyTracker Export'!$AA$1,FALSE) -> Wissem Bensaid | AB95: =IF(Table_query__64[[#This Row],[Project status]]=Table_query__64[[#This Row],[Project Status Check]],"OK","NOK") -> OK | AC95: =IF(Table_query__64[[#This Row],[PM]]=Table_query__64[[#This Row],[PM Check]],"OK","NOK") -> NOK | AD95: =IF(Table_query__64[[#This Row],[PP]]=Table_query__64[[#This Row],[Pilot Check]],"OK","NOK") -> OK
A96: O3487 | B96: TAKEDA (BELGIUM) | C96: OPUS-PED | D96: IPS Belgium | E96: Life Sciences | F96: Work in progress | G96: 46013.042 | I96: Nadège Herment | J96: Nicolas Dubois | K96: Amandyne Rosart | L96: Project Management;#1;#Engineering;#7 | M96: Reimbursable | N96: Q9056 | O96: 100 | P96: 235727.52 | Q96: 2025 | T96: 2867 | U96: O3487 TAKEDA (BELGIUM) OPUS-PED | V96: Item | W96: sites/Activity/Lists/GroupIPSProjects | X96: =VLOOKUP(Table_query__64[[#This Row],[Nr]],'MyTracker Export'!A:P,'MyTracker Export'!$P$1,FALSE) -> Work in progress | Y96: =VLOOKUP(Table_query__64[[#This Row],[Nr]],'MyTracker Export'!A:Z,'MyTracker Export'!$Z$1,FALSE) -> Nadège Herment | Z96: =VLOOKUP(Table_query__64[[#This Row],[Nr]],'MyTracker Export'!A:AA,'MyTracker Export'!$AA$1,FALSE) -> Nicolas Dubois | AB96: =IF(Table_query__64[[#This Row],[Project status]]=Table_query__64[[#This Row],[Project Status Check]],"OK","NOK") -> OK | AC96: =IF(Table_query__64[[#This Row],[PM]]=Table_query__64[[#This Row],[PM Check]],"OK","NOK") -> OK | AD96: =IF(Table_query__64[[#This Row],[PP]]=Table_query__64[[#This Row],[Pilot Check]],"OK","NOK") -> OK
A97: O3486 | B97: UNIVERSAL MUSIC | C97: MADNUN OFFICE UNIVERSAL | D97: IPS Spain | E97: Buildings | F97: Work in progress | G97: 46013.042 | I97: Iker Ruiz-Apilánez | J97: Cristina Rubio Rodríguez | K97: Yasmine Ben Rhaiem | L97: Project Management;#1;#Engineering;#7;#Construction Management;#42;#Engineering Coordination;#54 | M97: Lump sum | N97: Q9072 | O97: 2 | P97: 56132.1 | Q97: 2025 | T97: 2866 | U97: O3486 UNIVERSAL MUSIC MADNUN OFFICE UNIVERSAL | V97: Item | W97: sites/Activity/Lists/GroupIPSProjects | X97: =VLOOKUP(Table_query__64[[#This Row],[Nr]],'MyTracker Export'!A:P,'MyTracker Export'!$P$1,FALSE) -> Work in progress | Y97: =VLOOKUP(Table_query__64[[#This Row],[Nr]],'MyTracker Export'!A:Z,'MyTracker Export'!$Z$1,FALSE) -> Iker Ruiz | Z97: =VLOOKUP(Table_query__64[[#This Row],[Nr]],'MyTracker Export'!A:AA,'MyTracker Export'!$AA$1,FALSE) -> Cristina Rubio Rodríguez | AB97: =IF(Table_query__64[[#This Row],[Project status]]=Table_query__64[[#This Row],[Project Status Check]],"OK","NOK") -> OK | AC97: =IF(Table_query__64[[#This Row],[PM]]=Table_query__64[[#This Row],[PM Check]],"OK","NOK") -> NOK | AD97: =IF(Table_query__64[[#This Row],[PP]]=Table_query__64[[#This Row],[Pilot Check]],"OK","NOK") -> OK
A98: O3485 | B98: Carlsberg Supply Company AG | C98: Remplacement réseau enterré | D98: IPS France | E98: Food & Beverages | F98: Finished | G98: 46006.042 | H98: 46054.042 | I98: Andrew Delhaisse | J98: Pascal CORNUEZ | K98: Amandyne Rosart | L98: Project Management;#1;#Consulting;#2;#Architecture;#5;#Masterplan;#66 | M98: Reimbursable | N98: Q9044 | O98: 1000000 | P98: 5076.75 | Q98: 2025 | R98: 2026 | T98: 2865 | U98: O3485 Carlsberg Remplacement réseau enterré | V98: Item | W98: sites/Activity/Lists/GroupIPSProjects | X98: =VLOOKUP(Table_query__64[[#This Row],[Nr]],'MyTracker Export'!A:P,'MyTracker Export'!$P$1,FALSE) -> Finished | Y98: =VLOOKUP(Table_query__64[[#This Row],[Nr]],'MyTracker Export'!A:Z,'MyTracker Export'!$Z$1,FALSE) -> Andrew Delhaisse | Z98: =VLOOKUP(Table_query__64[[#This Row],[Nr]],'MyTracker Export'!A:AA,'MyTracker Export'!$AA$1,FALSE) -> Pascal Cornuez | AB98: =IF(Table_query__64[[#This Row],[Project status]]=Table_query__64[[#This Row],[Project Status Check]],"OK","NOK") -> OK | AC98: =IF(Table_query__64[[#This Row],[PM]]=Table_query__64[[#This Row],[PM Check]],"OK","NOK") -> OK | AD98: =IF(Table_query__64[[#This Row],[PP]]=Table_query__64[[#This Row],[Pilot Check]],"OK","NOK") -> OK
A99: O3484 | B99: Metinvest Adria SPA | C99: Hot-rolled coils | D99: Group-IPS | E99: Primary & Metals | F99: Work in progress | G99: 46006.042 | I99: Boris Krastev | J99: Marcos Delgado | K99: Amandyne Rosart | L99: Project Management;#1;#Project Assistance;#73 | M99: Reimbursable | N99: Q9016 | O99: 2600 | P99: 2092318.5 | Q99: 2025 | T99: 2864 | U99: O3484 Metinvest Adria SPA Hot-rolled coils | V99: Item | W99: sites/Activity/Lists/GroupIPSProjects | X99: =VLOOKUP(Table_query__64[[#This Row],[Nr]],'MyTracker Export'!A:P,'MyTracker Export'!$P$1,FALSE) -> Work in progress | Y99: =VLOOKUP(Table_query__64[[#This Row],[Nr]],'MyTracker Export'!A:Z,'MyTracker Export'!$Z$1,FALSE) -> Boris Krastev | Z99: =VLOOKUP(Table_query__64[[#This Row],[Nr]],'MyTracker Export'!A:AA,'MyTracker Export'!$AA$1,FALSE) -> Marcos Delgado Lopez | AB99: =IF(Table_query__64[[#This Row],[Project status]]=Table_query__64[[#This Row],[Project Status Check]],"OK","NOK") -> OK | AC99: =IF(Table_query__64[[#This Row],[PM]]=Table_query__64[[#This Row],[PM Check]],"OK","NOK") -> OK | AD99: =IF(Table_query__64[[#This Row],[PP]]=Table_query__64[[#This Row],[Pilot Check]],"OK","NOK") -> NOK
A100: O3483 | B100: Carmeuse S.A. | C100: EM4595_Mission EPCM | D100: IAPS Tunisia | E100: Primary & Metals | F100: Work in progress | G100: 46002.042 | I100: Wissem Bensaid | J100: Wissem Bensaid | L100: Project Management;#1;#Engineering;#7;#Utilities Engineering;#19;#Safety Engineering;#81 | M100: Lump sum | N100: Q9061 | O100: 0 | P100: 16983 | Q100: 2025 | T100: 2863 | U100: O3483 Carmeuse S.A. EM4595_Mission EPCM | V100: Item | W100: sites/Activity/Lists/GroupIPSProjects | X100: =VLOOKUP(Table_query__64[[#This Row],[Nr]],'MyTracker Export'!A:P,'MyTracker Export'!$P$1,FALSE) -> Work in progress | Y100: =VLOOKUP(Table_query__64[[#This Row],[Nr]],'MyTracker Export'!A:Z,'MyTracker Export'!$Z$1,FALSE) -> Ramzi MTIBAA | Z100: =VLOOKUP(Table_query__64[[#This Row],[Nr]],'MyTracker Export'!A:AA,'MyTracker Export'!$AA$1,FALSE) -> Wissem Bensaid | AB100: =IF(Table_query__64[[#This Row],[Project status]]=Table_query__64[[#This Row],[Project Status Check]],"OK","NOK") -> OK | AC100: =IF(Table_query__64[[#This Row],[PM]]=Table_query__64[[#This Row],[PM Check]],"OK","NOK") -> NOK | AD100: =IF(Table_query__64[[#This Row],[PP]]=Table_query__64[[#This Row],[Pilot Check]],"OK","NOK") -> OK
...

Sheet MyTracker Export
A1: 1 | B1: 2 | C1: 3 | D1: 4 | E1: 5 | F1: 6 | G1: 7 | H1: 8 | I1: 9 | J1: 10 | K1: 11 | L1: 12 | M1: 13 | N1: 14 | O1: 15 | P1: 16 | Q1: 17 | R1: 18 | S1: 19 | T1: 20 | U1: 21 | V1: 22 | W1: 23 | X1: 24 | Y1: 25 | Z1: 26 | AA1: 27
A2: ProjectNumber | B2: Title | C2: ProjectDescription | D2: ProjectManager | E2: ProjectPilot | F2: ProjectAssistant | G2: CustomerLookup | H2: ProjectFinType | I2: ProjectStartDate | J2: ProjectCloseDate | K2: LastScopeChange | L2: LastScopeChangeValue | M2: LastScopeChangeResponsible | N2: NrOfScopeChange | O2: LastScopeChangeIndex | P2: ProjectStatusLookup | Q2: AreaLookup | R2: IndustryLookup | S2: ServiceLookup | T2: LegalEntityLookup | U2: SubLegalEntityLookup | V2: QuotationNumber | W2: CapEx | X2: SumBaseWorkScopes | Y2: ReferenceSheetLink | Z2: Project Manager | AA2: Project Pilot
A3: O3581 | B3: PE1051_BESS Project | D3: istabrak.frikha@group-ips.com | E3: wissem.bensaid@group-ips.com | G3: GOPA | H3: Lump sum | I3: 46098 | K3: 46098 | L3: 172000 | M3: wissem.bensaid@group-ips.com | N3: 0 | O3: 0 | P3: Work in progress | R3: Chemicals | S3: Engineering|Project Management|HVAC Engineering|Utilities Engineering | T3: IAPS Tunisia | U3: IAPS Tunisia | V3: Q9253 | W3: 0 | X3: 172000 | Z3: =VLOOKUP(D3,'ZOHO Export'!$H:$W,16,FALSE) -> Istabrak Frikha | AA3: =VLOOKUP(E3,'ZOHO Export'!$H:$W,16,FALSE) -> Wissem Bensaid
A4: O3580 | B4: P&ID Update Nuts connection | D4: audric.jeanne@group-ips.com | E4: karel.de.swert@group-ips.com | G4: Cargill Chocolate Belgium NV (Mouscron) | H4: Lump sum | I4: 46098 | K4: 46098 | L4: 828.09 | M4: audric.jeanne@group-ips.com | N4: 0 | O4: 0 | P4: Work in progress | R4: Food & Beverages | S4: Engineering|Project Management | T4: IPS Belgium | U4: IPS Belgium|IAPS Tunisia | V4: Q9213 | W4: 10000 | X4: 828.09 | Z4: =VLOOKUP(D4,'ZOHO Export'!$H:$W,16,FALSE) -> Audric Jeanne | AA4: =VLOOKUP(E4,'ZOHO Export'!$H:$W,16,FALSE) -> Karel De Swert
A5: O3579 | B5: BLIP OFFICES | D5: laura.cestau@group-ips.com | E5: laura.cestau@group-ips.com | G5: BLIP | H5: Lump sum | I5: 46097 | K5: 46097 | L5: 33957 | M5: laura.cestau@group-ips.com | N5: 0 | O5: 0 | P5: Work in progress | R5: Buildings | S5: Architecture|Project Management|Author's Supervision | T5: Arquid | U5: IPS Belgium|IPS Spain|Arquid | V5: Q9076 | W5: 20 | X5: 33957 | Z5: =VLOOKUP(D5,'ZOHO Export'!$H:$W,16,FALSE) -> Laura Cestau | AA5: =VLOOKUP(E5,'ZOHO Export'!$H:$W,16,FALSE) -> Laura Cestau
A6: O3578 | B6: PE1049_Guebiba water | D6: anouar.trigui@group-ips.com | E6: wissem.bensaid@group-ips.com | G6: TPS | H6: Lump sum | I6: 46093 | K6: 46093 | L6: 88827.9 | M6: wissem.bensaid@group-ips.com | N6: 0 | O6: 0 | P6: Work in progress | R6: Chemicals | S6: Engineering|Project Management|Mechanical Engineering|Piping Engineering|Process Engineering|Civil engineering|Structural engineering | T6: IAPS Tunisia | U6: IAPS Tunisia | V6: Q9247 | W6: 0 | X6: 88827.9 | Z6: =VLOOKUP(D6,'ZOHO Export'!$H:$W,16,FALSE) -> Anouar Trigui | AA6: =VLOOKUP(E6,'ZOHO Export'!$H:$W,16,FALSE) -> Wissem Bensaid
A7: O3577 | B7: Magor Land Conversion | D7: natalia.martinez.nieto@group-ips.com | E7: natalia.martinez.nieto@group-ips.com | G7: Ab InBev EU HQ (BEL Leuven) | H7: Lump sum | I7: 46093 | K7: 46093 | L7: 4492.65 | M7: natalia.martinez.nieto@group-ips.com | N7: 0 | O7: 0 | P7: Work in progress | R7: Food & Beverages | S7: Architecture | T7: Group-IPS | U7: IPS UK | V7: Q9240 | X7: 4492.65 | Z7: =VLOOKUP(D7,'ZOHO Export'!$H:$W,16,FALSE) -> Natalia Martínez Nieto | AA7: =VLOOKUP(E7,'ZOHO Export'!$H:$W,16,FALSE) -> Natalia Martínez Nieto
A8: O3576 | B8: Affinity Petcare CGM_STB | D8: maria.bonaccio@group-ips.com | E8: maria.bonaccio@group-ips.com | G8: Affinity Factory Italy | H8: Reimbursable | I8: 46090 | K8: 46090 | L8: 155932.13 | M8: maria.bonaccio@group-ips.com | N8: 0 | O8: 0 | P8: Work in progress | R8: Food & Beverages | S8: Project Management | T8: IPS Spain | U8: IPS Spain | V8: Q9151 | W8: 500000 | X8: 155932.13 | Z8: =VLOOKUP(D8,'ZOHO Export'!$H:$W,16,FALSE) -> Maria Bonaccio | AA8: =VLOOKUP(E8,'ZOHO Export'!$H:$W,16,FALSE) -> Maria Bonaccio
A9: O3575 | B9: Logistics / Customs | D9: maria.romero@group-ips.com | E9: josue.silverio@group-ips.com | F9: salma.gueblaoui@group-ips.com | G9: Albioma | H9: Reimbursable | I9: 46090 | K9: 46090 | L9: 15876 | M9: josue.silverio@group-ips.com | N9: 0 | O9: 0 | P9: Work in progress | R9: Chemicals | S9: Sustainable Process & Environment|Masterplan|Consulting | T9: IPS France | U9: IPS France | V9: Q9118 | W9: 350 | X9: 15876 | Z9: =VLOOKUP(D9,'ZOHO Export'!$H:$W,16,FALSE) -> Maria Romero | AA9: =VLOOKUP(E9,'ZOHO Export'!$H:$W,16,FALSE) -> Josué Silverio
A10: O3574 | B10: Leuven WH roof renovation | D10: valerie.codesido@group-ips.com | E10: lucas.soto@group-ips.com | G10: InBev Belgium BV | H10: Lump sum | I10: 46087 | K10: 46087 | L10: 25725.73 | M10: lucas.soto@group-ips.com | N10: 0 | O10: 0 | P10: Work in progress | R10: Food & Beverages | S10: Architecture|Engineering|Utilities Engineering|Structural engineering | T10: IPS Belgium | U10: IPS Belgium | V10: Q9236 | W10: 1.7 | X10: 25725.73 | Z10: =VLOOKUP(D10,'ZOHO Export'!$H:$W,16,FALSE) -> Valérie Codesido | AA10: =VLOOKUP(E10,'ZOHO Export'!$H:$W,16,FALSE) -> Lucas Soto
A11: O3573 | B11: GSK RX86 - Design and Built | C11: Realization phase with design & built | D11: mathias.martin@group-ips.com | E11: yves.debaisieux@group-ips.com | F11: celine.lechado@group-ips.com | G11: GlaxoSmithKline Biologicals Rixensart | H11: Lump sum | I11: 46087 | K11: 46087 | L11: 123937 | M11: loic.bouvier@group-ips.com | N11: 0 | O11: 0 | P11: Work in progress | R11: Life Sciences | S11: Engineering|Safety|Project Management|Project Quality Support Team|Construction Management|Engineering Coordination|Process Engineering|Project Assistance|Safety & Site Supervision|Utilities Engineering|Civil engineering | T11: IPS Belgium | U11: IPS Belgium | V11: Q9070 | W11: 1 | X11: 123937 | Z11: =VLOOKUP(D11,'ZOHO Export'!$H:$W,16,FALSE) -> Mathias Martin | AA11: =VLOOKUP(E11,'ZOHO Export'!$H:$W,16,FALSE) -> Yves Debaisieux
A12: O3572 | B12: Facility Single Line Diagram | D12: pranay.pawar@group-ips.com | E12: pranay.pawar@group-ips.com | G12: Tennant Solutions | H12: Lump sum | I12: 46085 | K12: 46085 | L12: 15454 | M12: pranay.pawar@group-ips.com | N12: 0 | O12: 0 | P12: Work in progress | R12: Primary & Metals | S12: Engineering | T12: IPS USA | U12: IPS USA | V12: Q9082 | W12: 0.01 | X12: 15454 | Z12: =VLOOKUP(D12,'ZOHO Export'!$H:$W,16,FALSE) -> Pranay Pawar | AA12: =VLOOKUP(E12,'ZOHO Export'!$H:$W,16,FALSE) -> Pranay Pawar
A13: O3571 | B13: EBS_Plot EPCM services | D13: nevena.banova@group-ips.com | E13: nevena.banova@group-ips.com | G13: Eberspaecher Bulgaria | H13: Lump sum | I13: 46085 | K13: 46085 | L13: 4780 | M13: nevena.banova@group-ips.com | N13: 0 | O13: 0 | P13: Work in progress | R13: Buildings | S13: Engineering|Project Management|Construction Management|Procurement|Civil engineering | T13: IPS Bulgaria | U13: IPS Bulgaria | V13: Q8653 | X13: 4780 | Z13: =VLOOKUP(D13,'ZOHO Export'!$H:$W,16,FALSE) -> Nevena Banova | AA13: =VLOOKUP(E13,'ZOHO Export'!$H:$W,16,FALSE) -> Nevena Banova
A14: O3570 | B14: Highbay Extension Leuven | D14: karel.de.swert@group-ips.com | E14: karel.de.swert@group-ips.com | G14: Ab InBev EU HQ (BEL Leuven) | H14: Lump sum | I14: 46085 | K14: 46085 | L14: 25046.95 | M14: karel.de.swert@group-ips.com | N14: 0 | O14: 0 | P14: Work in progress | R14: Food & Beverages | S14: Architecture|Engineering|Project Management|Masterplan|Consulting|Transaction services|Permitting | T14: IPS Belgium | U14: IPS Belgium | V14: Q9176 | X14: 25046.95 | Z14: =VLOOKUP(D14,'ZOHO Export'!$H:$W,16,FALSE) -> Karel De Swert | AA14: =VLOOKUP(E14,'ZOHO Export'!$H:$W,16,FALSE) -> Karel De Swert
A15: O3569 | B15: PE1046_Safi TSP Plant | D15: souhail.wali@group-ips.com | E15: wissem.bensaid@group-ips.com | G15: Fertinagro | H15: Lump sum | I15: 46085 | K15: 46085 | L15: 264000 | M15: wissem.bensaid@group-ips.com | N15: 0 | O15: 0 | P15: Work in progress | R15: Chemicals | S15: Project Management | T15: IAPS Tunisia | U15: IAPS Tunisia | V15: Q9223 | W15: 0 | X15: 264000 | Z15: =VLOOKUP(D15,'ZOHO Export'!$H:$W,16,FALSE) -> Souhail WALI | AA15: =VLOOKUP(E15,'ZOHO Export'!$H:$W,16,FALSE) -> Wissem Bensaid
A16: O3568 | B16: Viviendas Berrocales | D16: jaime.alvarez.perez@group-ips.com | E16: felipe.langa@group-ips.com | G16: Servicoop Management SL | H16: Lump sum | I16: 46084 | K16: 46084 | L16: 151188.6 | M16: felipe.langa@group-ips.com | N16: 0 | O16: 0 | P16: Work in progress | R16: Buildings | S16: Architecture|Engineering|Project Management|Utilities Engineering|Author's Supervision|Structural engineering | T16: Arquid | U16: IPS Spain|Arquid | V16: Q9130 | W16: 5 | X16: 151188.6 | Z16: =VLOOKUP(D16,'ZOHO Export'!$H:$W,16,FALSE) -> Jaime Álvarez Pérez | AA16: =VLOOKUP(E16,'ZOHO Export'!$H:$W,16,FALSE) -> Felipe Langa Hernáez
A17: O3567 | B17: PE1047_Storage & Pipeline | D17: ali.trigui@group-ips.com | E17: wissem.bensaid@group-ips.com | G17: Fertinagro | H17: Lump sum | I17: 46084 | K17: 46084 | L17: 66420 | M17: wissem.bensaid@group-ips.com | N17: 0 | O17: 0 | P17: Work in progress | R17: Chemicals | S17: Engineering|Project Management|Piping Engineering|Process Engineering | T17: IAPS Tunisia | U17: IAPS Tunisia | V17: Q9220 | W17: 0 | X17: 66420 | Z17: =VLOOKUP(D17,'ZOHO Export'!$H:$W,16,FALSE) -> Ali TRIGUI | AA17: =VLOOKUP(E17,'ZOHO Export'!$H:$W,16,FALSE) -> Wissem Bensaid
A18: O3566 | B18: Witte Bg _PlantExtension | D18: nevena.banova@group-ips.com | E18: nevena.banova@group-ips.com | G18: WiTTE Automotive | H18: Reimbursable | I18: 46083 | K18: 46083 | L18: 7845.8 | M18: nevena.banova@group-ips.com | N18: 0 | O18: 0 | P18: Work in progress | R18: Other industry | S18: Project Management | T18: IPS Bulgaria | U18: IPS Bulgaria | V18: Q8870 | X18: 7845.8 | Z18: =VLOOKUP(D18,'ZOHO Export'!$H:$W,16,FALSE) -> Nevena Banova | AA18: =VLOOKUP(E18,'ZOHO Export'!$H:$W,16,FALSE) -> Nevena Banova
A19: O3565 | B19: Witte Bg _PlantExtension | D19: nevena.banova@group-ips.com | E19: nevena.banova@group-ips.com | G19: WiTTE Automotive | H19: Reimbursable | I19: 46083 | K19: 46083 | L19: 13238.4 | M19: nevena.banova@group-ips.com | N19: 0 | O19: 0 | P19: Work in progress | R19: Other industry | S19: Digital Supply Chain & Operations|Project Management|Project Assistance | T19: IPS Bulgaria | U19: IPS Bulgaria | V19: Q8740 | X19: 13238.4 | Z19: =VLOOKUP(D19,'ZOHO Export'!$H:$W,16,FALSE) -> Nevena Banova | AA19: =VLOOKUP(E19,'ZOHO Export'!$H:$W,16,FALSE) -> Nevena Banova
A20: O3564 | B20: HSE Standards | C20: IPS will support the Mondelez HSE Department on the site in LÃ¶rrach - Germany in preparation and embedding of the safety standards on site. | D20: jan.beske@group-ips.com | E20: yannick.vega@group-ips.com | G20: Mondelez GmbH LÃ¶rrach | H20: Reimbursable | I20: 46080 | K20: 46080 | L20: 116002 | M20: yannick.vega@group-ips.com | N20: 0 | O20: 0 | P20: Work in progress | R20: Food & Beverages | S20: Project Management | T20: Group-IPS | U20: IPS Germany|Group-IPS | V20: Q9147 | W20: 1 | X20: 116002 | Z20: =VLOOKUP(D20,'ZOHO Export'!$H:$W,16,FALSE) -> Jan Beske | AA20: =VLOOKUP(E20,'ZOHO Export'!$H:$W,16,FALSE) -> Yannick Vega Fernandez
A21: O3563 | B21: FK_D763 Str eng concr. floor | D21: charlelie.michel@group-ips.com | E21: peter.holvoet@group-ips.com | F21: sophie.saussu@group-ips.com | G21: Evonik Antwerpen N.V. | H21: Reimbursable | I21: 46080 | K21: 46080 | L21: 15742.35 | M21: peter.holvoet@group-ips.com | N21: 0 | O21: 0 | P21: Work in progress | R21: Chemicals | S21: Engineering|Project Management|Structural engineering | T21: IPS Belgium | U21: IPS Belgium | V21: Q9119 | W21: 0.3 | X21: 15742.35 | Z21: =VLOOKUP(D21,'ZOHO Export'!$H:$W,16,FALSE) -> Charlélie Michel | AA21: =VLOOKUP(E21,'ZOHO Export'!$H:$W,16,FALSE) -> Peter Holvoet
A22: O3562 | B22: Industrial Laundry BILBAO | C22: TDD/EDD industrial laundry Bilbao for potential acquisition | D22: maria.romero@group-ips.com | E22: miguel.menendez@group-ips.com | G22: Connecting visions | H22: Lump sum | I22: 46078 | K22: 46078 | L22: 8694 | M22: maria.romero@group-ips.com | N22: 0 | O22: 0 | P22: Work in progress | R22: Other industry | S22: Sustainable Process & Environment|Consulting|Transaction services | T22: IPS Spain | U22: IPS Belgium|IPS Spain | V22: Q9180 | W22: 1 | X22: 8694 | Z22: =VLOOKUP(D22,'ZOHO Export'!$H:$W,16,FALSE) -> Maria Romero | AA22: =VLOOKUP(E22,'ZOHO Export'!$H:$W,16,FALSE) -> Miguel Menéndez
A23: O3561 | B23: VSU Sistema 7 | D23: maria.bonaccio@group-ips.com | E23: maria.bonaccio@group-ips.com | G23: Affinity Factory _ Spain | H23: Reimbursable | I23: 46078 | J23: 46078 | K23: 46097 | L23: -15704.81 | M23: maria.bonaccio@group-ips.com | N23: 1 | O23: 1 | P23: Finished | R23: Food & Beverages | S23: Project Management | T23: IPS Spain | U23: IPS Spain | V23: Q9059 | W23: 0 | X23: 0 | Z23: =VLOOKUP(D23,'ZOHO Export'!$H:$W,16,FALSE) -> Maria Bonaccio | AA23: =VLOOKUP(E23,'ZOHO Export'!$H:$W,16,FALSE) -> Maria Bonaccio
A24: O3560 | B24: ARCADE 2026 | D24: ruben.gutierrez@group-ips.com | E24: felipe.langa@group-ips.com | G24: ARCADE | H24: Lump sum | I24: 46077 | K24: 46077 | L24: 0 | M24: ruben.gutierrez@group-ips.com | N24: 0 | O24: 0 | P24: Work in progress | R24: Other industry | S24: Architecture | T24: Arquid | U24: Arquid | V24: Q9211 | W24: 0 | X24: 0 | Z24: =VLOOKUP(D24,'ZOHO Export'!$H:$W,16,FALSE) -> Rubén Gutiérrez Llamas | AA24: =VLOOKUP(E24,'ZOHO Export'!$H:$W,16,FALSE) -> Felipe Langa Hernáez
A25: O3559 | B25: PE1045_Etd remplac sÃ©parateur | D25: taha.elghith@group-ips.com | E25: wissem.bensaid@group-ips.com | G25: MARETAP | H25: Lump sum | I25: 46073 | K25: 46073 | L25: 25000 | M25: wissem.bensaid@group-ips.com | N25: 0 | O25: 0 | P25: Work in progress | R25: Chemicals | S25: Engineering|Project Management|Mechanical Engineering|Piping Engineering|Process Engineering|Procurement | T25: IAPS Tunisia | U25: IAPS Tunisia | V25: Q9205 | W25: 0 | X25: 25000 | Z25: =VLOOKUP(D25,'ZOHO Export'!$H:$W,16,FALSE) -> Taha Elghith | AA25: =VLOOKUP(E25,'ZOHO Export'!$H:$W,16,FALSE) -> Wissem Bensaid
A26: O3558 | B26: MS project planning TAR | D26: niels.vanosselaer@group-ips.com | E26: peter.holvoet@group-ips.com | F26: julie.pollet@group-ips.com | G26: Ineos Feluy SA | H26: Reimbursable | I26: 46072 | K26: 46094 | L26: 7236.23 | M26: peter.holvoet@group-ips.com | N26: 1 | O26: 1 | P26: Work in progress | R26: Chemicals | S26: Project Management|Project Quality Support Team|Project Assistance | T26: IPS Belgium | U26: IPS Belgium | V26: Q9165 | W26: 0.5 | X26: 15088.37 | Z26: =VLOOKUP(D26,'ZOHO Export'!$H:$W,16,FALSE) -> Niels Van Osselaer | AA26: =VLOOKUP(E26,'ZOHO Export'!$H:$W,16,FALSE) -> Peter Holvoet
A27: O3557 | B27: Safety & CS Support_shutdown | D27: guy.melis@group-ips.com | E27: jurgen.van.den.driessche@group-ips.com | G27: 2Valorise Amel S.A. | H27: Reimbursable | I27: 46072 | K27: 46072 | L27: 45855 | M27: jurgen.van.den.driessche@group-ips.com | N27: 0 | O27: 0 | P27: Work in progress | R27: Primary & Metals | S27: Safety|Project Management|Safety & Site Supervision | T27: IPS Belgium | U27: IPS Belgium | V27: Q9114 | W27: 1 | X27: 45855 | Z27: =VLOOKUP(D27,'ZOHO Export'!$H:$W,16,FALSE) -> Guy Melis | AA27: =VLOOKUP(E27,'ZOHO Export'!$H:$W,16,FALSE) -> Jurgen Van Den Driessche
A28: O3556 | B28: Dedusting AM Belval TMB | D28: denis.remacle@group-ips.com | E28: denis.remacle@group-ips.com | F28: amandyne.rosart@group-ips.com | G28: ArcelorMittal Esch-Belval | H28: Reimbursable | I28: 46072 | K28: 46072 | L28: 11582.11 | M28: denis.remacle@group-ips.com | N28: 0 | O28: 0 | P28: Work in progress | R28: Primary & Metals | S28: Engineering|Project Management|Process Engineering | T28: IPS Belgium | U28: IPS Belgium | V28: Q9067 | W28: 0.01 | X28: 11582.11 | Z28: =VLOOKUP(D28,'ZOHO Export'!$H:$W,16,FALSE) -> Denis Remacle | AA28: =VLOOKUP(E28,'ZOHO Export'!$H:$W,16,FALSE) -> Denis Remacle
A29: O3555 | B29: PE1044_PrÃ©pration Plan Fluide | D29: lamiss.derbel@group-ips.com | E29: wissem.bensaid@group-ips.com | G29: SANITECHNIEK | H29: Reimbursable | I29: 46072 | K29: 46072 | L29: 8000 | M29: wissem.bensaid@group-ips.com | N29: 0 | O29: 0 | P29: Work in progress | R29: Buildings | S29: Engineering|Project Management|Engineering Coordination | T29: IAPS Tunisia | U29: IAPS Tunisia | V29: Q9202 | W29: 0 | X29: 8000 | Z29: =VLOOKUP(D29,'ZOHO Export'!$H:$W,16,FALSE) -> Lamiss Derbel | AA29: =VLOOKUP(E29,'ZOHO Export'!$H:$W,16,FALSE) -> Wissem Bensaid
A30: O3554 | B30: C&Q Cuves Mobiles WN10 | D30: yves.debaisieux@group-ips.com | E30: loic.bouvier@group-ips.com | F30: celine.lechado@group-ips.com | G30: GlaxoSmithKline Biologicals Wavre | H30: Lump sum | I30: 46071 | K30: 46071 | L30: 121800 | M30: loic.bouvier@group-ips.com | N30: 0 | O30: 0 | P30: Work in progress | R30: Life Sciences | S30: Project Management | T30: IPS Belgium | U30: IPS Belgium | V30: Q9054 | W30: 2 | X30: 121800 | Z30: =VLOOKUP(D30,'ZOHO Export'!$H:$W,16,FALSE) -> Yves Debaisieux | AA30: =VLOOKUP(E30,'ZOHO Export'!$H:$W,16,FALSE) -> Loïc Bouvier
A31: O3553 | B31: PE1042_Projeteur HVAC | D31: hanen.guebsi@group-ips.com | E31: wissem.bensaid@group-ips.com | G31: SANITECHNIEK | H31: Reimbursable | I31: 46069 | K31: 46069 | L31: 6400 | M31: wissem.bensaid@group-ips.com | N31: 0 | O31: 0 | P31: Work in progress | R31: Buildings | S31: Project Management | T31: IAPS Tunisia | U31: IAPS Tunisia | V31: Q9192 | W31: 0 | X31: 6400 | Z31: =VLOOKUP(D31,'ZOHO Export'!$H:$W,16,FALSE) -> Hanen GABSI | AA31: =VLOOKUP(E31,'ZOHO Export'!$H:$W,16,FALSE) -> Wissem Bensaid
A32: O3552 | B32: Project Engineer external | D32: fiete.heinrich@group-ips.com | E32: yannick.vega@group-ips.com | F32: yasmine.benrhaiem@group-ips.com | G32: Mondelez GmbH LÃ¶rrach | H32: Reimbursable | I32: 46069 | K32: 46069 | L32: 44000 | M32: yannick.vega@group-ips.com | N32: 0 | O32: 0 | P32: Work in progress | R32: Food & Beverages | S32: Project Management | T32: Group-IPS | U32: IPS Germany | V32: Q9191 | W32: 0 | X32: 44000 | Z32: =VLOOKUP(D32,'ZOHO Export'!$H:$W,16,FALSE) -> Fiete Heinrich | AA32: =VLOOKUP(E32,'ZOHO Export'!$H:$W,16,FALSE) -> Yannick Vega Fernandez
A33: O3551 | B33: PE1026_LNG Terminal Project | D33: omar.tounsi@group-ips.com | E33: wissem.bensaid@group-ips.com | G33: VEMAK | H33: Lump sum | I33: 46069 | K33: 46069 | L33: 251915.4 | M33: wissem.bensaid@group-ips.com | N33: 0 | O33: 0 | P33: Work in progress | R33: Chemicals | S33: Engineering|Project Management|Mechanical Engineering|Piping Engineering|Process Engineering | T33: IAPS Tunisia | U33: IAPS Tunisia | V33: Q9167 | W33: 0 | X33: 251915.4 | Z33: =VLOOKUP(D33,'ZOHO Export'!$H:$W,16,FALSE) -> Omar Tounsi | AA33: =VLOOKUP(E33,'ZOHO Export'!$H:$W,16,FALSE) -> Wissem Bensaid
A34: O3550 | B34: Realization Phase 1 BSB | D34: corto.tristan.travada@group-ips.com | E34: juan.juarez@group-ips.com | F34: delphine.myllecan@group-ips.com | G34: The British School | H34: Lump sum | I34: 46069 | K34: 46080 | L34: 96390 | M34: juan.juarez@group-ips.com | N34: 1 | O34: 1 | P34: Work in progress | R34: Buildings | S34: Architecture|Engineering|Safety|Project Management|Project Quality Support Team|Construction Management|Project Assistance|Safety & Site Supervision|Safety Coordination|Consulting|Procurement|Author's Supervision | T34: Group-IPS | U34: IPS Belgium|IPS France | V34: Q9173 | W34: 35 | X34: 1653632 | Z34: =VLOOKUP(D34,'ZOHO Export'!$H:$W,16,FALSE) -> Corto Tristan Travada | AA34: =VLOOKUP(E34,'ZOHO Export'!$H:$W,16,FALSE) -> Juan Juarez Quintana
A35: O3549 | B35: PE1039_Elec&Mechanical PM | D35: zied.maghrebi@group-ips.com | E35: wissem.bensaid@group-ips.com | G35: Groupe OCP | H35: Lump sum | I35: 46069 | K35: 46069 | L35: 70400 | M35: wissem.bensaid@group-ips.com | N35: 0 | O35: 0 | P35: Work in progress | R35: Chemicals | S35: Project Management | T35: IAPS Tunisia | U35: IAPS Tunisia | V35: Q9189 | W35: 0 | X35: 70400 | Z35: =VLOOKUP(D35,'ZOHO Export'!$H:$W,16,FALSE) -> Zied Maghrebi | AA35: =VLOOKUP(E35,'ZOHO Export'!$H:$W,16,FALSE) -> Wissem Bensaid
A36: O3548 | B36: PE1037_Etude servomoteur | D36: zied.maghrebi@group-ips.com | E36: wissem.bensaid@group-ips.com | G36: SCG Gabes | H36: Lump sum | I36: 46069 | K36: 46069 | L36: 4363.64 | M36: wissem.bensaid@group-ips.com | N36: 0 | O36: 0 | P36: Work in progress | R36: Primary & Metals | S36: Engineering|Project Management|Mechanical Engineering | T36: IAPS Tunisia | U36: IAPS Tunisia | V36: Q9188 | W36: 0 | X36: 4363.64 | Z36: =VLOOKUP(D36,'ZOHO Export'!$H:$W,16,FALSE) -> Zied Maghrebi | AA36: =VLOOKUP(E36,'ZOHO Export'!$H:$W,16,FALSE) -> Wissem Bensaid
A37: O3547 | B37: PE1014_Plan As-Built | D37: zied.maghrebi@group-ips.com | E37: wissem.bensaid@group-ips.com | G37: SCG Gabes | H37: Lump sum | I37: 46069 | K37: 46069 | L37: 7871.52 | M37: wissem.bensaid@group-ips.com | N37: 0 | O37: 0 | P37: Work in progress | R37: Primary & Metals | S37: Engineering|Project Management|Piping Engineering|Structural engineering | T37: IAPS Tunisia | U37: IAPS Tunisia | V37: Q9186 | W37: 0 | X37: 7871.52 | Z37: =VLOOKUP(D37,'ZOHO Export'!$H:$W,16,FALSE) -> Zied Maghrebi | AA37: =VLOOKUP(E37,'ZOHO Export'!$H:$W,16,FALSE) -> Wissem Bensaid
A38: O3546 | B38: PE1029_Root causes analysis | D38: zied.maghrebi@group-ips.com | E38: wissem.bensaid@group-ips.com | G38: TPS | H38: Lump sum | I38: 46069 | K38: 46069 | L38: 2100 | M38: wissem.bensaid@group-ips.com | N38: 0 | O38: 0 | P38: Work in progress | R38: Chemicals | S38: Project Management | T38: IAPS Tunisia | U38: IAPS Tunisia | V38: Q9187 | W38: 0 | X38: 2100 | Z38: =VLOOKUP(D38,'ZOHO Export'!$H:$W,16,FALSE) -> Zied Maghrebi | AA38: =VLOOKUP(E38,'ZOHO Export'!$H:$W,16,FALSE) -> Wissem Bensaid
A39: O3545 | B39: PE1041_3D & 2D de gaines | D39: souhir.hammami@group-ips.com | E39: wissem.bensaid@group-ips.com | G39: FIVES | H39: Lump sum | I39: 46066 | K39: 46066 | L39: 7200 | M39: wissem.bensaid@group-ips.com | N39: 0 | O39: 0 | P39: Work in progress | R39: Primary & Metals | S39: Engineering|Project Management|Mechanical Engineering | T39: IAPS Tunisia | U39: IAPS Tunisia | V39: Q9185 | W39: 0 | X39: 7200 | Z39: =VLOOKUP(D39,'ZOHO Export'!$H:$W,16,FALSE) -> Souhir HAMMAMI | AA39: =VLOOKUP(E39,'ZOHO Export'!$H:$W,16,FALSE) -> Wissem Bensaid
A40: O3544 | B40: PE1028_ Descriptif Tech | D40: mansour.hamza@group-ips.com | E40: wissem.bensaid@group-ips.com | G40: Groupe OCP | H40: Lump sum | I40: 46066 | K40: 46066 | L40: 85876 | M40: wissem.bensaid@group-ips.com | N40: 0 | O40: 0 | P40: Work in progress | R40: Chemicals | S40: Engineering|Project Management|Mechanical Engineering|Civil engineering|Structural engineering | T40: IAPS Tunisia | U40: IAPS Tunisia | V40: Q9184 | W40: 0 | X40: 85876 | Z40: =VLOOKUP(D40,'ZOHO Export'!$H:$W,16,FALSE) -> Mansour Hamza | AA40: =VLOOKUP(E40,'ZOHO Export'!$H:$W,16,FALSE) -> Wissem Bensaid
A41: O3543 | B41: PE1036_2 x CGL & CAGL in USA | D41: souhir.hammami@group-ips.com | E41: wissem.bensaid@group-ips.com | G41: FIVES | H41: Lump sum | I41: 46066 | K41: 46066 | L41: 24842.98 | M41: wissem.bensaid@group-ips.com | N41: 0 | O41: 0 | P41: Work in progress | R41: Primary & Metals | S41: Engineering|Project Management|Mechanical Engineering|Civil engineering|Structural engineering | T41: IAPS Tunisia | U41: IAPS Tunisia | V41: Q9183 | W41: 0 | X41: 24842.98 | Z41: =VLOOKUP(D41,'ZOHO Export'!$H:$W,16,FALSE) -> Souhir HAMMAMI | AA41: =VLOOKUP(E41,'ZOHO Export'!$H:$W,16,FALSE) -> Wissem Bensaid
A42: O3542 | B42: PE1032_Catalogue Plant 3D | D42: haithem.elleuch@group-ips.com | E42: wissem.bensaid@group-ips.com | G42: FIVES | H42: Lump sum | I42: 46066 | K42: 46066 | L42: 8320 | M42: wissem.bensaid@group-ips.com | N42: 0 | O42: 0 | P42: Work in progress | R42: Primary & Metals | S42: Engineering|Project Management|Piping Engineering | T42: IAPS Tunisia | U42: IAPS Tunisia | V42: Q9181 | W42: 0 | X42: 8320 | Z42: =VLOOKUP(D42,'ZOHO Export'!$H:$W,16,FALSE) -> Haithem Elleuch | AA42: =VLOOKUP(E42,'ZOHO Export'!$H:$W,16,FALSE) -> Wissem Bensaid
A43: O3541 | B43: PE1038_Al Jouf Greenfield | D43: souhail.wali@group-ips.com | E43: wissem.bensaid@group-ips.com | G43: Almayan | H43: Lump sum | I43: 46066 | K43: 46066 | L43: 27567.9 | M43: wissem.bensaid@group-ips.com | N43: 0 | O43: 0 | P43: Work in progress | R43: Buildings | S43: Engineering|Project Management|Utilities Engineering | T43: IAPS Tunisia | U43: IAPS Tunisia | V43: Q9178 | W43: 0 | X43: 27567.9 | Z43: =VLOOKUP(D43,'ZOHO Export'!$H:$W,16,FALSE) -> Souhail WALI | AA43: =VLOOKUP(E43,'ZOHO Export'!$H:$W,16,FALSE) -> Wissem Bensaid
A44: O3540 | B44: Project Hazelnut PE Support | D44: fiete.heinrich@group-ips.com | E44: fiete.heinrich@group-ips.com | G44: Cargill GmbH (Berlin-Reinickendorf) | H44: Reimbursable | I44: 46065 | K44: 46065 | L44: 54400 | M44: fiete.heinrich@group-ips.com | N44: 0 | O44: 0 | P44: Work in progress | R44: Food & Beverages | S44: Engineering|Project Management|Engineering Coordination | T44: IPS Germany | U44: IPS Belgium | V44: Q9145 | W44: 4 | X44: 54400 | Z44: =VLOOKUP(D44,'ZOHO Export'!$H:$W,16,FALSE) -> Fiete Heinrich | AA44: =VLOOKUP(E44,'ZOHO Export'!$H:$W,16,FALSE) -> Fiete Heinrich
A45: O3539 | B45: PE1031_Shougang CGL9 | D45: mohamed.hedi.hammemi@group-ips.com | E45: wissem.bensaid@group-ips.com | G45: FIVES | H45: Lump sum | I45: 46065 | K45: 46065 | L45: 159637.5 | M45: wissem.bensaid@group-ips.com | N45: 0 | O45: 0 | P45: Work in progress | R45: Primary & Metals | S45: Engineering|Project Management|Piping Engineering | T45: IAPS Tunisia | U45: IAPS Tunisia | V45: Q9177 | W45: 0 | X45: 159637.5 | Z45: =VLOOKUP(D45,'ZOHO Export'!$H:$W,16,FALSE) -> Mohamed Hedi Hammemi | AA45: =VLOOKUP(E45,'ZOHO Export'!$H:$W,16,FALSE) -> Wissem Bensaid
A46: O3538 | B46: Roof Renovation Leuven WH | D46: lucas.soto@group-ips.com | E46: lucas.soto@group-ips.com | G46: Ab InBev EU HQ (BEL Leuven) | H46: Lump sum | I46: 46065 | J46: 46065 | K46: 46098 | L46: -27145.84 | M46: lucas.soto@group-ips.com | N46: 1 | O46: 1 | P46: Finished | R46: Buildings | S46: Architecture|Engineering|Utilities Engineering|Structural engineering | T46: Arquid | U46: IPS Belgium | V46: Q9097 | W46: 0 | X46: 0 | Z46: =VLOOKUP(D46,'ZOHO Export'!$H:$W,16,FALSE) -> Lucas Soto | AA46: =VLOOKUP(E46,'ZOHO Export'!$H:$W,16,FALSE) -> Lucas Soto
A47: O3537 | B47: AS152 | D47: begona.soto@group-ips.com | E47: begona.soto@group-ips.com | G47: Reforma viviendas | H47: Lump sum | I47: 46064 | K47: 46064 | L47: 5130 | M47: begona.soto@group-ips.com | N47: 0 | O47: 0 | P47: Work in progress | R47: Buildings | S47: Architecture|Engineering|Author's Supervision | T47: Arquid | U47: Arquid | V47: Q9093 | W47: 297 | X47: 5130 | Z47: =VLOOKUP(D47,'ZOHO Export'!$H:$W,16,FALSE) -> Begona Soto | AA47: =VLOOKUP(E47,'ZOHO Export'!$H:$W,16,FALSE) -> Begona Soto
A48: O3536 | B48: Arch-PM refurb. support | D48: lucas.soto@group-ips.com | E48: lucas.soto@group-ips.com | F48: maximiliano.martin@group-ips.com | G48: Indicator Srl | H48: Reimbursable | I48: 46064 | K48: 46064 | L48: 19600 | M48: lucas.soto@group-ips.com | N48: 0 | O48: 0 | P48: Work in progress | R48: Buildings | S48: Architecture | T48: Arquid | U48: IPS Belgium | V48: Q9175 | W48: 1000000 | X48: 19600 | Z48: =VLOOKUP(D48,'ZOHO Export'!$H:$W,16,FALSE) -> Lucas Soto | AA48: =VLOOKUP(E48,'ZOHO Export'!$H:$W,16,FALSE) -> Lucas Soto
A49: O3535 | B49: FC NÃ¼rnberg Fan Experience | D49: natalia.martinez.nieto@group-ips.com | E49: natalia.martinez.nieto@group-ips.com | G49: EPHEMERALL | H49: Lump sum | I49: 46064 | K49: 46064 | L49: 3677 | M49: natalia.martinez.nieto@group-ips.com | N49: 0 | O49: 0 | P49: Work in progress | R49: Buildings | S49: Architecture | T49: Arquid | U49: Arquid | V49: Q9174 | X49: 3677 | Z49: =VLOOKUP(D49,'ZOHO Export'!$H:$W,16,FALSE) -> Natalia Martínez Nieto | AA49: =VLOOKUP(E49,'ZOHO Export'!$H:$W,16,FALSE) -> Natalia Martínez Nieto
A50: O3534 | B50: Duo Rail Preparation | D50: sang.dang@group-ips.com | E50: fiete.heinrich@group-ips.com | G50: Cargill Riesa | H50: Reimbursable | I50: 46063 | K50: 46063 | L50: 2925 | M50: fiete.heinrich@group-ips.com | N50: 0 | O50: 0 | P50: Work in progress | R50: Food & Beverages | S50: Engineering | T50: IPS Germany | U50: IPS Belgium | V50: Q9168 | W50: 0 | X50: 2925 | Z50: =VLOOKUP(D50,'ZOHO Export'!$H:$W,16,FALSE) -> Sang Tan Dang | AA50: =VLOOKUP(E50,'ZOHO Export'!$H:$W,16,FALSE) -> Fiete Heinrich
A51: O3533 | B51: PE1034_ Tag Electrique | D51: rawya.tlig@group-ips.com | E51: wissem.bensaid@group-ips.com | G51: FIVES | H51: Lump sum | I51: 46063 | K51: 46063 | L51: 10800 | M51: wissem.bensaid@group-ips.com | N51: 0 | O51: 0 | P51: Work in progress | R51: Primary & Metals | S51: Engineering|Project Management | T51: IAPS Tunisia | U51: IAPS Tunisia | V51: Q9166 | W51: 0 | X51: 10800 | Z51: =VLOOKUP(D51,'ZOHO Export'!$H:$W,16,FALSE) -> Rawya TLIG | AA51: =VLOOKUP(E51,'ZOHO Export'!$H:$W,16,FALSE) -> Wissem Bensaid
A52: O3532 | B52: PE1033_Flow Line Design | D52: houssem.bac@group-ips.com | E52: wissem.bensaid@group-ips.com | G52: ENDECO | H52: Lump sum | I52: 46063 | K52: 46063 | L52: 7000 | M52: wissem.bensaid@group-ips.com | N52: 0 | O52: 0 | P52: Work in progress | R52: Chemicals | S52: Engineering|Project Management|Piping Engineering | T52: IAPS Tunisia | U52: IAPS Tunisia | V52: Q9164 | W52: 0 | X52: 7000 | Z52: =VLOOKUP(D52,'ZOHO Export'!$H:$W,16,FALSE) -> Houssem Bac Ali | AA52: =VLOOKUP(E52,'ZOHO Export'!$H:$W,16,FALSE) -> Wissem Bensaid
A53: O3531 | B53: PE1030_Dispersion study | D53: wassim.ktari@group-ips.com | E53: wissem.bensaid@group-ips.com | G53: ENDECO | H53: Lump sum | I53: 46063 | K53: 46063 | L53: 3000 | M53: wissem.bensaid@group-ips.com | N53: 0 | O53: 0 | P53: Work in progress | R53: Chemicals | S53: Engineering|Process Engineering | T53: IAPS Tunisia | U53: IAPS Tunisia | V53: Q9163 | W53: 0 | X53: 3000 | Z53: =VLOOKUP(D53,'ZOHO Export'!$H:$W,16,FALSE) -> Wassim Ktari | AA53: =VLOOKUP(E53,'ZOHO Export'!$H:$W,16,FALSE) -> Wissem Bensaid
A54: O3530 | B54: Cerrado del Aguila plot M1-B | D54: miguel.menendez@group-ips.com | E54: miguel.menendez@group-ips.com | G54: Cordia Homes | H54: Lump sum | I54: 46062 | K54: 46062 | L54: 8316 | M54: miguel.menendez@group-ips.com | N54: 0 | O54: 0 | P54: Work in progress | R54: Buildings | S54: Engineering|Project Management|Cost Management|Civil engineering | T54: IPS Spain | U54: IPS Spain | V54: Q9161 | X54: 8316 | Z54: =VLOOKUP(D54,'ZOHO Export'!$H:$W,16,FALSE) -> Miguel Menéndez | AA54: =VLOOKUP(E54,'ZOHO Export'!$H:$W,16,FALSE) -> Miguel Menéndez
A55: O3529 | B55: PE1006_Design Report heater | D55: walid.taktak@group-ips.com | E55: wissem.bensaid@group-ips.com | G55: MARETAP | H55: Lump sum | I55: 46062 | K55: 46062 | L55: 1600 | M55: wissem.bensaid@group-ips.com | N55: 0 | O55: 0 | P55: Work in progress | R55: Chemicals | S55: Engineering|Mechanical Engineering | T55: IAPS Tunisia | U55: IAPS Tunisia | V55: Q9159 | W55: 0 | X55: 1600 | Z55: =VLOOKUP(D55,'ZOHO Export'!$H:$W,16,FALSE) -> Walid TAKTAK | AA55: =VLOOKUP(E55,'ZOHO Export'!$H:$W,16,FALSE) -> Wissem Bensaid
A56: O3528 | B56: PE1015_Architectural plan | D56: mohamed.ali.bouaziz@group-ips.com | E56: wissem.bensaid@group-ips.com | G56: PC Switzerland | H56: Lump sum | I56: 46062 | K56: 46062 | L56: 1800 | M56: wissem.bensaid@group-ips.com | N56: 0 | O56: 0 | P56: Work in progress | R56: Buildings | S56: Engineering | T56: IAPS Tunisia | U56: IAPS Tunisia | V56: Q9160 | W56: 0 | X56: 1800 | Z56: =VLOOKUP(D56,'ZOHO Export'!$H:$W,16,FALSE) -> Mohamed Ali Bouaziz | AA56: =VLOOKUP(E56,'ZOHO Export'!$H:$W,16,FALSE) -> Wissem Bensaid
A57: O3527 | B57: Cerrado del Aguila plot M1-A | C57: 2nd project for Cordia Homes in Cerrado del Aguila urbanization. | D57: belen.lopez@group-ips.com | E57: miguel.menendez@group-ips.com | G57: Cordia Homes | H57: Lump sum | I57: 46062 | K57: 46062 | L57: 8316 | M57: miguel.menendez@group-ips.com | N57: 0 | O57: 0 | P57: Work in progress | R57: Buildings | S57: Engineering|Project Management|Cost Management|Civil engineering | T57: IPS Spain | U57: IPS Spain | V57: Q8945 | W57: 27 | X57: 8316 | Z57: =VLOOKUP(D57,'ZOHO Export'!$H:$W,16,FALSE) -> Belén Lopez Barrera | AA57: =VLOOKUP(E57,'ZOHO Export'!$H:$W,16,FALSE) -> Miguel Menéndez
A58: O3526 | B58: 2026 Project Support | D58: sunny.yip@group-ips.com | E58: sunny.yip@group-ips.com | F58: delphine.myllecan@group-ips.com | G58: S.W.I.F.T. SC | H58: Reimbursable | I58: 46059 | K58: 46052 | L58: 467409.56 | M58: sunny.yip@group-ips.com | N58: 0 | O58: 0 | P58: Work in progress | R58: Buildings | S58: Engineering|Project Management|Project Quality Support Team|Construction Management|HVAC Engineering|Project Assistance | T58: IPS Belgium | U58: IPS Belgium|IPS USA|IPS Netherlands | V58: Q9010 | W58: 10 | X58: 467409.56 | Z58: =VLOOKUP(D58,'ZOHO Export'!$H:$W,16,FALSE) -> Sunny Yip | AA58: =VLOOKUP(E58,'ZOHO Export'!$H:$W,16,FALSE) -> Sunny Yip
A59: O3525 | B59: ATEX file update | D59: audric.jeanne@group-ips.com | E59: karel.de.swert@group-ips.com | F59: delphine.myllecan@group-ips.com | G59: Cargill Chocolate Belgium NV (Mouscron) | H59: Lump sum | I59: 46056 | K59: 46056 | L59: 1729.99 | M59: audric.jeanne@group-ips.com | N59: 0 | O59: 0 | P59: Work in progress | R59: Food & Beverages | S59: Safety|Project Management|Safety Engineering | T59: IPS Belgium | U59: IPS Belgium | V59: Q9110 | W59: 0.01 | X59: 1729.99 | Z59: =VLOOKUP(D59,'ZOHO Export'!$H:$W,16,FALSE) -> Audric Jeanne | AA59: =VLOOKUP(E59,'ZOHO Export'!$H:$W,16,FALSE) -> Karel De Swert
A60: O3524 | B60: Informe Villanueva 41 | D60: begona.soto@group-ips.com | E60: begona.soto@group-ips.com | G60: Gianni Housing | H60: Lump sum | I60: 46052 | K60: 46052 | L60: 1100 | M60: begona.soto@group-ips.com | N60: 0 | O60: 0 | P60: Work in progress | R60: Buildings | S60: Architecture | T60: Arquid | U60: Arquid | V60: Q9140 | W60: 1 | X60: 1100 | Z60: =VLOOKUP(D60,'ZOHO Export'!$H:$W,16,FALSE) -> Begona Soto | AA60: =VLOOKUP(E60,'ZOHO Export'!$H:$W,16,FALSE) -> Begona Soto
A61: O3523 | B61: PE1023_Algeria Beneficiation | D61: amir.ben.ayed@group-ips.com | E61: wissem.bensaid@group-ips.com | G61: ECOMIN | H61: Lump sum | I61: 46052 | K61: 46052 | L61: 154800 | M61: wissem.bensaid@group-ips.com | N61: 0 | O61: 0 | P61: Work in progress | R61: Chemicals | S61: Engineering|Project Management|Mechanical Engineering|Piping Engineering|Process Engineering|Civil engineering|Structural engineering | T61: IAPS Tunisia | U61: IAPS Tunisia | V61: Q9144 | W61: 0 | X61: 154800 | Z61: =VLOOKUP(D61,'ZOHO Export'!$H:$W,16,FALSE) -> Amir Ben Ayed | AA61: =VLOOKUP(E61,'ZOHO Export'!$H:$W,16,FALSE) -> Wissem Bensaid
A62: O3522 | B62: Micella Preheater | D62: lucas.olheiser@group-ips.com | E62: fiete.heinrich@group-ips.com | G62: LDC Wittenberg | H62: Reimbursable | I62: 46052 | K62: 46052 | L62: 59495 | M62: lucas.olheiser@group-ips.com | N62: 0 | O62: 0 | P62: Work in progress | R62: Food & Beverages | S62: Engineering|Project Management|Engineering Coordination | T62: IPS Germany | U62: IPS Belgium | V62: Q9038 | W62: 1 | X62: 59495 | Z62: =VLOOKUP(D62,'ZOHO Export'!$H:$W,16,FALSE) -> Lucas Olheiser | AA62: =VLOOKUP(E62,'ZOHO Export'!$H:$W,16,FALSE) -> Fiete Heinrich
A63: O3521 | B63: Oil Tank Replacement | C63: Replacement of the old Oil Tank with a new and bigger Oil Tank | D63: sang.dang@group-ips.com | E63: fiete.heinrich@group-ips.com | G63: LDC Wittenberg | H63: Reimbursable | I63: 46064 | K63: 46052 | L63: 40475 | M63: lucas.olheiser@group-ips.com | N63: 0 | O63: 0 | P63: Work in progress | R63: Food & Beverages | S63: Project Management | T63: IPS Germany | U63: IPS Belgium|IPS Germany | V63: Q9089 | W63: 0.7 | X63: 40475 | Z63: =VLOOKUP(D63,'ZOHO Export'!$H:$W,16,FALSE) -> Sang Tan Dang | AA63: =VLOOKUP(E63,'ZOHO Export'!$H:$W,16,FALSE) -> Fiete Heinrich
A64: O3520 | B64: PE1027_Etude GC Shutdown | D64: achraf.walha@group-ips.com | E64: wissem.bensaid@group-ips.com | G64: MARETAP | H64: Lump sum | I64: 46051 | K64: 46051 | L64: 8600 | M64: wissem.bensaid@group-ips.com | N64: 0 | O64: 0 | P64: Work in progress | R64: Chemicals | S64: Engineering|Project Management|Civil engineering | T64: IAPS Tunisia | U64: IAPS Tunisia | V64: Q9143 | W64: 0 | X64: 8600 | Z64: =VLOOKUP(D64,'ZOHO Export'!$H:$W,16,FALSE) -> Achraf Walha | AA64: =VLOOKUP(E64,'ZOHO Export'!$H:$W,16,FALSE) -> Wissem Bensaid
A65: O3519 | B65: 133_Extension_IPS Proposal | D65: maxim.mokdad@group-ips.com | E65: boris.krastev@group-ips.com | F65: nevena.banova@group-ips.com | G65: 133 School | H65: Lump sum | I65: 46034 | K65: 46051 | L65: 25075 | M65: nevena.banova@group-ips.com | N65: 0 | O65: 0 | P65: Work in progress | R65: Other industry | S65: Architecture|Engineering|Safety|Project Management|Construction Management|HVAC Engineering|Process Engineering|Safety Engineering|Cost Management | T65: IPS Bulgaria | U65: IPS Bulgaria | V65: Q9131 | W65: 0 | X65: 25075 | Z65: =VLOOKUP(D65,'ZOHO Export'!$H:$W,16,FALSE) -> Maxim Mokdad | AA65: =VLOOKUP(E65,'ZOHO Export'!$H:$W,16,FALSE) -> Boris Krastev
A66: O3518 | B66: Air Liquide_PM services | D66: dobri.gatev@group-ips.com | E66: tsanko.mihov@group-ips.com | F66: nevena.banova@group-ips.com | G66: Air Liquide | H66: Reimbursable | I66: 45931 | K66: 46051 | L66: 115200 | M66: nevena.banova@group-ips.com | N66: 0 | O66: 0 | P66: Work in progress | R66: Chemicals | S66: Project Management | T66: IPS Bulgaria | U66: IPS Bulgaria | V66: Q8962 | W66: 0 | X66: 115200 | Z66: =VLOOKUP(D66,'ZOHO Export'!$H:$W,16,FALSE) -> Dobri Gatev | AA66: =VLOOKUP(E66,'ZOHO Export'!$H:$W,16,FALSE) -> Tsanko Mihov
A67: O3517 | B67: CONSULTA URBANÃSTICA_PARKING | D67: paqui.romero@group-ips.com | E67: paqui.romero@group-ips.com | G67: Puratos_Sils (Spain) | H67: Lump sum | I67: 46048 | K67: 46048 | L67: 6100 | M67: paqui.romero@group-ips.com | N67: 0 | O67: 0 | P67: Work in progress | R67: Food & Beverages | S67: Architecture|Project Management | T67: IPS Spain | U67: IPS Belgium | V67: Q9105 | W67: 1 | X67: 6100 | Z67: =VLOOKUP(D67,'ZOHO Export'!$H:$W,16,FALSE) -> Paqui Romero | AA67: =VLOOKUP(E67,'ZOHO Export'!$H:$W,16,FALSE) -> Paqui Romero
A68: O3516 | B68: TDD Azuqueca Henares | C68: Technical Due Diligence and Environmental Due Diligence purchase process for an asset in Azuqueca de Henares. | D68: miguel.menendez@group-ips.com | E68: juan.juarez@group-ips.com | G68: P3 Logistic Parks | H68: Lump sum | I68: 46048 | K68: 46048 | L68: 32997.89 | M68: miguel.menendez@group-ips.com | N68: 0 | O68: 0 | P68: Work in progress | R68: Buildings | S68: Consulting|Transaction services | T68: IPS Spain | U68: IPS Spain | V68: Q9074 | W68: 30 | X68: 32997.89 | Z68: =VLOOKUP(D68,'ZOHO Export'!$H:$W,16,FALSE) -> Miguel Menéndez | AA68: =VLOOKUP(E68,'ZOHO Export'!$H:$W,16,FALSE) -> Juan Juarez Quintana
A69: O3515 | B69: R&M Project Admin Work | D69: mark.sensenig@group-ips.com | E69: mark.sensenig@group-ips.com | G69: Blommer Chocolate | H69: Lump sum | I69: 46048 | K69: 46048 | L69: 27216 | M69: mark.sensenig@group-ips.com | N69: 0 | O69: 0 | P69: Work in progress | R69: Food & Beverages | S69: Project Management | T69: IPS USA | U69: IPS USA | V69: Q9135 | W69: 0.1 | X69: 27216 | Z69: =VLOOKUP(D69,'ZOHO Export'!$H:$W,16,FALSE) -> Mark Sensenig | AA69: =VLOOKUP(E69,'ZOHO Export'!$H:$W,16,FALSE) -> Mark Sensenig
A70: O3514 | B70: PE1025_Excellence Projets | D70: bacem.charmi@group-ips.com | E70: wissem.bensaid@group-ips.com | G70: SNIM | H70: Lump sum | I70: 46045 | K70: 46045 | L70: 87686.25 | M70: wissem.bensaid@group-ips.com | N70: 0 | O70: 0 | P70: Work in progress | R70: Primary & Metals | S70: Project Management | T70: IAPS Tunisia | U70: IAPS Tunisia | V70: Q9129 | W70: 0 | X70: 87686.25 | Z70: =VLOOKUP(D70,'ZOHO Export'!$H:$W,16,FALSE) -> Bacem CHARMI | AA70: =VLOOKUP(E70,'ZOHO Export'!$H:$W,16,FALSE) -> Wissem Bensaid
A71: O3513 | B71: BRU1 - Project Support 2026 | D71: jurgen.van.den.driessche@group-ips.com | E71: bram.puttemans@group-ips.com | F71: delphine.myllecan@group-ips.com | G71: Digital Realty | H71: Reimbursable | I71: 46045 | K71: 46045 | L71: 46440 | M71: bram.puttemans@group-ips.com | N71: 0 | O71: 0 | P71: Work in progress | R71: Buildings | S71: Safety|Project Management|Safety & Site Supervision | T71: IPS Belgium | U71: IPS Belgium | V71: Q9092 | W71: 2000000 | X71: 46440 | Z71: =VLOOKUP(D71,'ZOHO Export'!$H:$W,16,FALSE) -> Jurgen Van Den Driessche | AA71: =VLOOKUP(E71,'ZOHO Export'!$H:$W,16,FALSE) -> Bram Puttemans
A72: O3512 | B72: PM - Paseo Delicias 61 | D72: cristina.rubio.rodriguez@group-ips.com | E72: juan.juarez@group-ips.com | G72: UNIVERSAL MUSIC | H72: Lump sum | I72: 46044 | K72: 46044 | L72: 103509 | M72: juan.juarez@group-ips.com | N72: 0 | O72: 0 | P72: Work in progress | R72: Buildings | S72: Project Management|Construction Management | T72: IPS Spain | U72: IPS Spain | V72: Q8955 | W72: 2 | X72: 103509 | Z72: =VLOOKUP(D72,'ZOHO Export'!$H:$W,16,FALSE) -> Cristina Rubio Rodríguez | AA72: =VLOOKUP(E72,'ZOHO Export'!$H:$W,16,FALSE) -> Juan Juarez Quintana
A73: O3511 | B73: ART HOUSE | D73: cristina.rubio.rodriguez@group-ips.com | E73: juan.juarez@group-ips.com | G73: UNIVERSAL MUSIC | H73: Lump sum | I73: 46044 | K73: 46044 | L73: 72931.5 | M73: juan.juarez@group-ips.com | N73: 0 | O73: 0 | P73: Work in progress | R73: Buildings | S73: Project Management|Construction Management|Consulting|Transaction services | T73: IPS Spain | U73: IPS Spain|Arquid | V73: Q9073 | W73: 2 | X73: 72931.5 | Z73: =VLOOKUP(D73,'ZOHO Export'!$H:$W,16,FALSE) -> Cristina Rubio Rodríguez | AA73: =VLOOKUP(E73,'ZOHO Export'!$H:$W,16,FALSE) -> Juan Juarez Quintana
A74: O3510 | B74: PE1024_Etude BÃ¢timent | D74: habib.kharrat@group-ips.com | E74: wissem.bensaid@group-ips.com | G74: AMA Group | H74: Lump sum | I74: 46044 | K74: 46044 | L74: 75000 | M74: wissem.bensaid@group-ips.com | N74: 0 | O74: 0 | P74: Work in progress | R74: Buildings | S74: Engineering|Project Management|HVAC Engineering|Utilities Engineering|Civil engineering | T74: IAPS Tunisia | U74: IAPS Tunisia | V74: Q9127 | W74: 0 | X74: 75000 | Z74: =VLOOKUP(D74,'ZOHO Export'!$H:$W,16,FALSE) -> Habib Kharrat | AA74: =VLOOKUP(E74,'ZOHO Export'!$H:$W,16,FALSE) -> Wissem Bensaid
A75: O3509 | B75: PE1022_Site Visit | D75: zied.maghrebi@group-ips.com | E75: wissem.bensaid@group-ips.com | G75: TPS | H75: Lump sum | I75: 46044 | K75: 46044 | L75: 2864.86 | M75: wissem.bensaid@group-ips.com | N75: 0 | O75: 0 | P75: Work in progress | R75: Chemicals | S75: Project Management | T75: IAPS Tunisia | U75: IAPS Tunisia | V75: Q9126 | W75: 0 | X75: 2864.86 | Z75: =VLOOKUP(D75,'ZOHO Export'!$H:$W,16,FALSE) -> Zied Maghrebi | AA75: =VLOOKUP(E75,'ZOHO Export'!$H:$W,16,FALSE) -> Wissem Bensaid
A76: O3508 | B76: PE1020_modification Tank | D76: montassar.gharsallah@group-ips.com | E76: wissem.bensaid@group-ips.com | G76: Alsawaed Libya | H76: Lump sum | I76: 46044 | K76: 46044 | L76: 7296 | M76: wissem.bensaid@group-ips.com | N76: 0 | O76: 0 | P76: Work in progress | R76: Chemicals | S76: Engineering|Project Management|Mechanical Engineering | T76: IAPS Tunisia | U76: IAPS Tunisia | V76: Q9125 | W76: 0 | X76: 7296 | Z76: =VLOOKUP(D76,'ZOHO Export'!$H:$W,16,FALSE) -> Montassar Gharsallah | AA76: =VLOOKUP(E76,'ZOHO Export'!$H:$W,16,FALSE) -> Wissem Bensaid
A77: O3507 | B77: PE1019_PM Service | D77: bilel.tajouri@group-ips.com | E77: wissem.bensaid@group-ips.com | G77: BARRY CALLEBAUT (IVORY COAST) | H77: Lump sum | I77: 46044 | K77: 46044 | L77: 33088 | M77: wissem.bensaid@group-ips.com | N77: 0 | O77: 0 | P77: Work in progress | R77: Food & Beverages | S77: Project Management|Construction Management | T77: IAPS Tunisia | U77: IAPS Tunisia | V77: Q9124 | W77: 0 | X77: 33088 | Z77: =VLOOKUP(D77,'ZOHO Export'!$H:$W,16,FALSE) -> Bilel Tajouri | AA77: =VLOOKUP(E77,'ZOHO Export'!$H:$W,16,FALSE) -> Wissem Bensaid
A78: O3506 | B78: PE1017_Tender Support | D78: walim.jribi@group-ips.com | E78: wissem.bensaid@group-ips.com | G78: PETROLEAD | H78: Lump sum | I78: 46044 | K78: 46044 | L78: 4800 | M78: wissem.bensaid@group-ips.com | N78: 0 | O78: 0 | P78: Work in progress | R78: Chemicals | S78: Project Management | T78: IAPS Tunisia | U78: IAPS Tunisia | V78: Q9123 | W78: 0 | X78: 4800 | Z78: =VLOOKUP(D78,'ZOHO Export'!$H:$W,16,FALSE) -> Walim JRIBI | AA78: =VLOOKUP(E78,'ZOHO Export'!$H:$W,16,FALSE) -> Wissem Bensaid
A79: O3505 | B79: PE1021_Etude cuisine | D79: aziz.hentati@group-ips.com | E79: wissem.bensaid@group-ips.com | G79: YAZAKI TUNISIA S.A. | H79: Lump sum | I79: 46043 | K79: 46043 | L79: 18500 | M79: wissem.bensaid@group-ips.com | N79: 0 | O79: 0 | P79: Work in progress | R79: Primary & Metals | S79: Engineering|Project Management|HVAC Engineering|Utilities Engineering|Procurement|Civil engineering|Structural engineering | T79: IAPS Tunisia | U79: IAPS Tunisia | V79: Q9117 | W79: 0 | X79: 18500 | Z79: =VLOOKUP(D79,'ZOHO Export'!$H:$W,16,FALSE) -> AZIZ HENTATI | AA79: =VLOOKUP(E79,'ZOHO Export'!$H:$W,16,FALSE) -> Wissem Bensaid
A80: O3504 | B80: DMZR | D80: audric.jeanne@group-ips.com | E80: karel.de.swert@group-ips.com | F80: celine.lechado@group-ips.com | G80: CBRE Belgium | H80: Lump sum | I80: 46043 | K80: 46043 | L80: 12072 | M80: nicolas.dubois@group-ips.com | N80: 0 | O80: 0 | P80: Work in progress | R80: Buildings | S80: Engineering|Project Management|HVAC Engineering|Procurement | T80: IPS Belgium | U80: IPS Belgium | V80: Q9102 | W80: 1 | X80: 12072 | Z80: =VLOOKUP(D80,'ZOHO Export'!$H:$W,16,FALSE) -> Audric Jeanne | AA80: =VLOOKUP(E80,'ZOHO Export'!$H:$W,16,FALSE) -> Karel De Swert
A81: O3503 | B81: MasterPlan | D81: begona.soto@group-ips.com | E81: carlos.bravo.fernandez@group-ips.com | G81: GB Foods, Spain | H81: Lump sum | I81: 46041 | K81: 46052 | L81: 14237.11 | M81: yannick.vega@group-ips.com | N81: 1 | O81: 1 | P81: Work in progress | R81: Food & Beverages | S81: Architecture|Engineering|Digital Supply Chain & Operations|Project Management|Masterplan|Utilities Engineering|Consulting|Permitting | T81: IPS Spain | U81: IPS Spain|Group-IPS|Arquid|IPS Belgium | V81: Q9075 | W81: 0 | X81: 73021.34 | Z81: =VLOOKUP(D81,'ZOHO Export'!$H:$W,16,FALSE) -> Begona Soto | AA81: =VLOOKUP(E81,'ZOHO Export'!$H:$W,16,FALSE) -> Carlos Bravo Fernández
A82: O3502 | B82: GF Investm. Risk evaluation | D82: alfredo.bartolome@group-ips.com | E82: carlos.bravo.fernandez@group-ips.com | F82: delphine.myllecan@group-ips.com | G82: SynPet | H82: Lump sum | I82: 46041 | J82: 46092 | K82: 46041 | L82: 6685.62 | M82: carlos.bravo.fernandez@group-ips.com | N82: 0 | O82: 0 | P82: Finished | R82: Chemicals | S82: Consulting | T82: Group-IPS | U82: Group-IPS | V82: Q9109 | W82: 256 | X82: 6685.62 | Z82: =VLOOKUP(D82,'ZOHO Export'!$H:$W,16,FALSE) -> Alfredo Bartolome | AA82: =VLOOKUP(E82,'ZOHO Export'!$H:$W,16,FALSE) -> Carlos Bravo Fernández
A83: O3501 | B83: Airtable Implementation | D83: irene.martinez@group-ips.com | E83: damien.hemmeryckx@group-ips.com | F83: amandyne.rosart@group-ips.com | G83: NLMK La Louviere | H83: Reimbursable | I83: 45931 | J83: 46081 | K83: 46041 | L83: 145462.8 | M83: damien.hemmeryckx@group-ips.com | N83: 0 | O83: 0 | P83: Finished | R83: Primary & Metals | S83: Project Management|Software Developments | T83: IPS Belgium | U83: IPS Belgium|BAIPS | V83: Q9108 | W83: 1000 | X83: 145462.8 | Z83: =VLOOKUP(D83,'ZOHO Export'!$H:$W,16,FALSE) -> Irene Martínez Margallo | AA83: =VLOOKUP(E83,'ZOHO Export'!$H:$W,16,FALSE) -> Damien Hemmeryckx
A84: O3500 | B84: Construction Management | D84: francois.casteleyn@group-ips.com | E84: adrien.ongenae@group-ips.com | F84: delphine.myllecan@group-ips.com | G84: DSM-firmenich Seclin | H84: Reimbursable | I84: 46038 | K84: 46038 | L84: 294300 | M84: adrien.ongenae@group-ips.com | N84: 0 | O84: 0 | P84: Work in progress | R84: Food & Beverages | S84: Project Management|Construction Management | T84: IPS France | U84: IPS Belgium | V84: Q9060 | W84: 20000000 | X84: 294300 | Z84: =VLOOKUP(D84,'ZOHO Export'!$H:$W,16,FALSE) -> François Casteleyn | AA84: =VLOOKUP(E84,'ZOHO Export'!$H:$W,16,FALSE) -> Adrien Ongenae
A85: O3499 | B85: Renders EDHINOR BOCM | D85: ricardo.roda@group-ips.com | E85: maximiliano.martin@group-ips.com | F85: yasmine.benrhaiem@group-ips.com | G85: EDHINOR SA | H85: Lump sum | I85: 46037 | K85: 46037 | L85: 1000.69 | M85: ricardo.roda@group-ips.com | N85: 0 | O85: 0 | P85: Work in progress | R85: Buildings | S85: Architecture | T85: Arquid | U85: Arquid | V85: Q9101 | W85: 1 | X85: 1000.69 | Z85: =VLOOKUP(D85,'ZOHO Export'!$H:$W,16,FALSE) -> Ricardo Roda | AA85: =VLOOKUP(E85,'ZOHO Export'!$H:$W,16,FALSE) -> Maximiliano Martin Parra
A86: O3498 | B86: LPO Valdetorres 11 | D86: ricardo.roda@group-ips.com | E86: juan.juarez@group-ips.com | F86: yasmine.benrhaiem@group-ips.com | G86: Sergio Diez | H86: Lump sum | I86: 46037 | J86: 46052 | K86: 46037 | L86: 8034.26 | M86: ricardo.roda@group-ips.com | N86: 0 | O86: 0 | P86: Work in progress | R86: Buildings | S86: Architecture | T86: Arquid | U86: Arquid | V86: Q9100 | W86: 1 | X86: 8034.26 | Z86: =VLOOKUP(D86,'ZOHO Export'!$H:$W,16,FALSE) -> Ricardo Roda | AA86: =VLOOKUP(E86,'ZOHO Export'!$H:$W,16,FALSE) -> Juan Juarez Quintana
A87: O3497 | B87: JC_AFS_Site supp_Munich DE | D87: jurgen.van.den.driessche@group-ips.com | E87: peter.holvoet@group-ips.com | F87: sophie.saussu@group-ips.com | G87: John Cockerill SA | H87: Lump sum | I87: 46035 | K87: 46035 | L87: 109980 | M87: jurgen.van.den.driessche@group-ips.com | N87: 0 | O87: 0 | P87: Work in progress | R87: Chemicals | S87: Project Management|Construction Management | T87: IPS Belgium | U87: IPS Belgium | V87: Q9063 | W87: 2 | X87: 109980 | Z87: =VLOOKUP(D87,'ZOHO Export'!$H:$W,16,FALSE) -> Jurgen Van Den Driessche | AA87: =VLOOKUP(E87,'ZOHO Export'!$H:$W,16,FALSE) -> Peter Holvoet
A88: O3496 | B88: CBAM training | D88: maria.romero@group-ips.com | E88: maria.romero@group-ips.com | F88: celine.lechado@group-ips.com | G88: AEFA Agronutrientes | H88: Lump sum | I88: 46035 | J88: 46079 | K88: 46057 | L88: 449.98 | M88: maria.romero@group-ips.com | N88: 1 | O88: 1 | P88: Finished | R88: Chemicals | S88: Sustainable Process & Environment | T88: Group-IPS | U88: IPS Belgium | V88: Q9095 | W88: 0.1 | X88: 450 | Z88: =VLOOKUP(D88,'ZOHO Export'!$H:$W,16,FALSE) -> Maria Romero | AA88: =VLOOKUP(E88,'ZOHO Export'!$H:$W,16,FALSE) -> Maria Romero
A89: O3495 | B89: HK D779 Feasability | D89: sunny.yip@group-ips.com | E89: peter.holvoet@group-ips.com | F89: sophie.saussu@group-ips.com | G89: Evonik Antwerpen N.V. | H89: Reimbursable | I89: 46035 | J89: 46082 | K89: 46035 | L89: 16470.79 | M89: peter.holvoet@group-ips.com | N89: 0 | O89: 0 | P89: Finished | R89: Chemicals | S89: Engineering|Project Management|Project Quality Support Team|Project Assistance|Structural engineering | T89: IPS Belgium | U89: IPS Belgium | V89: Q9058 | W89: 0.5 | X89: 16470.79 | Z89: =VLOOKUP(D89,'ZOHO Export'!$H:$W,16,FALSE) -> Sunny Yip | AA89: =VLOOKUP(E89,'ZOHO Export'!$H:$W,16,FALSE) -> Peter Holvoet
A90: O3494 | B90: ATC Layout | D90: denis.remacle@group-ips.com | E90: denis.remacle@group-ips.com | F90: amandyne.rosart@group-ips.com | G90: ArcelorMittal Esch-Belval | H90: Reimbursable | I90: 46031 | K90: 46031 | L90: 140875.73 | M90: denis.remacle@group-ips.com | N90: 0 | O90: 0 | P90: Work in progress | R90: Primary & Metals | S90: Engineering | T90: IPS Belgium | U90: IPS Belgium | V90: Q8913 | W90: 0.01 | X90: 140875.73 | Z90: =VLOOKUP(D90,'ZOHO Export'!$H:$W,16,FALSE) -> Denis Remacle | AA90: =VLOOKUP(E90,'ZOHO Export'!$H:$W,16,FALSE) -> Denis Remacle
A91: O3493 | B91: Davenport, IA CM Support | D91: pranay.pawar@group-ips.com | E91: mac.o.lean@group-ips.com | G91: Carmeuse Lime & Stone (Headquarters) | H91: Reimbursable | I91: 46029 | K91: 46029 | L91: 61250 | M91: pranay.pawar@group-ips.com | N91: 0 | O91: 0 | P91: Work in progress | R91: Primary & Metals | S91: Project Management|Construction Management | T91: IPS USA | U91: IPS USA | V91: Q9069 | W91: 0.01 | X91: 61250 | Z91: =VLOOKUP(D91,'ZOHO Export'!$H:$W,16,FALSE) -> Pranay Pawar | AA91: =VLOOKUP(E91,'ZOHO Export'!$H:$W,16,FALSE) -> Mac Olean
A92: O3492 | B92: Libro de Estilo | D92: laura.cestau@group-ips.com | E92: laura.cestau@group-ips.com | F92: yasmine.benrhaiem@group-ips.com | G92: The Residential Club | H92: Lump sum | I92: 46029 | K92: 46029 | L92: 15012 | M92: laura.cestau@group-ips.com | N92: 0 | O92: 0 | P92: Work in progress | R92: Buildings | S92: Architecture | T92: Arquid | U92: IPS Belgium|Arquid | V92: Q8826 | W92: 10 | X92: 15012 | Z92: =VLOOKUP(D92,'ZOHO Export'!$H:$W,16,FALSE) -> Laura Cestau | AA92: =VLOOKUP(E92,'ZOHO Export'!$H:$W,16,FALSE) -> Laura Cestau
A93: O3491 | B93: Pocketfilters Glucose Loading | D93: mohamedchedly.benghorbel@group-ips.com | E93: fiete.heinrich@group-ips.com | G93: Cargill GmbH Barby (Elbe) | H93: Lump sum | I93: 46028 | K93: 46028 | L93: 32000 | M93: fiete.heinrich@group-ips.com | N93: 0 | O93: 0 | P93: Work in progress | R93: Food & Beverages | S93: Architecture|Engineering|Project Management|Engineering Coordination|Piping Engineering|Civil engineering | T93: IPS Germany | U93: IPS Belgium | V93: Q8964 | W93: 0.5 | X93: 32000 | Z93: =VLOOKUP(D93,'ZOHO Export'!$H:$W,16,FALSE) -> Mohamed Chedly Ben Ghorbel | AA93: =VLOOKUP(E93,'ZOHO Export'!$H:$W,16,FALSE) -> Fiete Heinrich
A94: O3490 | B94: PE1013_EtudesEquipement | D94: bilel.khemakhem@group-ips.com | E94: wissem.bensaid@group-ips.com | G94: SCIF | H94: Lump sum | I94: 46021 | K94: 46021 | L94: 38000 | M94: wissem.bensaid@group-ips.com | N94: 0 | O94: 0 | P94: Work in progress | R94: Chemicals | S94: Engineering|Project Management|Mechanical Engineering|Piping Engineering|Structural engineering | T94: IAPS Tunisia | U94: IAPS Tunisia | V94: Q9084 | W94: 0 | X94: 38000 | Z94: =VLOOKUP(D94,'ZOHO Export'!$H:$W,16,FALSE) -> Bilel Khemakhem | AA94: =VLOOKUP(E94,'ZOHO Export'!$H:$W,16,FALSE) -> Wissem Bensaid
A95: O3489 | B95: Lindt Kitchen 3D Modeling | D95: evan.bardinas@group-ips.com | E95: mark.sensenig@group-ips.com | G95: Lindt & Sprungli USA | H95: Lump sum | I95: 46020 | K95: 46020 | L95: 13824 | M95: evan.bardinas@group-ips.com | N95: 0 | O95: 0 | P95: Work in progress | R95: Food & Beverages | S95: Engineering|Engineering Coordination|Piping Engineering | T95: IPS USA | U95: IAPS Tunisia|IPS USA | V95: Q9050 | W95: 2 | X95: 13824 | Z95: =VLOOKUP(D95,'ZOHO Export'!$H:$W,16,FALSE) -> Evan Bardinas | AA95: =VLOOKUP(E95,'ZOHO Export'!$H:$W,16,FALSE) -> Mark Sensenig
A96: O3488 | B96: PE1012_Etude RÃ©servoir Daoui | D96: mansour.hamza@group-ips.com | E96: wissem.bensaid@group-ips.com | G96: JESA | H96: Lump sum | I96: 46016 | K96: 46016 | L96: 90500 | M96: wissem.bensaid@group-ips.com | N96: 0 | O96: 0 | P96: Work in progress | R96: Chemicals | S96: Engineering|Project Management|Mechanical Engineering|Piping Engineering|Process Engineering|Procurement|Civil engineering|Structural engineering | T96: IAPS Tunisia | U96: IAPS Tunisia | V96: Q9062 | W96: 0 | X96: 90500 | Z96: =VLOOKUP(D96,'ZOHO Export'!$H:$W,16,FALSE) -> Mansour Hamza | AA96: =VLOOKUP(E96,'ZOHO Export'!$H:$W,16,FALSE) -> Wissem Bensaid
A97: O3487 | B97: OPUS-PED | D97: nadege.herment@group-ips.com | E97: nicolas.dubois@group-ips.com | F97: amandyne.rosart@group-ips.com | G97: TAKEDA (BELGIUM) | H97: Reimbursable | I97: 46013 | K97: 46013 | L97: 26754.72 | M97: nicolas.dubois@group-ips.com | N97: 0 | O97: 0 | P97: Work in progress | R97: Life Sciences | S97: Engineering|Project Management | T97: IPS Belgium | U97: IPS Belgium | V97: Q9056 | W97: 100 | X97: 26754.72 | Z97: =VLOOKUP(D97,'ZOHO Export'!$H:$W,16,FALSE) -> Nadège Herment | AA97: =VLOOKUP(E97,'ZOHO Export'!$H:$W,16,FALSE) -> Nicolas Dubois
A98: O3486 | B98: MADNUN OFFICE UNIVERSAL | D98: iker.ruiz-apilanez@group-ips.com | E98: cristina.rubio.rodriguez@group-ips.com | F98: yasmine.benrhaiem@group-ips.com | G98: UNIVERSAL MUSIC | H98: Lump sum | I98: 46013 | K98: 46013 | L98: 49410 | M98: juan.juarez@group-ips.com | N98: 0 | O98: 0 | P98: Work in progress | R98: Buildings | S98: Engineering|Project Management|Construction Management|Engineering Coordination|Procurement | T98: IPS Spain | U98: IPS Spain | V98: Q9072 | W98: 2 | X98: 49410 | Z98: =VLOOKUP(D98,'ZOHO Export'!$H:$W,16,FALSE) -> Iker Ruiz | AA98: =VLOOKUP(E98,'ZOHO Export'!$H:$W,16,FALSE) -> Cristina Rubio Rodríguez
A99: O3485 | B99: Remplacement rÃ©seau enterrÃ© | D99: andrew.delhaisse@group-ips.com | E99: pascal.cornuez@group-ips.com | F99: amandyne.rosart@group-ips.com | G99: Carlsberg Supply Company AG | H99: Reimbursable | I99: 46006 | J99: 46054 | K99: 46006 | L99: 5076.75 | M99: pascal.cornuez@group-ips.com | N99: 0 | O99: 0 | P99: Finished | R99: Food & Beverages | S99: Architecture|Project Management|Sustainable Process & Environment|Masterplan|Consulting|Procurement | T99: IPS France | U99: IPS Belgium | V99: Q9044 | W99: 1000000 | X99: 5076.75 | Z99: =VLOOKUP(D99,'ZOHO Export'!$H:$W,16,FALSE) -> Andrew Delhaisse | AA99: =VLOOKUP(E99,'ZOHO Export'!$H:$W,16,FALSE) -> Pascal Cornuez
A100: O3484 | B100: Hot-rolled coils | D100: boris.krastev@group-ips.com | E100: marcos.delgado@group-ips.com | F100: amandyne.rosart@group-ips.com | G100: Metinvest Adria SPA | H100: Reimbursable | I100: 46006 | K100: 46006 | L100: 2092318.5 | M100: yannick.vega@group-ips.com | N100: 0 | O100: 0 | P100: Work in progress | R100: Primary & Metals | S100: Project Management|Project Quality Support Team|Project Assistance|Cost Management | T100: Group-IPS | U100: IPS Belgium|IPS Spain|Group-IPS | V100: Q9016 | W100: 2600 | X100: 2092318.5 | Z100: =VLOOKUP(D100,'ZOHO Export'!$H:$W,16,FALSE) -> Boris Krastev | AA100: =VLOOKUP(E100,'ZOHO Export'!$H:$W,16,FALSE) -> Marcos Delgado Lopez
...

Sheet ZOHO Export
A1: ZOHO_LINK_ID | B1: Date of joining | C1: Date of exit | D1: First Name | E1: Last Name | F1: Nick Name | G1: Short Email | H1: Email ID | I1: Legal Entity | J1: Belonging Entity | K1: Department | L1: Engineering Discipline | M1: Seniority level | N1: Location | O1: Work location | P1: Reporting To | Q1: Email ID | R1: IPS Mobile Phone | S1: Training Eisenhuttenstadt | T1: Company function | U1: Years at IPS | V1: External Company Name | W1: Full Name
A2: 26362000045192364 | B2: 46099 | C2: 46173 | D2: Naroa | E2: Simal | F2: naroa.simal | G2: naroa.simal@group-ips.com | H2: naroa.simal@group-ips.com | I2: IPS Spain | J2: Same as Payroll Entity | K2: Consulting | M2: Junior | N2: Madrid | O2: Madrid | P2: Alfredo Bartolome 792 | Q2: alfredo.bartolome@group-ips.com | S2: Nee | T2: Team Member | W2: =D2&" "&E2 -> Naroa Simal
A3: 26362000045143744 | B3: 46097 | D3: Eduardo | E3: Barreda | F3: eduardo.barreda | G3: eduardo.barreda@group-ips.com | H3: eduardo.barreda@group-ips.com | I3: IPS Spain | J3: Same as Payroll Entity | K3: Consulting | M3: Junior | N3: Madrid | O3: Madrid | P3: Alfredo Bartolome 792 | Q3: alfredo.bartolome@group-ips.com | R3: 34-663927033 | S3: Nee | T3: Team Member | W3: =D3&" "&E3 -> Eduardo Barreda
A4: 26362000044880877 | B4: 46090 | C4: 46177 | D4: Jean | E4: Soares Lopes | F4: JSO | G4: JSO@group-ips.com | H4: jean.soares@group-ips.com | I4: IPS Belgium | J4: Same as Payroll Entity | K4: Human Resources | M4: Junior | N4: Nivelles | O4: Nivelles | P4: Rachel Saïdi 429 | Q4: rachel.saidi@group-ips.com | S4: Nee | T4: Team Member | W4: =D4&" "&E4 -> Jean Soares Lopes
A5: 26362000044770447 | B5: 46083 | D5: Victoria | E5: Peponnet | F5: VPE | G5: VPE@group-ips.com | H5: victoria.peponnet@group-ips.com | I5: IPS Spain | J5: Same as Payroll Entity | K5: Food & Beverages | M5: Intermediate | N5: Barcelona | O5: Barcelona | P5: Paqui Romero 213 | Q5: paqui.romero@group-ips.com | R5: 34-663567762 | S5: Nee | T5: Team Member | W5: =D5&" "&E5 -> Victoria Peponnet
A6: 26362000044726376 | B6: 46076 | C6: 46172 | D6: Zakaria | E6: Tahiri | F6: ZTA | G6: ZTA@group-ips.com | H6: zakaria.tahiri@group-ips.com | I6: Group-IPS | J6: Same as Payroll Entity | K6: Business Development | M6: Junior | N6: Madrid | O6: Madrid | P6: Yannick Vega Fernandez 95 | Q6: yannick.vega@group-ips.com | S6: Nee | T6: Team Member | W6: =D6&" "&E6 -> Zakaria Tahiri
A7: 26362000044690560 | B7: 46070 | D7: ammar | E7: magthoub | F7: AGT | G7: AGT@group-ips.com | H7: ammar.magthoub@group-ips.com | I7: IAPS Tunisia | J7: Same as Payroll Entity | K7: Engineering | L7: Civil | M7: Senior | N7: Jeddah | O7: Jeddah | P7: Wissem Bensaid 96 | Q7: wissem.bensaid@group-ips.com | S7: Nee | T7: Team Member | U7: 1 maand(en) | V7: Ammar.magthoub | W7: =D7&" "&E7 -> ammar magthoub
A8: 26362000044626246 | B8: 46044 | D8: Zied | E8: Daoud | F8: ZDA | G8: ZDA@group-ips.com | H8: zied.daoud@group-ips.com | I8: IAPS Tunisia | J8: Same as Payroll Entity | K8: Marketing | M8: Senior | N8: Sfax | O8: Sfax | P8: Wissem Bensaid 96 | Q8: wissem.bensaid@group-ips.com | S8: Nee | T8: Team Member | U8: 1 maand(en) | V8: daoud Zied | W8: =D8&" "&E8 -> Zied Daoud
A9: 26362000044602155 | B9: 46132 | C9: 46233 | D9: Gilles | E9: Seyns | F9: GSY | G9: GSY@group-ips.com | H9: gilles.seyns@group-ips.com | I9: IPS Spain | J9: Group-IPS | K9: Business Development | M9: Junior | N9: Madrid | O9: Madrid | P9: Yannick Vega Fernandez 95 | Q9: yannick.vega@group-ips.com | S9: Nee | T9: Team Member | U9: -1 maand(en) | W9: =D9&" "&E9 -> Gilles Seyns
A10: 26362000044602044 | B10: 46069 | C10: 46171 | D10: Amélie | E10: Cools | F10: COO | G10: COO@group-ips.com | H10: amelie.cools@group-ips.com | I10: IPS Spain | J10: Group-IPS | K10: Business Development | M10: Junior | N10: Madrid | O10: Madrid | P10: Yannick Vega Fernandez 95 | Q10: yannick.vega@group-ips.com | S10: Nee | T10: Team Member | U10: 1 maand(en) | W10: =D10&" "&E10 -> Amélie Cools
A11: 26362000044599699 | B11: 46069 | D11: Miguel | E11: San Millán | F11: MSM | G11: MSM@group-ips.com | H11: miguel.sanmillan@group-ips.com | I11: IPS Spain | J11: Same as Payroll Entity | K11: Buildings | M11: Manager | N11: Madrid | O11: Madrid | P11: Juan Juarez Quintana 164 | Q11: juan.juarez@group-ips.com | S11: Nee | T11: Team Member | U11: 1 maand(en) | W11: =D11&" "&E11 -> Miguel San Millán
A12: 26362000044599408 | B12: 46083 | D12: Jolie | E12: Verfaille | F12: JVF | G12: JVF@group-ips.com | H12: jolie.verfaille@group-ips.com | I12: IPS Spain | J12: Group-IPS | K12: Business Development | M12: Junior | N12: Madrid | O12: Madrid | P12: Yannick Vega Fernandez 95 | Q12: yannick.vega@group-ips.com | S12: Nee | T12: Team Member | W12: =D12&" "&E12 -> Jolie Verfaille
A13: 26362000044599337 | B13: 46069 | C13: 46171 | D13: Noor | E13: Maes | F13: NMS | G13: NMS@group-ips.com | H13: noor.maes@group-ips.com | I13: IPS Spain | J13: Group-IPS | K13: Business Development | M13: Junior | N13: Madrid | O13: Madrid | P13: Yannick Vega Fernandez 95 | Q13: yannick.vega@group-ips.com | S13: Nee | T13: Team Member | U13: 1 maand(en) | W13: =D13&" "&E13 -> Noor Maes
A14: 26362000044599246 | B14: 46069 | C14: 46171 | D14: Imiana | E14: Van Achter | F14: IVA | G14: IVA@group-ips.com | H14: imiana.vanachter@group-ips.com | I14: IPS Spain | J14: Group-IPS | K14: Human Resources | M14: Junior | N14: Madrid | O14: Madrid | P14: Ana Montejo Del Castillo 135 | Q14: ana.montejo@group-ips.com | S14: Nee | T14: Team Member | U14: 1 maand(en) | W14: =D14&" "&E14 -> Imiana Van Achter
A15: 26362000044599177 | B15: 46069 | C15: 46171 | D15: Senne | E15: De Brucker | F15: SDB | G15: SDB@group-ips.com | H15: senne.debrucker@group-ips.com | I15: IPS Spain | J15: Group-IPS | K15: Human Resources | M15: Junior | N15: Madrid | O15: Madrid | P15: Patricia Rebollo 433 | Q15: patricia.rebollo@group-ips.com | S15: Nee | T15: Team Member | U15: 1 maand(en) | W15: =D15&" "&E15 -> Senne De Brucker
A16: 26362000044599110 | B16: 46069 | C16: 46171 | D16: Ioannis | E16: Cosmuta | F16: ICO | G16: ICO@group-ips.com | H16: ioannis.cosmuta@group-ips.com | I16: IPS Spain | J16: Group-IPS | K16: Business Development | M16: Junior | N16: Madrid | O16: Madrid | P16: Yannick Vega Fernandez 95 | Q16: yannick.vega@group-ips.com | S16: Nee | T16: Team Member | U16: 1 maand(en) | W16: =D16&" "&E16 -> Ioannis Cosmuta
A17: 26362000044599041 | B17: 46069 | C17: 46171 | D17: Loic | E17: Beelprez | F17: LBP | G17: LBP@group-ips.com | H17: loic.beelprez@group-ips.com | I17: IPS Spain | J17: Group-IPS | K17: Business Development | M17: Junior | N17: Madrid | O17: Madrid | P17: Yannick Vega Fernandez 95 | Q17: yannick.vega@group-ips.com | S17: Nee | T17: Team Member | U17: 1 maand(en) | W17: =D17&" "&E17 -> Loic Beelprez
A18: 26362000044593974 | B18: 46069 | C18: 46171 | D18: Simon | E18: Van der Paal | F18: SVP | G18: SVP@group-ips.com | H18: simon.vanderpaal@group-ips.com | I18: IPS Spain | J18: Group-IPS | K18: Business Development | M18: Junior | N18: Madrid | O18: Madrid | P18: Yannick Vega Fernandez 95 | Q18: yannick.vega@group-ips.com | S18: Nee | T18: Team Member | U18: 1 maand(en) | W18: =D18&" "&E18 -> Simon Van der Paal
A19: 26362000044593839 | B19: 46069 | D19: Sofia | E19: Prytoluk | F19: SPR | G19: SPR@group-ips.com | H19: sofia.prytoluk@group-ips.com | I19: Arquid | J19: Same as Payroll Entity | K19: Architecture | M19: Junior | N19: Barcelona | O19: Barcelona | P19: Gonzalo Martin 561 | Q19: gonzalo.martin@group-ips.com | S19: Nee | T19: Team Member | U19: 1 maand(en) | W19: =D19&" "&E19 -> Sofia Prytoluk
A20: 26362000044570296 | B20: 46069 | C20: 46171 | D20: Arzoe | E20: Parsaie | F20: RPA | G20: RPA@group-ips.com | H20: arzoe.parsaie@group-ips.com | I20: IPS Belgium | J20: Same as Payroll Entity | K20: Business Development | M20: Junior | N20: Nivelles | O20: Nivelles | P20: Yannick Vega Fernandez 95 | Q20: yannick.vega@group-ips.com | S20: Nee | T20: Team Member | U20: 1 maand(en) | W20: =D20&" "&E20 -> Arzoe Parsaie
A21: 26362000044335941 | B21: 46055 | C21: 46157 | D21: Tiziano | E21: Lavia | F21: TLI | G21: TLI@group-ips.com | H21: tiziano.lavia@group-ips.com | I21: IPS Belgium | J21: Same as Payroll Entity | K21: Finance & Accounting | M21: Junior | N21: Nivelles | O21: Nivelles | P21: Pascale Olivy 519 | Q21: pascale.olivy@group-ips.com | S21: Nee | T21: Team Member | U21: 1 maand(en) | W21: =D21&" "&E21 -> Tiziano Lavia
A22: 26362000044001223 | B22: 46034 | C22: 46173 | D22: Andrea | E22: Bartolomé | F22: AND | G22: AND@group-ips.com | H22: andrea.bartolome@group-ips.com | I22: Arquid | J22: Arquid | K22: Architecture | M22: Junior | N22: Madrid | O22: Madrid | P22: Maximiliano Martin Parra 79 | Q22: maximiliano.martin@group-ips.com | S22: Nee | T22: Team Member | U22: 2 maand(en) | W22: =D22&" "&E22 -> Andrea Bartolomé
A23: 26362000044001098 | B23: 46034 | D23: Iker | E23: Ruiz | F23: IKR | G23: IKR@group-ips.com | H23: iker.ruiz-apilanez@group-ips.com | I23: IPS Spain | J23: Same as Payroll Entity | K23: Buildings | M23: Intermediate | N23: Madrid | O23: Madrid | P23: Miguel Menéndez 132 | Q23: miguel.menendez@group-ips.com | R23: 34-663091184 | S23: Nee | T23: Team Member | U23: 2 maand(en) | W23: =D23&" "&E23 -> Iker Ruiz
A24: 26362000043970008 | B24: 46029 | D24: Antonio | E24: Iglesias | F24: AIG | G24: AIG@group-ips.com | H24: antonio.iglesias@group-ips.com | I24: IPS Spain | J24: Group-IPS | K24: Consulting | M24: Manager | N24: Madrid | O24: Madrid | P24: Carlos Bravo Fernández 150 | Q24: carlos.bravo.fernandez@group-ips.com | S24: Nee | T24: International Business Unit Manager | U24: 2 maand(en) | W24: =D24&" "&E24 -> Antonio Iglesias
A25: 26362000043472462 | B25: 45992 | D25: Faouzi | E25: Maallem | F25: FAM | G25: FAM@group-ips.com | H25: Faouzi.maallem@group-ips.com | I25: IAPS Tunisia | J25: Same as Payroll Entity | K25: Engineering | M25: Senior | N25: Sfax | O25: Sfax | P25: Wissem Bensaid 96 | Q25: wissem.bensaid@group-ips.com | S25: Nee | T25: Team Member | U25: 3 maand(en) | V25: Faouzi MAALLEM | W25: =D25&" "&E25 -> Faouzi Maallem
A26: 26362000043472405 | B26: 45992 | D26: Jean Martial | E26: N'goran | F26: JMN | G26: JMN@group-ips.com | H26: Jean.martialnggoran@group-ips.com | I26: IAPS Tunisia | J26: Same as Payroll Entity | K26: Engineering | M26: Senior | N26: Sfax | O26: Sfax | P26: Wissem Bensaid 96 | Q26: wissem.bensaid@group-ips.com | S26: Nee | T26: Team Member | U26: 3 maand(en) | V26: Jean Martial N'GORAN | W26: =D26&" "&E26 -> Jean Martial N'goran
A27: 26362000043380771 | B27: 45992 | D27: Yasmine | E27: Ben Rhaiem | F27: YBR | G27: YBR@group-ips.com | H27: yasmine.benrhaiem@group-ips.com | I27: IAPS Tunisia | J27: IPS Belgium | K27: Project Quality Support Team | M27: Junior | N27: Sfax | O27: Sfax | P27: Bram Puttemans 141 | Q27: bram.puttemans@group-ips.com | R27: 216-29476363 | S27: Nee | T27: Team Member | U27: 3 maand(en) | W27: =D27&" "&E27 -> Yasmine Ben Rhaiem
A28: 26362000043347766 | B28: 45994 | D28: Darya | E28: Ligay | F28: DLI | G28: DLI@group-ips.com | H28: darya.ligay@group-ips.com | I28: IPS Germany | J28: Same as Payroll Entity | K28: Food & Beverages | M28: Junior | N28: Berlin | O28: Berlin | P28: Fiete Heinrich 175 | Q28: fiete.heinrich@group-ips.com | S28: Nee | T28: Team Member | U28: 3 maand(en) | W28: =D28&" "&E28 -> Darya Ligay
A29: 26362000043339580 | B29: 45992 | D29: Princilia | E29: Wandji | F29: PWA | G29: PWA@group-ips.com | H29: princilia.wandji@group-ips.com | I29: IPS Germany | J29: Same as Payroll Entity | K29: Permitting | M29: Junior | N29: Berlin | O29: Berlin | P29: Anja Lüttringhaus 492 | Q29: anja.luettringhaus@group-ips.com | R29: 49-1709492233 | S29: Nee | T29: Team Member | U29: 3 maand(en) | W29: =D29&" "&E29 -> Princilia Wandji
A30: 26362000043311968 | B30: 45992 | D30: Hussam | E30: Bayazid | F30: HBY | G30: HBY@group-ips.com | H30: hussam.bayazid@group-ips.com | I30: IPS Germany | J30: Same as Payroll Entity | K30: Food & Beverages | M30: Intermediate | N30: Berlin | O30: Berlin | P30: Fiete Heinrich 175 | Q30: fiete.heinrich@group-ips.com | R30: 01709492215 | S30: Nee | T30: Team Member | U30: 3 maand(en) | W30: =D30&" "&E30 -> Hussam Bayazid
A31: 26362000043142279 | B31: 45978 | D31: Teresa | E31: García Sanz | F31: TGA | G31: TGA@group-ips.com | H31: teresa.garcia@group-ips.com | I31: IPS Germany | J31: Arquid | K31: Architecture | M31: Junior | N31: Berlin | O31: Berlin | P31: Miguel Laporta 374 | Q31: miguel.laporta@group-ips.com | S31: Nee | T31: Team Member | U31: 4 maand(en) | W31: =D31&" "&E31 -> Teresa García Sanz
A32: 26362000043054953 | B32: 45971 | D32: Nicolas | E32: Rousselet | F32: NIR | G32: NIR@group-ips.com | H32: nicolas.rousselet@group-ips.com | I32: IPS USA | J32: Same as Payroll Entity | K32: Project Management | M32: Junior | N32: Philadelphia | O32: Philadelphia | P32: Mark Sensenig 122 | Q32: mark.sensenig@group-ips.com | S32: Nee | T32: Team Member | U32: 4 maand(en) | W32: =D32&" "&E32 -> Nicolas Rousselet
A33: 26362000043009513 | B33: 45992 | D33: Said | E33: Ait Ali | F33: SAI | G33: SAI@group-ips.com | H33: said.aitali@group-ips.com | I33: IPS Belgium | J33: Same as Payroll Entity | K33: Buildings | M33: Senior | N33: Nivelles | O33: Nivelles | P33: Juan Juarez Quintana 164 | Q33: juan.juarez@group-ips.com | S33: Nee | T33: Team Member | U33: 3 maand(en) | W33: =D33&" "&E33 -> Said Ait Ali
A34: 26362000042964132 | B34: 45972 | D34: Faustino | E34: López Garrido | F34: FLO | G34: FLO@group-ips.com | H34: faustino.lopez@group-ips.com | I34: IPS Spain | J34: Same as Payroll Entity | K34: Engineering | L34: Mechanical;Pipeline;Piping;Utilities | M34: Senior | N34: Barcelona | O34: Barcelona | P34: Marcos Delgado Lopez 254 | Q34: marcos.delgado@group-ips.com | R34: 34-663937680 | S34: Nee | T34: Team Member | U34: 4 maand(en) | W34: =D34&" "&E34 -> Faustino López Garrido
A35: 26362000042860661 | B35: 45964 | D35: Azim | E35: Azrak | F35: AAZ | G35: AAZ@group-ips.com | H35: azim.azrak@group-ips.com | I35: IPS Germany | J35: Same as Payroll Entity | K35: Food & Beverages | M35: Junior | N35: Berlin | O35: Berlin | P35: Fiete Heinrich 175 | Q35: fiete.heinrich@group-ips.com | R35: 49-1711862348 | S35: Nee | T35: Team Member | U35: 4 maand(en) | W35: =D35&" "&E35 -> Azim Azrak
A36: 26362000042791016 | B36: 45964 | D36: Intissar | E36: Lhannaoui | F36: ILH | G36: ILH@group-ips.com | H36: intissar.lhannaoui@group-ips.com | I36: IPS Belgium | J36: Same as Payroll Entity | K36: Safety | M36: Junior | N36: Nivelles | O36: Nivelles | P36: Jurgen Van Den Driessche 114 | Q36: jurgen.van.den.driessche@group-ips.com | R36: 32-0470742607 | S36: Nee | T36: Team Member | U36: 4 maand(en) | W36: =D36&" "&E36 -> Intissar Lhannaoui
A37: 26362000042780196 | B37: 45964 | D37: Jaspe | E37: Kisoka | F37: JKI | G37: JKI@group-ips.com | H37: jaspe.kisoka@group-ips.com | I37: IPS Belgium | J37: Same as Payroll Entity | K37: Safety | M37: Junior | N37: Nivelles | O37: Nivelles | P37: Jurgen Van Den Driessche 114 | Q37: jurgen.van.den.driessche@group-ips.com | R37: 32-470744057 | S37: Nee | T37: Team Member | U37: 4 maand(en) | W37: =D37&" "&E37 -> Jaspe Kisoka
A38: 26362000042764376 | B38: 45957 | C38: 46203 | D38: Alvaro | E38: Gil | F38: AGL | G38: AGL@group-ips.com | H38: alvaro.gil@group-ips.com | I38: Arquid | J38: Arquid | K38: Architecture | M38: Junior | N38: Madrid | O38: Madrid | P38: Maximiliano Martin Parra 79 | Q38: maximiliano.martin@group-ips.com | S38: Nee | T38: Team Member | U38: 4 maand(en) | W38: =D38&" "&E38 -> Alvaro Gil
A39: 26362000042765115 | B39: 45945 | D39: Sander | E39: Devoogt | F39: sdt | G39: SDT@group-ips.com | H39: sander.devoogt@group-ips.com | I39: IPS Belgium | J39: Same as Payroll Entity | K39: Safety | M39: Intermediate | N39: Nivelles | O39: Nivelles | P39: Jurgen Van Den Driessche 114 | Q39: jurgen.van.den.driessche@group-ips.com | S39: Nee | T39: Team Member | U39: 5 maand(en) | V39: Groupe Trimako | W39: =D39&" "&E39 -> Sander Devoogt
A40: 26362000042757823 | B40: 45964 | D40: Claudia | E40: Gonzalez | F40: CEZ | G40: CEZ@group-ips.com | H40: claudia.gonzalez@group-ips.com | I40: IPS Spain | J40: Same as Payroll Entity | K40: Food & Beverages | M40: Junior | N40: Valencia | O40: Valencia | P40: Paqui Romero 213 | Q40: paqui.romero@group-ips.com | R40: 34-663930147 | S40: Nee | T40: Team Member | U40: 4 maand(en) | W40: =D40&" "&E40 -> Claudia Gonzalez
A41: 26362000042630378 | B41: 45957 | D41: Awa | E41: Sow Carrasco | F41: SOW | G41: SOW@group-ips.com | H41: awa.sow@group-ips.com | I41: IPS Spain | J41: Same as Payroll Entity | K41: Buildings | M41: Junior | N41: Madrid | O41: Madrid | P41: Miguel Menéndez 132 | Q41: miguel.menendez@group-ips.com | S41: Nee | T41: Team Member | U41: 4 maand(en) | W41: =D41&" "&E41 -> Awa Sow Carrasco
A42: 26362000042584664 | B42: 45950 | D42: Oliver | E42: Holden | F42: OHO | G42: OHO@group-ips.com | H42: oliver.holden@group-ips.com | I42: IPS UK | J42: Same as Payroll Entity | K42: Project Management | M42: Intermediate | N42: Warrington | O42: Warrington | P42: Mac Olean 260 | Q42: mac.o.lean@group-ips.com | S42: Nee | T42: Team Member | U42: 4 maand(en) | W42: =D42&" "&E42 -> Oliver Holden
A43: 26362000042531239 | B43: 45943 | D43: Scott | E43: Thomson | F43: SCT | G43: SCT@group-ips.com | H43: scott.thomson@group-ips.com | I43: IPS UK | J43: Same as Payroll Entity | K43: Business Development | M43: Junior | N43: Warrington | O43: Warrington | P43: Mac Olean 260 | Q43: mac.o.lean@group-ips.com | S43: Nee | T43: Team Member | U43: 5 maand(en) | W43: =D43&" "&E43 -> Scott Thomson
A44: 26362000042421963 | B44: 45936 | D44: Bert | E44: Van Loock | F44: BVL | G44: BVL@group-ips.com | H44: bert.vanloock@group-ips.com | I44: IPS Belgium | J44: Same as Payroll Entity | K44: Safety | M44: Intermediate | N44: Nivelles | O44: Nivelles | P44: Jurgen Van Den Driessche 114 | Q44: jurgen.van.den.driessche@group-ips.com | R44: 32-470742017 | S44: Nee | T44: Team Member | U44: 5 maand(en) | W44: =D44&" "&E44 -> Bert Van Loock
A45: 26362000042361207 | B45: 45931 | D45: Fatma | E45: Boujelben | F45: FBO | G45: FBO@group-ips.com | H45: fatma.boujelben@group-ips.com | I45: IAPS Tunisia | J45: Same as Payroll Entity | K45: Marketing | M45: Senior | N45: Sfax | O45: Sfax | P45: Wissem Bensaid 96 | Q45: wissem.bensaid@group-ips.com | R45: 216-29389221 | S45: Nee | T45: Team Member | U45: 5 maand(en) | W45: =D45&" "&E45 -> Fatma Boujelben
A46: 26362000042235873 | B46: 45929 | D46: Emma | E46: Elliott | F46: EEL | G46: EEL@group-ips.com | H46: emma.elliott@group-ips.com | I46: IPS USA | J46: Same as Payroll Entity | K46: Project Management | M46: Junior | N46: Philadelphia | O46: Philadelphia | P46: Pranay Pawar 123 | Q46: pranay.pawar@group-ips.com | R46: 8566303518 | S46: Nee | T46: Team Member | U46: 5 maand(en) | W46: =D46&" "&E46 -> Emma Elliott
A47: 26362000042228204 | B47: 45923 | D47: Marc | E47: Van Overtveldt | F47: MVO | G47: MVO@group-ips.com | H47: Marc.VanOvertveldt@group-ips.com | I47: IPS Belgium | J47: Same as Payroll Entity | K47: Safety | M47: Senior | N47: Mechelen | O47: Mechelen | P47: Jurgen Van Den Driessche 114 | Q47: jurgen.van.den.driessche@group-ips.com | S47: Nee | T47: Team Member | U47: 5 maand(en) | V47: Proprevent | W47: =D47&" "&E47 -> Marc Van Overtveldt
A48: 26362000042171980 | B48: 45915 | D48: emrah | E48: karahan | F48: EMK | G48: EMK@group-ips.com | H48: emrah.karahan@group-ips.com | I48: IPS Turkey | J48: Same as Payroll Entity | K48: Engineering | M48: Senior | N48: Istanbul | O48: Istanbul | P48: Wissem Bensaid 96 | Q48: wissem.bensaid@group-ips.com | S48: Nee | T48: Team Member | U48: 6 maand(en) | V48: UGUR | W48: =D48&" "&E48 -> emrah karahan
A49: 26362000042171929 | B49: 45915 | D49: ismail | E49: ucuncu | F49: IUC | G49: IUC@group-ips.com | H49: ismail.ucuncu@group-ips.com | I49: IPS Turkey | J49: Same as Payroll Entity | K49: Engineering | M49: Senior | N49: Istanbul | O49: Istanbul | P49: Wissem Bensaid 96 | Q49: wissem.bensaid@group-ips.com | S49: Nee | T49: Team Member | U49: 6 maand(en) | V49: UGUR | W49: =D49&" "&E49 -> ismail ucuncu
A50: 26362000042158963 | B50: 45922 | D50: Hakim | E50: Ben Aissa | F50: HAK | G50: HAK@group-ips.com | H50: hakim.benaissa@group-ips.com | I50: IPS Belgium | J50: Same as Payroll Entity | K50: Engineering | L50: HVAC | M50: Senior | N50: Nivelles | O50: Nivelles | P50: Marcos Delgado Lopez 254 | Q50: marcos.delgado@group-ips.com | R50: 32-470741526 | S50: Nee | T50: Team Member | U50: 5 maand(en) | W50: =D50&" "&E50 -> Hakim Ben Aissa
A51: 26362000042158814 | B51: 45931 | D51: Raf | E51: Vissers | F51: RAV | G51: RAV@group-ips.com | H51: raf.vissers@group-ips.com | I51: IPS Belgium | J51: Same as Payroll Entity | K51: Primary & Metals | M51: Junior | N51: Nivelles | O51: Nivelles | P51: William Beyst 161 | Q51: william.beyst@group-ips.com | R51: 32-470741377 | S51: Nee | T51: Team Member | U51: 5 maand(en) | W51: =D51&" "&E51 -> Raf Vissers
A52: 26362000042158733 | B52: 45931 | D52: Niels | E52: Van Osselaer | F52: NVO | G52: NVO@group-ips.com | H52: niels.vanosselaer@group-ips.com | I52: IPS Belgium | J52: Same as Payroll Entity | K52: Chemicals | M52: Junior | N52: Nivelles | O52: Nivelles | P52: Peter Holvoet 155 | Q52: peter.holvoet@group-ips.com | R52: 32-470740306 | S52: Nee | T52: Team Member | U52: 5 maand(en) | W52: =D52&" "&E52 -> Niels Van Osselaer
A53: 26362000042155729 | B53: 45922 | D53: Ayberk | E53: Özyürek | F53: AYO | G53: AYO@group-ips.com | H53: ayberk.ozyurek@group-ips.com | I53: IPS Germany | J53: Same as Payroll Entity | K53: Buildings | M53: Junior | N53: Berlin | O53: Berlin | P53: Juan Juarez Quintana 164 | Q53: juan.juarez@group-ips.com | R53: 49-15117964070 | S53: Nee | T53: Team Member | U53: 5 maand(en) | W53: =D53&" "&E53 -> Ayberk Özyürek
A54: 26362000042009903 | B54: 45903 | D54: abdullah | E54: alamoudi | F54: AAH | G54: AAH@group-ips.com | H54: abdullah.alamoudi@group-ips.com | I54: IAPS Tunisia | J54: Same as Payroll Entity | K54: Engineering | M54: Senior | N54: Sfax | O54: Sfax | P54: Wissem Bensaid 96 | Q54: wissem.bensaid@group-ips.com | S54: Nee | T54: Team Member | U54: 6 maand(en) | V54: Abdullah M ALAmoudi | W54: =D54&" "&E54 -> abdullah alamoudi
A55: 26362000042006555 | B55: 45916 | D55: Oleksandra | E55: Shmatok | F55: OSH | G55: OSH@group-ips.com | H55: oleksandra.shmatok@group-ips.com | I55: IPS Germany | J55: Same as Payroll Entity | K55: Human Resources | M55: Junior | N55: Berlin | O55: Berlin | P55: Patricia Rebollo 433 | Q55: patricia.rebollo@group-ips.com | S55: Nee | T55: Team Member | U55: 6 maand(en) | W55: =D55&" "&E55 -> Oleksandra Shmatok
A56: 26362000041993327 | B56: 45915 | D56: Antoine | E56: Assaf | F56: AAS | G56: AAS@group-ips.com | H56: antoine.assaf@group-ips.com | I56: IPS Belgium | J56: Same as Payroll Entity | K56: Data Centers | M56: Senior | N56: Nivelles | O56: Nivelles | P56: Emmanuel Van De Casteele 30 | Q56: emmanuel.van.de.casteele@group-ips.com | S56: Nee | T56: Team Member | U56: 6 maand(en) | W56: =D56&" "&E56 -> Antoine Assaf
A57: 26362000041809364 | B57: 45901 | D57: David | E57: Garaizar | F57: DAG | G57: DAG@group-ips.com | H57: david.garaizar@group-ips.com | I57: Arquid | J57: Arquid | K57: Architecture | M57: Intermediate | N57: Madrid | O57: Madrid | P57: Maximiliano Martin Parra 79 | Q57: maximiliano.martin@group-ips.com | R57: 34-637042184 | S57: Nee | T57: Team Member | U57: 6 maand(en) | W57: =D57&" "&E57 -> David Garaizar
A58: 26362000041809259 | B58: 45901 | D58: Claudia | E58: Noguera Herebia | F58: CNH | G58: CNH@group-ips.com | H58: claudia.noguera@group-ips.com | I58: IPS Spain | J58: Same as Payroll Entity | K58: Digital Supply Chain & Operations | M58: Intermediate | N58: Madrid | O58: Madrid | P58: Carlos Bravo Fernández 150 | Q58: carlos.bravo.fernandez@group-ips.com | R58: 34-674257686 | S58: Nee | T58: Team Member | U58: 6 maand(en) | W58: =D58&" "&E58 -> Claudia Noguera Herebia
A59: 26362000041780095 | B59: 45901 | D59: Vincent | E59: Verbeke | F59: VIV | G59: VIV@group-ips.com | H59: vincent.verbeke@group-ips.com | I59: IPS Belgium | J59: Same as Payroll Entity | K59: Life Sciences | M59: Junior | N59: Nivelles | O59: Nivelles | P59: Xavier Noriega 690 | Q59: xavier.noriega@group-ips.com | R59: 32-0470740891 | S59: Nee | T59: Team Member | U59: 6 maand(en) | W59: =D59&" "&E59 -> Vincent Verbeke
A60: 26362000041780024 | B60: 45901 | D60: Edwin | E60: Goozen | F60: EGZ | G60: EDG@group-ips.com | H60: edwin.goozen@group-ips.com | I60: IPS Belgium | J60: Same as Payroll Entity | K60: Safety | M60: Senior | N60: Nivelles | O60: Nivelles | P60: Jurgen Van Den Driessche 114 | Q60: jurgen.van.den.driessche@group-ips.com | S60: Nee | T60: Team Member | U60: 6 maand(en) | W60: =D60&" "&E60 -> Edwin Goozen
A61: 26362000041775805 | B61: 45901 | D61: Dhiraj | E61: Kanaujia | F61: DKA | G61: DKA@group-ips.com | H61: dhiraj.kanaujia@group-ips.com | I61: IPS Germany | J61: Same as Payroll Entity | K61: Food & Beverages | M61: Intermediate | N61: Berlin | O61: Berlin | P61: Fiete Heinrich 175 | Q61: fiete.heinrich@group-ips.com | S61: Nee | T61: Team Member | U61: 6 maand(en) | W61: =D61&" "&E61 -> Dhiraj Kanaujia
A62: 26362000041588593 | B62: 45875 | D62: Taha | E62: Elghith | F62: TEL | G62: TEL@group-ips.com | H62: taha.elghith@group-ips.com | I62: IAPS Tunisia | J62: Same as Payroll Entity | K62: Engineering | M62: Senior | N62: Sfax | O62: Sfax | P62: Wissem Bensaid 96 | Q62: wissem.bensaid@group-ips.com | S62: Nee | T62: Team Member | U62: 7 maand(en) | W62: =D62&" "&E62 -> Taha Elghith
A63: 26362000041497214 | B63: 45929 | C63: 46142 | D63: Dorig | E63: Goardou | F63: DOG | G63: DOG@group-ips.com | H63: dorig.goardou@group-ips.com | I63: Group-IPS | J63: Same as Payroll Entity | K63: Corporate Development | M63: Junior | N63: Nivelles | O63: Nivelles | P63: Lucas Joassin 335 | Q63: lucas.joassin@group-ips.com | S63: Nee | T63: Team Member | U63: 5 maand(en) | W63: =D63&" "&E63 -> Dorig Goardou
A64: 26362000041356689 | B64: 45873 | D64: Juan Carlos | E64: Gonzalez Rosario | F64: JCG | G64: JCG@group-ips.com | H64: juancarlos.gonzalez@group-ips.com | I64: IPS Spain | J64: Same as Payroll Entity | K64: Food & Beverages | M64: Intermediate | N64: Barcelona | O64: Barcelona | P64: Paqui Romero 213 | Q64: paqui.romero@group-ips.com | S64: Nee | T64: Team Member | U64: 7 maand(en) | W64: =D64&" "&E64 -> Juan Carlos Gonzalez Rosario
A65: 26362000041304325 | B65: 45859 | D65: Raymond | E65: Mutebi | F65: RAM | G65: RMU@group-ips.com | H65: raymond.mutebi@group-ips.com | I65: IPS USA | J65: Same as Payroll Entity | K65: Project Management | M65: Junior | N65: Philadelphia | O65: Philadelphia | P65: Pranay Pawar 123 | Q65: pranay.pawar@group-ips.com | S65: Nee | T65: Team Member | U65: 7 maand(en) | W65: =D65&" "&E65 -> Raymond Mutebi
A66: 26362000041255013 | B66: 45859 | D66: Daniel | E66: Eso-Oluborode | F66: DEO | G66: DEO@group-ips.com | H66: daniel.eso-oluborode@group-ips.com | I66: IPS UK | J66: IPS USA | K66: Project Management | M66: Junior | N66: Warrington | O66: Warrington | P66: Mac Olean 260 | Q66: mac.o.lean@group-ips.com | R66: 44-7824497220 | S66: Nee | T66: Team Member | U66: 7 maand(en) | W66: =D66&" "&E66 -> Daniel Eso-Oluborode
